Workbook
Name Cod_proy: #REF!
Name Cod_proy: #REF!
Name Giro_Alpin: #REF!
Name Giro_Alpin: #REF!
Name Lider_Nombre: #REF!
Name Lider_Nombre: #REF!
Name Nivel: #REF!
Name Nivel: #REF!
Name Nom_Cl: #REF!
Name Nom_Cl: #REF!
Name tblDatos: OFFSET(#REF!,0,0,COUNTA(#REF!),11)
Name tblDatos: OFFSET(#REF!,0,0,COUNTA(#REF!),11)

Sheet ENERO
C1: CALCULO DE BONOS ENERO
C3: REGION OCCIDENTE
C5: KILOS | E5: Variacion | G5: PESOS | I5: Variacion
B6: MES | C6: Presupuesto | D6: Real | E6: KG | F6: % | G6: Presupuesto | H6: Real | I6: $ | J6: %
B7: ENERO | C7: 143666.11 | D7: 176493.95 | E7: =D7-C7 -> 32827.834 | F7: =D7/C7-1 -> 0.22850088 | G7: 4297825.1 | H7: 4667283 | I7: =H7-G7 -> 369457.84 | J7: =H7/G7-1 -> 0.085963907
B9: COMPOSICION BONO | G9: ALCANCE DE OBJETIVOS
B10: Bono | C10: Concepto | D10: % Bono | E10: Monto | G10: Concepto | H10: Presupuesto | I10: Real | J10: % Cobertura | K10: Bono | M10: Objetivo Minimo
B11: 12000 | C11: Cumplimiento Presupuesto | D11: 0.7 | E11: =B11*D11 -> 8400 | G11: Cumplimiento Presupuesto | H11: =G7 -> 4297825.1 | I11: =H7 -> 4667283 | J11: =IFERROR(I11/H11,0) -> 1.0859639 | K11: =IF(J11<M11,0,J11*$E11) -> 9122.0968 | M11: 0.9
C12: Cierre de 3 pedidos 1000 Kgcon clientes actuales de FMC | D12: 0.12 | E12: =B11*D12 -> 1440 | G12: =C12 -> Cierre de 3 pedidos 1000 Kgcon clientes actuales de FMC | H12: 1 | J12: =I12/H12 -> 0 | K12: =IF(J12<M12,0,J12*$E12) -> 0 | M12: 0.8
C13: Contar con calendario de pruebas inicios de año 2020 | D13: 0.05 | E13: =B$11*D$13 -> 600 | G13: =C13 -> Contar con calendario de pruebas inicios de año 2020 | H13: 1 | J13: =I13/H13 -> 0 | K13: =IF(J13<M13,0,J13*$E13) -> 0 | M13: 1
C14: Presentar estrategica por region Occidente 2020 | D14: 0.05 | E14: =B$11*D$13 -> 600 | G14: =C14 -> Presentar estrategica por region Occidente 2020 | H14: 1 | J14: =I14/H14 -> 0 | K14: =IF(J14<M14,0,J14*$E14) -> 0 | M14: 0.75
C15: Presentar presupuesto lunes 6 de Diciembre | D15: 0.08 | E15: =B11*D15 -> 960 | G15: =C15 -> Presentar presupuesto lunes 6 de Diciembre | H15: 1 | J15: =I15/H15 -> 0 | K15: =IF(J15<M15,0,J15*$E15) -> 0 | M15: 0.75
C16: Total | D16: =SUM(D11:D15) -> 1 | E16: =SUM(E11:E15) -> 12000 | J16: Total sin Presupuesto | K16: =SUM(K12:K15) -> 0
J18: TOTAL | K18: =+K16+K11 -> 9122.0968
C24: REGION PACIFICO
C26: KILOS | E26: Variacion | G26: PESOS | I26: Variacion
B27: MES | C27: Presupuesto | D27: Real | E27: KG | F27: % | G27: Presupuesto | H27: Real | I27: $ | J27: %
B28: =$B$7 -> ENERO | C28: 38799 | D28: 24322.564 | E28: =D28-C28 -> -14476.436 | F28: =D28/C28-1 -> -0.37311364 | G28: 2453010.1 | H28: 1240760.1 | I28: =H28-G28 -> -1212249.9 | J28: =H28/G28-1 -> -0.49418873
B30: COMPOSICION BONO
B31: Bono | C31: Concepto | D31: % Bono | E31: Monto | F31: Objetivo Minimo | G31: Concepto | H31: Presupuesto | I31: Real | J31: % Cobertura | K31: Bono | M31: Objetivo Minimo
B32: 1000 | C32: Cumplimiento Presupuesto | D32: =E32/$B$37 -> 0.15384615 | E32: 1000 | F32: 0.5 | G32: =C32 -> Cumplimiento Presupuesto | H32: =G28 -> 2453010.1 | I32: =H28 -> 1240760.1 | J32: =IFERROR(I32/H32,0) -> 0.50581127 | K32: =IF(J32<M32,0,J32*$E32) -> 505.81127 | M32: 0.5
B33: 1000 | C33: Pruebas atorizadas por realizar con cliente | D33: =E33/$B$37 -> 0.15384615 | E33: 1000 | F33: 1 | G33: =C33 -> Pruebas atorizadas por realizar con cliente | H33: 1 | J33: =IFERROR(I33/H33,0) -> 0 | K33: =IF(J33<M33,0,J33*$E33) -> 0 | M33: 1
B34: 1500 | C34: Armado e implementación estrategia Baja California | D34: =E34/$B$37 -> 0.23076923 | E34: 1500 | F34: 1 | G34: =C34 -> Armado e implementación estrategia Baja California | H34: 1 | J34: =IFERROR(I34/H34,0) -> 0 | K34: =IF(J34<M34,0,J34*$E34) -> 0 | M34: 1
B35: 1500 | C35: Presentar estrategica por región 2020 | D35: =E35/$B$37 -> 0.23076923 | E35: 1500 | F35: 0.75 | G35: =C35 -> Presentar estrategica por región 2020 | H35: 1 | J35: =IFERROR(I35/H35,0) -> 0 | K35: =IF(J35<M35,0,J35*$E35) -> 0 | M35: 0.75
B36: 1500 | C36: Presentar presupuesto lunes 6 de Diciembre | D36: =E36/$B$37 -> 0.23076923 | E36: 1500 | F36: 0.75 | G36: =C36 -> Presentar presupuesto lunes 6 de Diciembre | H36: 1 | J36: =IFERROR(I36/H36,0) -> 0 | K36: =IF(J36<M36,0,J36*$E36) -> 0 | M36: 0.75
B37: =SUM(B32:B36) -> 6500 | C37: Total | E37: =SUM(E31:E36) -> 6500 | J37: Total sin Presupuesto | K37: =SUM(K34:K34) -> 0
J39: TOTAL | K39: =+K37+K32 -> 505.81127
J40: Abono adeudo Marinador
J41: Total a pagar | K41: =+K39-K40 -> 505.81127
C43: REGION BAJIO
C45: KILOS | E45: Variacion | G45: PESOS | I45: Variacion
B46: MES | C46: Presupuesto | D46: Real | E46: KG | F46: % | G46: Presupuesto | H46: Real | I46: $ | J46: %
B47: =$B$7 -> ENERO | C47: 22303.184 | D47: 29864.766 | E47: =D47-C47 -> 7561.5817 | F47: =D47/C47-1 -> 0.33903597 | G47: 1364911.6 | H47: 1383531 | I47: =H47-G47 -> 18619.354 | J47: =H47/G47-1 -> 0.013641435
B49: COMPOSICION BONO | G49: ALCANCE DE OBJETIVOS
B50: Bono | C50: Concepto | D50: % Bono | E50: Monto | G50: Concepto | H50: Presupuesto | I50: Real | J50: % Cobertura | K50: Bono
B51: 7000 | C51: Cumplimiento Presupuesto | D51: 0.5 | E51: =B51*D51 -> 3500 | G51: =C51 -> Cumplimiento Presupuesto | H51: =G47 -> 1364911.6 | I51: =H47 -> 1383531 | J51: =IFERROR(I51/H51,0) -> 1.0136414 | K51: =IF(J51<M52,0,J51*$E51) -> 3547.745 | M51: Objetivo Minimo
C52: Aplicación de pruebas unidades de chorizo | D52: 0.2 | E52: =B51*D52 -> 1400 | G52: =C52 -> Aplicación de pruebas unidades de chorizo | H52: 1 | J52: =IFERROR(I52/H52,0) -> 0 | K52: =IF(J52<M53,0,J52*$E52) -> 0 | M52: 0.95
C53: Prospectación | D53: 0.2 | E53: =B51*D53 -> 1400 | G53: =C53 -> Prospectación | H53: 1 | J53: =IFERROR(I53/H53,0) -> 0 | K53: =IF(J53<M54,0,J53*$E53) -> 0 | M53: 0.75
C54: Cierre de venta con productos nuevos AGR | D54: 0.1 | E54: =+D54*B51 -> 700 | G54: =C54 -> Cierre de venta con productos nuevos AGR | H54: 1 | J54: =IFERROR(I54/H54,0) -> 0 | K54: =IF(J54<M55,0,J54*$E54) -> 0 | M54: 0.75
C55: Total | D55: =SUM(D51:D54) -> 1 | E55: =SUM(E51:E54) -> 7000 | J55: Total sin Presupuesto | K55: =SUM(K52:K54) -> 0 | M55: 0.75
J57: TOTAL | K57: =+K55+K51 -> 3547.745
C61: ALTOS NORTE
C63: KILOS | E63: Variacion | G63: PESOS | I63: Variacion
B64: MES | C64: Presupuesto | D64: Real | E64: KG | F64: % | G64: Presupuesto | H64: Real | I64: $ | J64: %
B65: =$B$7 -> ENERO | C65: 67465.636 | D65: 51324.94 | E65: =D65-C65 -> -16140.696 | F65: =D65/C65-1 -> -0.23924322 | G65: 2234878.4 | H65: 1879387.2 | I65: =H65-G65 -> -355491.18 | J65: =H65/G65-1 -> -0.15906511
B67: COMPOSICION BONO | G67: ALCANCE DE OBJETIVOS
B68: Bono | C68: Concepto | D68: % Bono | E68: Monto | G68: Concepto | H68: Presupuesto | I68: Real | J68: % Cobertura | K68: Bono | M68: Objetivo Minimo
B69: 10000 | C69: Cumplimiento Presupuesto | D69: 0.6 | E69: =+D69*B69 -> 6000 | G69: =C69 -> Cumplimiento Presupuesto | H69: =G65 -> 2234878.4 | I69: =H65 -> 1879387.2 | J69: =IFERROR(I69/H69,0) -> 0.84093489 | K69: =IF(J69<M69,0,J69*$E69) -> 5045.6093 | M69: 0.8
C70: Cierre de 3 pedidos 300 Kgcon clientes actuales de FMC | D70: 0.1 | E70: =B69*D70 -> 1000 | G70: =C70 -> Cierre de 3 pedidos 300 Kgcon clientes actuales de FMC | H70: 1 | J70: =I70/H70 -> 0 | K70: =IF(J70<M70,0,J70*$E70) -> 0 | M70: 0.8
C71: Contar con calendario de pruebas inicios de año 2020 | D71: 0.12 | E71: =+D71*B69 -> 1200 | G71: =C71 -> Contar con calendario de pruebas inicios de año 2020 | H71: 1 | J71: =IFERROR(I71/H71,0) -> 0 | K71: =IF(J71<M71,0,J71*$E71) -> 0 | M71: 1
C72: Presentar estrategica por region 2020 | D72: 0.07 | E72: =+D72*B69 -> 700 | G72: =C72 -> Presentar estrategica por region 2020 | H72: 1 | J72: =IFERROR(I72/H72,0) -> 0 | K72: =IF(J72<M72,0,J72*$E72) -> 0 | M72: 1
C73: Presentar presupuesto lunes 6 de Diciembre | D73: 0.11 | E73: =+D73*B69 -> 1100 | G73: =C73 -> Presentar presupuesto lunes 6 de Diciembre | H73: 1 | J73: =IFERROR(I73/H73,0) -> 0 | K73: =IF(J73<M73,0,J73*$E73) -> 0 | M73: 1
C74: Total | D74: =SUM(D69:D73) -> 1 | E74: =SUM(E69:E73) -> 10000 | J74: Total sin Presupuesto | K74: =SUM(K70:K73) -> 0
J76: TOTAL | K76: =+K74+K69 -> 5045.6093
C80: ATENCION TELEFONICA
C82: KILOS | E82: Variacion | G82: PESOS | I82: Variacion
B83: MES | C83: Presupuesto | D83: Real | E83: KG | F83: % | G83: Presupuesto | H83: Real | I83: $ | J83: %
B84: =$B$7 -> ENERO | C84: 67254.68 | D84: 93055.9 | E84: =D84-C84 -> 25801.22 | F84: =D84/C84-1 -> 0.38363457 | G84: 1864535.6 | H84: 2148268.5 | I84: =H84-G84 -> 283732.96 | J84: =H84/G84-1 -> 0.15217353
B86: COMPOSICION BONO | G86: ALCANCE DE OBJETIVOS
B87: Bono | C87: Concepto | D87: % Bono | E87: Monto | G87: Concepto | H87: Presupuesto | I87: Real | J87: % Cobertura | K87: Bono | M87: Objetivo Minimo
C88: Cumplimiento Presupuesto | D88: 0.6 | E88: =+D88*B88 -> 0 | G88: =C88 -> Cumplimiento Presupuesto | H88: =G84 -> 1864535.6 | I88: =H84 -> 2148268.5 | J88: =IFERROR(I88/H88,0) -> 1.1521735 | K88: =IF(J88<M88,0,J88*$E88) -> 0 | M88: 0.8
D89: 0.1 | E89: =B88*D89 -> 0 | G89: =C89 -> 0 | H89: 1 | J89: =I89/H89 -> 0 | K89: =IF(J89<M89,0,J89*$E89) -> 0 | M89: 0.8
D90: 0.12 | E90: =+D90*B88 -> 0 | G90: =C90 -> 0 | H90: 1 | J90: =IFERROR(I90/H90,0) -> 0 | K90: =IF(J90<M90,0,J90*$E90) -> 0 | M90: 1
D91: 0.07 | E91: =+D91*B88 -> 0 | G91: =C91 -> 0 | H91: 1 | J91: =IFERROR(I91/H91,0) -> 0 | K91: =IF(J91<M91,0,J91*$E91) -> 0 | M91: 1
D92: 0.11 | E92: =+D92*B88 -> 0 | G92: =C92 -> 0 | H92: 1 | J92: =IFERROR(I92/H92,0) -> 0 | K92: =IF(J92<M92,0,J92*$E92) -> 0 | M92: 1
C93: Total | D93: =SUM(D88:D92) -> 1 | E93: =SUM(E88:E92) -> 0 | J93: Total sin Presupuesto | K93: =SUM(K89:K92) -> 0
J95: TOTAL | K95: =+K93+K88 -> 0
N170: 3 | O170: 3.1 | P170: =+O170-N170 -> 0.1 | Q170: =+P170/O170 -> 0.032258065
P174: =2000*3*12 -> 72000
P177: =2000*12 -> 24000

Sheet FEBRERO
C1: CALCULO DE BONOS FEBRERO
C3: REGION OCCIDENTE
C5: KILOS | E5: Variacion | G5: PESOS | I5: Variacion
B6: MES | C6: Presupuesto | D6: Real | E6: KG | F6: % | G6: Presupuesto | H6: Real | I6: $ | J6: %
B7: FEBRERO | C7: ='ESSENTIA FEB'!O27 -> 149031.37 | D7: ='ESSENTIA FEB'!N27 -> 134310.4 | E7: =D7-C7 -> -14720.97 | F7: =D7/C7-1 -> -0.098777655 | G7: ='ESSENTIA FEB'!G27 -> 4256404.4 | H7: ='ESSENTIA FEB'!F27 -> 3799747.9 | I7: =H7-G7 -> -456656.47 | J7: =H7/G7-1 -> -0.10728691
B9: COMPOSICION BONO | G9: ALCANCE DE OBJETIVOS
B10: Bono | C10: Concepto | D10: % Bono | E10: Monto | G10: Concepto | H10: Presupuesto | I10: Real | J10: % Cobertura | K10: Bono | M10: Objetivo Minimo
B11: 12000 | C11: Cumplimiento Presupuesto | D11: 0.7 | E11: =B11*D11 -> 8400 | G11: Cumplimiento Presupuesto | H11: =G7 -> 4256404.4 | I11: =H7 -> 3799747.9 | J11: =IFERROR(I11/H11,0) -> 0.89271309 | K11: =IF(J11<M11,0,J11*$E11) -> 0 | M11: 0.9
C12: Cierre de 3 pedidos 1000 Kgcon clientes actuales de FMC | D12: 0.12 | E12: =B11*D12 -> 1440 | G12: =C12 -> Cierre de 3 pedidos 1000 Kgcon clientes actuales de FMC | H12: 1 | J12: =I12/H12 -> 0 | K12: =IF(J12<M12,0,J12*$E12) -> 0 | M12: 0.8
C13: Contar con calendario de pruebas inicios de año 2020 | D13: 0.05 | E13: =B$11*D$13 -> 600 | G13: =C13 -> Contar con calendario de pruebas inicios de año 2020 | H13: 1 | J13: =I13/H13 -> 0 | K13: =IF(J13<M13,0,J13*$E13) -> 0 | M13: 1
C14: Presentar estrategica por region Occidente 2020 | D14: 0.05 | E14: =B$11*D$13 -> 600 | G14: =C14 -> Presentar estrategica por region Occidente 2020 | H14: 1 | J14: =I14/H14 -> 0 | K14: =IF(J14<M14,0,J14*$E14) -> 0 | M14: 0.75
C15: Presentar presupuesto lunes 6 de Diciembre | D15: 0.08 | E15: =B11*D15 -> 960 | G15: =C15 -> Presentar presupuesto lunes 6 de Diciembre | H15: 1 | J15: =I15/H15 -> 0 | K15: =IF(J15<M15,0,J15*$E15) -> 0 | M15: 0.75
C16: Total | D16: =SUM(D11:D15) -> 1 | E16: =SUM(E11:E15) -> 12000 | J16: Total sin Presupuesto | K16: =SUM(K12:K15) -> 0
J18: TOTAL | K18: =+K16+K11 -> 0
C24: REGION PACIFICO
C26: KILOS | E26: Variacion | G26: PESOS | I26: Variacion
B27: MES | C27: Presupuesto | D27: Real | E27: KG | F27: % | G27: Presupuesto | H27: Real | I27: $ | J27: %
B28: =$B$7 -> FEBRERO | C28: ='ESSENTIA FEB'!O28 -> 34839 | D28: ='ESSENTIA FEB'!N28 -> 29580.708 | E28: =D28-C28 -> -5258.2921 | F28: =D28/C28-1 -> -0.1509312 | G28: ='ESSENTIA FEB'!G28 -> 2205545.3 | H28: ='ESSENTIA FEB'!F28 -> 2144834.8 | I28: =H28-G28 -> -60710.488 | J28: =H28/G28-1 -> -0.027526294
B30: COMPOSICION BONO
B31: Bono | C31: Concepto | D31: % Bono | E31: Monto | F31: Objetivo Minimo | G31: Concepto | H31: Presupuesto | I31: Real | J31: % Cobertura | K31: Bono | M31: Objetivo Minimo
B32: 1000 | C32: Cumplimiento Presupuesto | D32: =E32/$B$37 -> 0.15384615 | E32: 1000 | F32: 0.5 | G32: =C32 -> Cumplimiento Presupuesto | H32: =G28 -> 2205545.3 | I32: =H28 -> 2144834.8 | J32: =IFERROR(I32/H32,0) -> 0.97247371 | K32: =IF(J32<M32,0,J32*$E32) -> 972.47371 | M32: 0.5
B33: 1000 | C33: Pruebas atorizadas por realizar con cliente | D33: =E33/$B$37 -> 0.15384615 | E33: 1000 | F33: 1 | G33: =C33 -> Pruebas atorizadas por realizar con cliente | H33: 1 | J33: =IFERROR(I33/H33,0) -> 0 | K33: =IF(J33<M33,0,J33*$E33) -> 0 | M33: 1
B34: 1500 | C34: Armado e implementación estrategia Baja California | D34: =E34/$B$37 -> 0.23076923 | E34: 1500 | F34: 1 | G34: =C34 -> Armado e implementación estrategia Baja California | H34: 1 | J34: =IFERROR(I34/H34,0) -> 0 | K34: =IF(J34<M34,0,J34*$E34) -> 0 | M34: 1
B35: 1500 | C35: Presentar estrategica por región 2020 | D35: =E35/$B$37 -> 0.23076923 | E35: 1500 | F35: 0.75 | G35: =C35 -> Presentar estrategica por región 2020 | H35: 1 | J35: =IFERROR(I35/H35,0) -> 0 | K35: =IF(J35<M35,0,J35*$E35) -> 0 | M35: 0.75
B36: 1500 | C36: Presentar presupuesto lunes 6 de Diciembre | D36: =E36/$B$37 -> 0.23076923 | E36: 1500 | F36: 0.75 | G36: =C36 -> Presentar presupuesto lunes 6 de Diciembre | H36: 1 | J36: =IFERROR(I36/H36,0) -> 0 | K36: =IF(J36<M36,0,J36*$E36) -> 0 | M36: 0.75
B37: =SUM(B32:B36) -> 6500 | C37: Total | E37: =SUM(E31:E36) -> 6500 | J37: Total sin Presupuesto | K37: =SUM(K34:K34) -> 0
J39: TOTAL | K39: =+K37+K32 -> 972.47371
C43: REGION BAJIO
C45: KILOS | E45: Variacion | G45: PESOS | I45: Variacion
B46: MES | C46: Presupuesto | D46: Real | E46: KG | F46: % | G46: Presupuesto | H46: Real | I46: $ | J46: %
B47: =$B$7 -> FEBRERO | C47: ='ESSENTIA FEB'!O32 -> 24032.929 | D47: ='ESSENTIA FEB'!N32 -> 27953.524 | E47: =D47-C47 -> 3920.5948 | F47: =D47/C47-1 -> 0.16313429 | G47: ='ESSENTIA FEB'!G32 -> 1288812.4 | H47: ='ESSENTIA FEB'!F32 -> 1575484.4 | I47: =H47-G47 -> 286672.1 | J47: =H47/G47-1 -> 0.22243122
B49: COMPOSICION BONO | G49: ALCANCE DE OBJETIVOS
B50: Bono | C50: Concepto | D50: % Bono | E50: Monto | G50: Concepto | H50: Presupuesto | I50: Real | J50: % Cobertura | K50: Bono
B51: 7000 | C51: Cumplimiento Presupuesto | D51: 0.5 | E51: =B51*D51 -> 3500 | G51: =C51 -> Cumplimiento Presupuesto | H51: =G47 -> 1288812.4 | I51: =H47 -> 1575484.4 | J51: =IFERROR(I51/H51,0) -> 1.2224312 | K51: =IF(J51<M52,0,J51*$E51) -> 4278.5093 | M51: Objetivo Minimo
C52: Aplicación de pruebas unidades de chorizo | D52: 0.2 | E52: =B51*D52 -> 1400 | G52: =C52 -> Aplicación de pruebas unidades de chorizo | H52: 1 | J52: =IFERROR(I52/H52,0) -> 0 | K52: =IF(J52<M53,0,J52*$E52) -> 0 | M52: 0.95
C53: Prospectación | D53: 0.2 | E53: =B51*D53 -> 1400 | G53: =C53 -> Prospectación | H53: 1 | J53: =IFERROR(I53/H53,0) -> 0 | K53: =IF(J53<M54,0,J53*$E53) -> 0 | M53: 0.75
C54: Cierre de venta con productos nuevos AGR | D54: 0.1 | E54: =+D54*B51 -> 700 | G54: =C54 -> Cierre de venta con productos nuevos AGR | H54: 1 | J54: =IFERROR(I54/H54,0) -> 0 | K54: =IF(J54<M55,0,J54*$E54) -> 0 | M54: 0.75
C55: Total | D55: =SUM(D51:D54) -> 1 | E55: =SUM(E51:E54) -> 7000 | J55: Total sin Presupuesto | K55: =SUM(K52:K54) -> 0 | M55: 0.75
J57: TOTAL | K57: =+K55+K51 -> 4278.5093
C61: ALTOS NORTE
C63: KILOS | E63: Variacion | G63: PESOS | I63: Variacion
B64: MES | C64: Presupuesto | D64: Real | E64: KG | F64: % | G64: Presupuesto | H64: Real | I64: $ | J64: %
B65: =$B$7 -> FEBRERO | C65: ='ESSENTIA FEB'!O31 -> 92409.672 | D65: ='ESSENTIA FEB'!N31 -> 71398.03 | E65: =D65-C65 -> -21011.642 | F65: =D65/C65-1 -> -0.22737492 | G65: ='ESSENTIA FEB'!G31 -> 2361039.8 | H65: ='ESSENTIA FEB'!F31 -> 2450819.7 | I65: =H65-G65 -> 89779.906 | J65: =H65/G65-1 -> 0.038025579
B67: COMPOSICION BONO | G67: ALCANCE DE OBJETIVOS
B68: Bono | C68: Concepto | D68: % Bono | E68: Monto | G68: Concepto | H68: Presupuesto | I68: Real | J68: % Cobertura | K68: Bono | M68: Objetivo Minimo
B69: 10000 | C69: Cumplimiento Presupuesto | D69: 0.6 | E69: =+D69*B69 -> 6000 | G69: =C69 -> Cumplimiento Presupuesto | H69: =G65 -> 2361039.8 | I69: =H65 -> 2450819.7 | J69: =IFERROR(I69/H69,0) -> 1.0380256 | K69: =IF(J69<M69,0,J69*$E69) -> 6228.1535 | M69: 0.8
C70: Cierre de 3 pedidos 300 Kgcon clientes actuales de FMC | D70: 0.1 | E70: =B69*D70 -> 1000 | G70: =C70 -> Cierre de 3 pedidos 300 Kgcon clientes actuales de FMC | H70: 1 | J70: =I70/H70 -> 0 | K70: =IF(J70<M70,0,J70*$E70) -> 0 | M70: 0.8
C71: Contar con calendario de pruebas inicios de año 2020 | D71: 0.12 | E71: =+D71*B69 -> 1200 | G71: =C71 -> Contar con calendario de pruebas inicios de año 2020 | H71: 1 | J71: =IFERROR(I71/H71,0) -> 0 | K71: =IF(J71<M71,0,J71*$E71) -> 0 | M71: 1
C72: Presentar estrategica por region 2020 | D72: 0.07 | E72: =+D72*B69 -> 700 | G72: =C72 -> Presentar estrategica por region 2020 | H72: 1 | J72: =IFERROR(I72/H72,0) -> 0 | K72: =IF(J72<M72,0,J72*$E72) -> 0 | M72: 1
C73: Presentar presupuesto lunes 6 de Diciembre | D73: 0.11 | E73: =+D73*B69 -> 1100 | G73: =C73 -> Presentar presupuesto lunes 6 de Diciembre | H73: 1 | J73: =IFERROR(I73/H73,0) -> 0 | K73: =IF(J73<M73,0,J73*$E73) -> 0 | M73: 1
C74: Total | D74: =SUM(D69:D73) -> 1 | E74: =SUM(E69:E73) -> 10000 | J74: Total sin Presupuesto | K74: =SUM(K70:K73) -> 0
J76: TOTAL | K76: =+K74+K69 -> 6228.1535
C80: COORDINACION DE VENTAS
C82: KILOS | E82: Variacion | G82: PESOS | I82: Variacion
B83: MES | C83: Presupuesto | D83: Real | E83: KG | F83: % | G83: Presupuesto | H83: Real | I83: $ | J83: %
B84: =$B$7 -> FEBRERO | C84: ='ESSENTIA FEB'!O29 -> 71343.08 | D84: ='ESSENTIA FEB'!N29 -> 49576.13 | E84: =D84-C84 -> -21766.95 | F84: =D84/C84-1 -> -0.30510247 | G84: ='ESSENTIA FEB'!G29 -> 2132270.3 | H84: ='ESSENTIA FEB'!F29 -> 1586907 | I84: =H84-G84 -> -545363.33 | J84: =H84/G84-1 -> -0.25576651
B86: COMPOSICION BONO | G86: ALCANCE DE OBJETIVOS
B87: Bono | C87: Concepto | D87: % Bono | E87: Monto | G87: Concepto | H87: Presupuesto | I87: Real | J87: % Cobertura | K87: Bono | M87: Objetivo Minimo
C88: Cumplimiento Presupuesto | D88: 1 | E88: =+D88*B88 -> 0 | G88: =C88 -> Cumplimiento Presupuesto | H88: =G84 -> 2132270.3 | I88: =H84 -> 1586907 | J88: =IFERROR(I88/H88,0) -> 0.74423349 | K88: =IF(J88<M88,0,J88*$E88) -> 0 | M88: 0.8
E89: =B88*D89 -> 0 | G89: =C89 -> 0 | H89: 1 | J89: =I89/H89 -> 0 | K89: =IF(J89<M89,0,J89*$E89) -> 0 | M89: 0.8
E90: =+D90*B88 -> 0 | G90: =C90 -> 0 | H90: 1 | J90: =IFERROR(I90/H90,0) -> 0 | K90: =IF(J90<M90,0,J90*$E90) -> 0 | M90: 1
E91: =+D91*B88 -> 0 | G91: =C91 -> 0 | H91: 1 | J91: =IFERROR(I91/H91,0) -> 0 | K91: =IF(J91<M91,0,J91*$E91) -> 0 | M91: 1
E92: =+D92*B88 -> 0 | G92: =C92 -> 0 | H92: 1 | J92: =IFERROR(I92/H92,0) -> 0 | K92: =IF(J92<M92,0,J92*$E92) -> 0 | M92: 1
C93: Total | D93: =SUM(D88:D92) -> 1 | E93: =SUM(E88:E92) -> 0 | J93: Total sin Presupuesto | K93: =SUM(K89:K92) -> 0
J95: TOTAL | K95: =+K93+K88 -> 0
N170: 3 | O170: 3.1 | P170: =+O170-N170 -> 0.1 | Q170: =+P170/O170 -> 0.032258065
P174: =2000*3*12 -> 72000
P177: =2000*12 -> 24000

Sheet ESSENTIA FEB
E3: PRESUPUESTO ORIGINAL | F3: Importes | N3: Kilogramos
D4: Clave | E4: Region | F4: 2020 | G4: Pres | H4: Dif | I4: % Inc | J4: 2019 | K4: Dif | L4: % Inc | N4: 2020 | O4: Pres | P4: Dif | Q4: % Inc | R4: 2019 | S4: Dif | T4: % Inc
D5: 1 | E5: Occidente | F5: 3799747.9 | G5: 4354552.4 | H5: =F5-G5 -> -554804.51 | I5: =IFERROR(F5/G5-1,0) -> -0.12740793 | J5: 5433696.7 | K5: =F5-J5 -> -1633948.8 | L5: =IFERROR(F5/J5-1,0) -> -0.30070666 | N5: 134310.4 | O5: 149514.37 | P5: =N5-O5 -> -15203.97 | Q5: =IFERROR(N5/O5-1,0) -> -0.10168902 | R5: 169472.67 | S5: =N5-R5 -> -35162.266 | T5: =IFERROR(N5/R5-1,0) -> -0.20748045
D6: 2 | E6: Pacifico | F6: 2144834.8 | G6: 2211391.5 | H6: =F6-G6 -> -66556.678 | I6: =IFERROR(F6/G6-1,0) -> -0.030097193 | J6: 4367621 | K6: =F6-J6 -> -2222786.1 | L6: =IFERROR(F6/J6-1,0) -> -0.50892377 | N6: 29580.708 | O6: 34859 | P6: =N6-O6 -> -5278.2921 | Q6: =IFERROR(N6/O6-1,0) -> -0.15141835 | R6: 81065.497 | S6: =N6-R6 -> -51484.789 | T6: =IFERROR(N6/R6-1,0) -> -0.63510113
D7: 3 | E7: Servicio al cliente | F7: 1586907 | G7: 2163659.5 | H7: =F7-G7 -> -576752.48 | I7: =IFERROR(F7/G7-1,0) -> -0.26656343 | J7: 1522760.3 | K7: =F7-J7 -> 64146.7 | L7: =IFERROR(F7/J7-1,0) -> 0.042125278 | N7: 49576.13 | O7: 71475.08 | P7: =N7-O7 -> -21898.95 | Q7: =IFERROR(N7/O7-1,0) -> -0.30638581 | R7: 47484.45 | S7: =N7-R7 -> 2091.6803 | T7: =IFERROR(N7/R7-1,0) -> 0.044049796
D8: 5 | E8: Mexico | F8: 121042.57 | G8: 114742.17 | H8: =F8-G8 -> 6300.397 | I8: =IFERROR(F8/G8-1,0) -> 0.054909166 | J8: 134134.86 | K8: =F8-J8 -> -13092.29 | L8: =IFERROR(F8/J8-1,0) -> -0.097605425 | N8: 150 | O8: 130 | P8: =N8-O8 -> 20 | Q8: =IFERROR(N8/O8-1,0) -> 0.15384615 | R8: 160 | S8: =N8-R8 -> -10 | T8: =IFERROR(N8/R8-1,0) -> -0.0625
D9: 6 | E9: Altos Norte | F9: 2450819.7 | G9: 2431461.7 | H9: =F9-G9 -> 19358.026 | I9: =IFERROR(F9/G9-1,0) -> 0.007961477 | J9: 2822915.1 | K9: =F9-J9 -> -372095.36 | L9: =IFERROR(F9/J9-1,0) -> -0.13181245 | N9: 71398.03 | O9: 92726.672 | P9: =N9-O9 -> -21328.642 | Q9: =IFERROR(N9/O9-1,0) -> -0.23001626 | R9: 96533.346 | S9: =N9-R9 -> -25135.316 | T9: =IFERROR(N9/R9-1,0) -> -0.26037962
D10: 7 | E10: Bajio | F10: 1575484.4 | G10: 1300918.2 | H10: =F10-G10 -> 274566.21 | I10: =IFERROR(F10/G10-1,0) -> 0.2110557 | J10: 1228581.4 | K10: =F10-J10 -> 346903.07 | L10: =IFERROR(F10/J10-1,0) -> 0.28236068 | N10: 27953.524 | O10: 24074.929 | P10: =N10-O10 -> 3878.5948 | Q10: =IFERROR(N10/O10-1,0) -> 0.16110514 | R10: 22928.504 | S10: =N10-R10 -> 5025.02 | T10: =IFERROR(N10/R10-1,0) -> 0.2191604
F11: =SUM(F5:F10) -> 11678836 | G11: =SUM(G5:G10) -> 12576726 | H11: =F11-G11 -> -897889.04 | I11: =IFERROR(F11/G11-1,0) -> -0.071392911 | J11: =SUM(J5:J10) -> 15509709 | K11: =F11-J11 -> -3830872.8 | L11: =IFERROR(F11/J11-1,0) -> -0.24699836 | N11: =SUM(N5:N10) -> 312968.8 | O11: =SUM(O5:O10) -> 372780.05 | P11: =N11-O11 -> -59811.259 | Q11: =IFERROR(N11/O11-1,0) -> -0.16044651 | R11: =SUM(R5:R10) -> 417644.47 | S11: =N11-R11 -> -104675.67 | T11: =IFERROR(N11/R11-1,0) -> -0.25063344
E14: PERDIDA VENTA ESSENTIA | F14: Importes | N14: Kilogramos
D15: Clave | E15: Region | F15: 2020 | G15: Pres | H15: Dif | I15: % Inc | J15: 2019 | K15: Dif | L15: % Inc | N15: 2020 | O15: Pres | P15: Dif | Q15: % Inc | R15: 2019 | S15: Dif | T15: % Inc
D16: 1 | E16: Occidente | G16: =L40+L41+L42+L43+L44+L45+L46+L47 -> -98148.039 | O16: =H40+H41+H42+H43+H44+H45+H46+H47 -> -483
D17: 2 | E17: Pacifico | G17: =L58 -> -5846.19 | O17: =H58 -> -20
D18: 3 | E18: Servicio al cliente | G18: =L66+L67+L68+L69+L70+L71 -> -31389.151 | O18: =H66+H67+H68+H69+H70+H71 -> -132
D19: 5 | E19: Mexico
D20: 6 | E20: Altos Norte | G20: =L80+L81+L82+L83+L84+L85+L86 -> -70421.879 | O20: =H80+H81+H82+H83+H84+H85 -> -317
D21: 7 | E21: Bajio | G21: =L95 -> -12105.891 | O21: =H95 -> -42
F22: =SUM(F16:F21) -> 0 | G22: =SUM(G16:G21) -> -217911.15 | H22: =F22-G22 -> 217911.15 | I22: =IFERROR(F22/G22-1,0) -> -1 | J22: =SUM(J16:J21) -> 0 | K22: =F22-J22 -> 0 | L22: =IFERROR(F22/J22-1,0) -> 0 | N22: =SUM(N16:N21) -> 0 | O22: =SUM(O16:O21) -> -994 | P22: =N22-O22 -> 994 | Q22: =IFERROR(N22/O22-1,0) -> -1 | R22: =SUM(R16:R21) -> 0 | S22: =N22-R22 -> 0 | T22: =IFERROR(N22/R22-1,0) -> 0
E25: PRESUPUESTO MODIFICADO | F25: Importes | N25: Kilogramos
D26: Clave | E26: Region | F26: 2020 | G26: Pres | H26: Dif | I26: % Inc | J26: 2019 | K26: Dif | L26: % Inc | N26: 2020 | O26: Pres | P26: Dif | Q26: % Inc | R26: 2019 | S26: Dif | T26: % Inc
D27: 1 | E27: Occidente | F27: 3799747.9 | G27: =G5+G16 -> 4256404.4 | H27: =F27-G27 -> -456656.47 | I27: =IFERROR(F27/G27-1,0) -> -0.10728691 | J27: 5433696.7 | K27: =F27-J27 -> -1633948.8 | L27: =IFERROR(F27/J27-1,0) -> -0.30070666 | N27: 134310.4 | O27: =O5+O16 -> 149031.37 | P27: =N27-O27 -> -14720.97 | Q27: =IFERROR(N27/O27-1,0) -> -0.098777655 | R27: 169472.67 | S27: =N27-R27 -> -35162.266 | T27: =IFERROR(N27/R27-1,0) -> -0.20748045
D28: 2 | E28: Pacifico | F28: 2144834.8 | G28: =G6+G17 -> 2205545.3 | H28: =F28-G28 -> -60710.488 | I28: =IFERROR(F28/G28-1,0) -> -0.027526294 | J28: 4367621 | K28: =F28-J28 -> -2222786.1 | L28: =IFERROR(F28/J28-1,0) -> -0.50892377 | N28: 29580.708 | O28: =O6+O17 -> 34839 | P28: =N28-O28 -> -5258.2921 | Q28: =IFERROR(N28/O28-1,0) -> -0.1509312 | R28: 81065.497 | S28: =N28-R28 -> -51484.789 | T28: =IFERROR(N28/R28-1,0) -> -0.63510113
D29: 3 | E29: Servicio al cliente | F29: 1586907 | G29: =G7+G18 -> 2132270.3 | H29: =F29-G29 -> -545363.33 | I29: =IFERROR(F29/G29-1,0) -> -0.25576651 | J29: 1522760.3 | K29: =F29-J29 -> 64146.7 | L29: =IFERROR(F29/J29-1,0) -> 0.042125278 | N29: 49576.13 | O29: =O7+O18 -> 71343.08 | P29: =N29-O29 -> -21766.95 | Q29: =IFERROR(N29/O29-1,0) -> -0.30510247 | R29: 47484.45 | S29: =N29-R29 -> 2091.6803 | T29: =IFERROR(N29/R29-1,0) -> 0.044049796
D30: 5 | E30: Mexico | F30: 121042.57 | G30: =G8+G19 -> 114742.17 | H30: =F30-G30 -> 6300.397 | I30: =IFERROR(F30/G30-1,0) -> 0.054909166 | J30: 134134.86 | K30: =F30-J30 -> -13092.29 | L30: =IFERROR(F30/J30-1,0) -> -0.097605425 | N30: 150 | O30: =O8+O19 -> 130 | P30: =N30-O30 -> 20 | Q30: =IFERROR(N30/O30-1,0) -> 0.15384615 | R30: 160 | S30: =N30-R30 -> -10 | T30: =IFERROR(N30/R30-1,0) -> -0.0625
D31: 6 | E31: Altos Norte | F31: 2450819.7 | G31: =G9+G20 -> 2361039.8 | H31: =F31-G31 -> 89779.906 | I31: =IFERROR(F31/G31-1,0) -> 0.038025579 | J31: 2822915.1 | K31: =F31-J31 -> -372095.36 | L31: =IFERROR(F31/J31-1,0) -> -0.13181245 | N31: 71398.03 | O31: =O9+O20 -> 92409.672 | P31: =N31-O31 -> -21011.642 | Q31: =IFERROR(N31/O31-1,0) -> -0.22737492 | R31: 96533.346 | S31: =N31-R31 -> -25135.316 | T31: =IFERROR(N31/R31-1,0) -> -0.26037962
D32: 7 | E32: Bajio | F32: 1575484.4 | G32: =G10+G21 -> 1288812.4 | H32: =F32-G32 -> 286672.1 | I32: =IFERROR(F32/G32-1,0) -> 0.22243122 | J32: 1228581.4 | K32: =F32-J32 -> 346903.07 | L32: =IFERROR(F32/J32-1,0) -> 0.28236068 | N32: 27953.524 | O32: =O10+O21 -> 24032.929 | P32: =N32-O32 -> 3920.5948 | Q32: =IFERROR(N32/O32-1,0) -> 0.16313429 | R32: 22928.504 | S32: =N32-R32 -> 5025.02 | T32: =IFERROR(N32/R32-1,0) -> 0.2191604
F33: =SUM(F27:F32) -> 11678836 | G33: =SUM(G27:G32) -> 12358814 | H33: =F33-G33 -> -679977.89 | I33: =IFERROR(F33/G33-1,0) -> -0.05501967 | J33: =SUM(J27:J32) -> 15509709 | K33: =F33-J33 -> -3830872.8 | L33: =IFERROR(F33/J33-1,0) -> -0.24699836 | N33: =SUM(N27:N32) -> 312968.8 | O33: =SUM(O27:O32) -> 371786.05 | P33: =N33-O33 -> -58817.259 | Q33: =IFERROR(N33/O33-1,0) -> -0.1582019 | R33: =SUM(R27:R32) -> 417644.47 | S33: =N33-R33 -> -104675.67 | T33: =IFERROR(N33/R33-1,0) -> -0.25063344
F37: FEBRERO
C38: OCCIDENTE | F38: KILOS | J38: PESOS
A39: Vend | B39: Cte | C39: Nombre | D39: Código | E39: Descripcion | F39: Pres | G39: 2020 | H39: DIF | I39: % | J39: Pres | K39: 2020 | L39: DIF | M39: %
A40: 1 | B40: 327 | C40: EMPACADORAS UNIDAS DE LA PIEDAD SA DE CV | D40: PRO5500 | E40: APROPORK BOL 25 Kg | F40: 288.75 | G40: 40 | H40: -248.75 | I40: -0.86147186 | J40: 37349.668 | K40: 4732.22 | L40: -32617.448 | M40: -0.87329954
A41: 1 | B41: 481 | C41: GRUPO BRAVO NUÑO S.C. DE R.L. DE C.V. | D41: PROAPR | E41: APRORED BOLSA 1KG | F41: 84 | G41: 0 | H41: -84 | I41: -1 | J41: 21388.5 | K41: 0 | L41: -21388.5 | M41: -1
A42: 1 | B42: 313 | C42: CARNES FINAS DE LA SIERRA SA DE CV | D42: PROAPR | E42: APRORED BOLSA 1KG | F42: 42 | G42: 0 | H42: -42 | I42: -1 | J42: 12276.999 | K42: 0 | L42: -12276.999 | M42: -1
A43: 1 | B43: 485 | C43: PRODUCTOS EL GRAN CHAPARRAL SA DE CV | D43: PROAPR | E43: APRORED BOLSA 1KG | F43: 42 | G43: 0 | H43: -42 | I43: -1 | J43: 12276.999 | K43: 0 | L43: -12276.999 | M43: -1
A44: 1 | B44: 657 | C44: HECTOR ALONSO ZARATE QUIROZ | D44: PROAPR | E44: APRORED BOLSA 1KG | F44: 31.5 | G44: 0 | H44: -31.5 | I44: -1 | J44: 9207.7493 | K44: 0 | L44: -9207.7493 | M44: -1
A45: 1 | B45: 038 | C45: EMPACADORA BONNACARNE SA DE CV | D45: PROAPR | E45: APRORED BOLSA 1KG | F45: 21 | G45: 0 | H45: -21 | I45: -1 | J45: 6288.219 | K45: 0 | L45: -6288.219 | M45: -1
A46: 1 | B46: 009 | C46: EMPACADORA EL CENTENARIO, SA DE CV | D46: PROAPR | E46: APRORED BOLSA 1KG | F46: 10.5 | G46: 0 | H46: -10.5 | I46: -1 | J46: 3069.2497 | K46: 0 | L46: -3069.2497 | M46: -1
A47: 1 | B47: 476 | C47: OMEX ALIMENTARIA SA DE CV | D47: PROAPR | E47: APRORED BOLSA 1KG | F47: 5.25 | G47: 2 | H47: -3.25 | I47: -0.61904762 | J47: 1572.0548 | K47: 549.18 | L47: -1022.8747 | M47: -0.65066102
A48: 1 | B48: 038 | C48: EMPACADORA BONNACARNE SA DE CV | D48: PROAPR10 | E48: COM0213 APRORED BOLSA 10KG | F48: 0 | G48: 2.15 | H48: 2.15 | I48: 0 | J48: 0 | K48: 604.37 | L48: 604.37 | M48: 0
A49: 1 | B49: 476 | C49: OMEX ALIMENTARIA SA DE CV | D49: PROAPR10 | E49: COM0213 APRORED BOLSA 10KG | F49: 0 | G49: 10 | H49: 10 | I49: 0 | J49: 0 | K49: 2740.93 | L49: 2740.93 | M49: 0
A50: 1 | B50: 009 | C50: EMPACADORA EL CENTENARIO, SA DE CV | D50: PRO5500 | E50: APROPORK BOL 25 Kg | F50: 630 | G50: 780 | H50: 150 | I50: 0.23809524 | J50: 83415.15 | K50: 95060.03 | L50: 11644.88 | M50: 0.1396015
F51: =SUM(F40:F50) -> 1155 | G51: =SUM(G40:G50) -> 834.15 | H51: =SUM(H40:H50) -> -320.85 | I51: =H51/F51 -> -0.27779221 | J51: =SUM(J40:J50) -> 186844.59 | K51: =SUM(K40:K50) -> 103686.73 | L51: =SUM(L40:L50) -> -83157.859 | M51: =L51/J51 -> -0.44506431
F55: FEBRERO
C56: PACIFICO | F56: KILOS | J56: PESOS
A57: Vend | B57: Cte | C57: Nombre | D57: Código | E57: Descripcion | F57: Pres | G57: 2020 | H57: DIF | I57: % | J57: Pres | K57: 2020 | L57: DIF | M57: %
A58: 2 | B58: 012 | C58: KAREY ALIMENTOS, SA DE CV | D58: PROAPR | E58: APRORED BOLSA 1KG | F58: 20 | G58: 0 | H58: -20 | I58: -1 | J58: 5846.19 | K58: 0 | L58: -5846.19 | M58: -1
F59: =SUM(F58) -> 20 | G59: =SUM(G58) -> 0 | H59: =SUM(H58) -> -20 | I59: =H59/F59 -> -1 | J59: =SUM(J58) -> 5846.19 | K59: =SUM(K58) -> 0 | L59: =SUM(L58) -> -5846.19 | M59: =L59/J59 -> -1
F63: FEBRERO
C64: COORDINADORA DE VENTAS | F64: KILOS | J64: PESOS
A65: Vend | B65: Cte | C65: Nombre | D65: Código | E65: Descripcion | F65: Pres | G65: 2020 | H65: DIF | I65: % | J65: Pres | K65: 2020 | L65: DIF | M65: %
A66: 3 | B66: 654 | C66: LUIS ALBERTO MACHAIN GONZALEZ | D66: PROAPR | E66: APRORED BOLSA 1KG | F66: 40 | G66: 0 | H66: -40 | I66: -1 | J66: 11692.38 | K66: 0 | L66: -11692.38 | M66: -1
A67: 3 | B67: 601 | C67: VILLESPA, SPR DE RL | D67: PROAPR | E67: APRORED BOLSA 1KG | F67: 40 | G67: 0 | H67: -40 | I67: -1 | J67: 11692.38 | K67: 0 | L67: -11692.38 | M67: -1
A68: 3 | B68: 714 | C68: Cooperativa de produccion pesquera el palacio, SC de RL | D68: PRO5500 | E68: APROPORK BOL 25 Kg | F68: 25 | G68: 0 | H68: -25 | I68: -1 | J68: 3310.125 | K68: 0 | L68: -3310.125 | M68: -1
A69: 3 | B69: 103 | C69: MARIA ESTHER JAUREGUI VELASCO | D69: PRO5500 | E69: APROPORK BOL 20 Kg | F69: 20 | G69: 0 | H69: -20 | I69: -1 | J69: 2648.1 | K69: 0 | L69: -2648.1 | M69: -1
A70: 3 | B70: 518 | C70: INTEGRADORA PECUARIA GURMA S.P.R. DE R.L. DE C.V. | D70: PROAPR | E70: APRORED BOLSA 1KG | F70: 5 | G70: 0 | H70: -5 | I70: -1 | J70: 1461.5475 | K70: 0 | L70: -1461.5475 | M70: -1
A71: 3 | B71: 746 | C71: FREEZER MEALS, S.A DE C.V | D71: PROAPR | E71: APRORED BOLSA 1KG | F71: 2 | G71: 0 | H71: -2 | I71: -1 | J71: 584.619 | K71: 0 | L71: -584.619 | M71: -1
A72: 3 | B72: 738 | C72: JUAN ALBERTO RODRIGUEZ LLANES | D72: PRO5500 | E72: APROPORK BOL 20 Kg | F72: 0 | G72: 20 | H72: 20 | I72: 0 | J72: 0 | K72: 2417.38 | L72: 2417.38 | M72: 0
F73: =SUM(F66:F72) -> 132 | G73: =SUM(G66:G72) -> 20 | H73: =SUM(H66:H72) -> -112 | I73: =H73/F73 -> -0.84848485 | J73: =SUM(J66:J72) -> 31389.151 | K73: =SUM(K66:K72) -> 2417.38 | L73: =SUM(L66:L72) -> -28971.771 | M73: =L73/J73 -> -0.92298677
F77: FEBRERO
C78: ALTOS NORTE | F78: KILOS | J78: PESOS
A79: Vend | B79: Cte | C79: Nombre | D79: Código | E79: Descripcion | F79: Pres | G79: 2020 | H79: DIF | I79: % | J79: Pres | K79: 2020 | L79: DIF | M79: %
A80: 6 | B80: 340 | C80: PRODUCTOS JAMEX SA DE CV | D80: PROAPR | E80: APRORED BOLSA 1KG | F80: 100 | G80: 0 | H80: -100 | I80: -1 | J80: 29230.95 | K80: 0 | L80: -29230.95 | M80: -1
A81: 6 | B81: 037 | C81: MAXIM ALIMENTOS SA DE CV | D81: PRO5500 | E81: APROPORK BOL 25 Kg | F81: 180 | G81: 40 | H81: -140 | I81: -0.77777778 | J81: 22916.25 | K81: 4666.13 | L81: -18250.12 | M81: -0.79638335
A82: 6 | B82: 515 | C82: CARNES SELECTAS EL CIEN, SA DE CV | D82: PROAPR | E82: APRORED BOLSA 1KG | F82: 60 | G82: 0 | H82: -60 | I82: -1 | J82: 17538.57 | K82: 0 | L82: -17538.57 | M82: -1
A83: 6 | B83: 708 | C83: EVANGELINA BAUTISTA SANCHEZ | D83: PROAPR | E83: APRORED BOLSA 1KG | F83: 10 | G83: 3 | H83: -7 | I83: -0.7 | J83: 2923.095 | K83: 835.05 | L83: -2088.045 | M83: -0.71432677
A84: 6 | B84: 013 | C84: EMBUTIDOS SUPREMOS, SA DE CV | D84: PROAPR | E84: APRORED BOLSA 1KG | F84: 5 | G84: 0 | H84: -5 | I84: -1 | J84: 1461.5475 | K84: 0 | L84: -1461.5475 | M84: -1
A85: 6 | B85: 030 | C85: EMPACADORA ESTRELLA, SA DE CV | D85: PROAPR | E85: APRORED BOLSA 1KG | F85: 5 | G85: 0 | H85: -5 | I85: -1 | J85: 1427.937 | K85: 0 | L85: -1427.937 | M85: -1
A86: 6 | B86: 515 | C86: CARNES SELECTAS EL CIEN, SA DE CV | D86: PRO5500 | E86: APROPORK BOL 25 Kg | F86: 150 | G86: 160 | H86: 10 | I86: 0.066666667 | J86: 19860.75 | K86: 19436.04 | L86: -424.71 | M86: -0.021384389
A87: 6 | B87: 769 | C87: EMBOTIT DEL PATRON SA DE CV | D87: PRO5500 | E87: APROPORK BOL 20 Kg | F87: 0 | G87: 20 | H87: 20 | I87: 0 | J87: 0 | K87: 2423.95 | L87: 2423.95 | M87: 0
F88: =SUM(F80:F87) -> 510 | G88: =SUM(G80:G87) -> 223 | H88: =SUM(H80:H87) -> -287 | I88: =H88/F88 -> -0.5627451 | J88: =SUM(J80:J87) -> 95359.099 | K88: =SUM(K80:K87) -> 27361.17 | L88: =SUM(L80:L87) -> -67997.929 | M88: =L88/J88 -> -0.71307227
F92: FEBRERO
C93: BAJIO | F93: KILOS | J93: PESOS
A94: Vend | B94: Cte | C94: Nombre | D94: Código | E94: Descripcion | F94: Pres | G94: 2020 | H94: DIF | I94: % | J94: Pres | K94: 2020 | L94: DIF | M94: %
A95: 7 | B95: 093 | C95: EMPACADORA CELAYA SA DE CV | D95: PROAPR10 | E95: COM0213 APRORED BOLSA 10KG | F95: 42 | G95: 0 | H95: -42 | I95: -1 | J95: 12105.891 | K95: 0 | L95: -12105.891 | M95: -1
F97: =SUM(F95:F96) -> 42 | G97: =SUM(G95:G96) -> 0 | H97: =SUM(H95:H96) -> -42 | I97: =H97/F97 -> -1 | J97: =SUM(J95:J96) -> 12105.891 | K97: =SUM(K95:K96) -> 0 | L97: =SUM(L95:L96) -> -12105.891 | M97: =L97/J97 -> -1

Sheet MARZO
C1: CALCULO DE BONOS MARZO
C3: REGION OCCIDENTE
C5: KILOS | E5: Variacion | G5: PESOS | I5: Variacion
B6: MES | C6: Presupuesto | D6: Real | E6: KG | F6: % | G6: Presupuesto | H6: Real | I6: $ | J6: %
B7: MARZO | C7: ='ESSENTIA MAR'!O30 -> 145029.94 | D7: ='ESSENTIA MAR'!N30 -> 197180.65 | E7: =D7-C7 -> 52150.708 | F7: =D7/C7-1 -> 0.3595858 | G7: ='ESSENTIA MAR'!G30 -> 4337268.9 | H7: ='ESSENTIA MAR'!F30 -> 5866628.9 | I7: =H7-G7 -> 1529360 | J7: =H7/G7-1 -> 0.35260898
B9: COMPOSICION BONO | G9: ALCANCE DE OBJETIVOS
B10: Bono | C10: Concepto | D10: % Bono | E10: Monto | G10: Concepto | H10: Presupuesto | I10: Real | J10: % Cobertura | K10: Bono | M10: Objetivo Minimo
B11: 12000 | C11: Cumplimiento Presupuesto | D11: 0.7 | E11: =B11*D11 -> 8400 | G11: Cumplimiento Presupuesto | H11: =G7 -> 4337268.9 | I11: =H7 -> 5866628.9 | J11: =IFERROR(I11/H11,0) -> 1.352609 | K11: =IF(J11<M11,0,J11*$E11) -> 11361.915 | M11: 0.9
C12: Cierre de 3 pedidos 1000 Kgcon clientes actuales de FMC | D12: 0.12 | E12: =B11*D12 -> 1440 | G12: =C12 -> Cierre de 3 pedidos 1000 Kgcon clientes actuales de FMC | H12: 1 | J12: =I12/H12 -> 0 | K12: =IF(J12<M12,0,J12*$E12) -> 0 | M12: 0.8
C13: Contar con calendario de pruebas inicios de año 2020 | D13: 0.05 | E13: =B$11*D$13 -> 600 | G13: =C13 -> Contar con calendario de pruebas inicios de año 2020 | H13: 1 | J13: =I13/H13 -> 0 | K13: =IF(J13<M13,0,J13*$E13) -> 0 | M13: 1
C14: Presentar estrategica por region Occidente 2020 | D14: 0.05 | E14: =B$11*D$13 -> 600 | G14: =C14 -> Presentar estrategica por region Occidente 2020 | H14: 1 | J14: =I14/H14 -> 0 | K14: =IF(J14<M14,0,J14*$E14) -> 0 | M14: 0.75
C15: Presentar presupuesto lunes 6 de Diciembre | D15: 0.08 | E15: =B11*D15 -> 960 | G15: =C15 -> Presentar presupuesto lunes 6 de Diciembre | H15: 1 | J15: =I15/H15 -> 0 | K15: =IF(J15<M15,0,J15*$E15) -> 0 | M15: 0.75
C16: Total | D16: =SUM(D11:D15) -> 1 | E16: =SUM(E11:E15) -> 12000 | J16: Total sin Presupuesto | K16: =SUM(K12:K15) -> 0
J18: TOTAL | K18: =+K16+K11 -> 11361.915
C24: REGION PACIFICO
C26: KILOS | E26: Variacion | G26: PESOS | I26: Variacion
B27: MES | C27: Presupuesto | D27: Real | E27: KG | F27: % | G27: Presupuesto | H27: Real | I27: $ | J27: %
B28: =$B$7 -> MARZO | C28: ='ESSENTIA MAR'!O31 -> 40269.12 | D28: ='ESSENTIA MAR'!N31 -> 28197.388 | E28: =D28-C28 -> -12071.732 | F28: =D28/C28-1 -> -0.2997764 | G28: ='ESSENTIA MAR'!G31 -> 2513753.7 | H28: ='ESSENTIA MAR'!F31 -> 2114853.9 | I28: =H28-G28 -> -398899.75 | J28: =H28/G28-1 -> -0.15868689
B30: COMPOSICION BONO
B31: Bono | C31: Concepto | D31: % Bono | E31: Monto | F31: Objetivo Minimo | G31: Concepto | H31: Presupuesto | I31: Real | J31: % Cobertura | K31: Bono | M31: Objetivo Minimo
B32: 1000 | C32: Cumplimiento Presupuesto | D32: =E32/$B$37 -> 0.15384615 | E32: 1000 | F32: 0.5 | G32: =C32 -> Cumplimiento Presupuesto | H32: =G28 -> 2513753.7 | I32: =H28 -> 2114853.9 | J32: =IFERROR(I32/H32,0) -> 0.84131311 | K32: =IF(J32<M32,0,J32*$E32) -> 841.31311 | M32: 0.5
B33: 1000 | C33: Pruebas atorizadas por realizar con cliente | D33: =E33/$B$37 -> 0.15384615 | E33: 1000 | F33: 1 | G33: =C33 -> Pruebas atorizadas por realizar con cliente | H33: 1 | J33: =IFERROR(I33/H33,0) -> 0 | K33: =IF(J33<M33,0,J33*$E33) -> 0 | M33: 1
B34: 1500 | C34: Armado e implementación estrategia Baja California | D34: =E34/$B$37 -> 0.23076923 | E34: 1500 | F34: 1 | G34: =C34 -> Armado e implementación estrategia Baja California | H34: 1 | J34: =IFERROR(I34/H34,0) -> 0 | K34: =IF(J34<M34,0,J34*$E34) -> 0 | M34: 1
B35: 1500 | C35: Presentar estrategica por región 2020 | D35: =E35/$B$37 -> 0.23076923 | E35: 1500 | F35: 0.75 | G35: =C35 -> Presentar estrategica por región 2020 | H35: 1 | J35: =IFERROR(I35/H35,0) -> 0 | K35: =IF(J35<M35,0,J35*$E35) -> 0 | M35: 0.75
B36: 1500 | C36: Presentar presupuesto lunes 6 de Diciembre | D36: =E36/$B$37 -> 0.23076923 | E36: 1500 | F36: 0.75 | G36: =C36 -> Presentar presupuesto lunes 6 de Diciembre | H36: 1 | J36: =IFERROR(I36/H36,0) -> 0 | K36: =IF(J36<M36,0,J36*$E36) -> 0 | M36: 0.75
B37: =SUM(B32:B36) -> 6500 | C37: Total | E37: =SUM(E31:E36) -> 6500 | J37: Total sin Presupuesto | K37: =SUM(K34:K34) -> 0
J39: TOTAL | K39: =+K37+K32 -> 841.31311
C43: REGION BAJIO
C45: KILOS | E45: Variacion | G45: PESOS | I45: Variacion
B46: MES | C46: Presupuesto | D46: Real | E46: KG | F46: % | G46: Presupuesto | H46: Real | I46: $ | J46: %
B47: =$B$7 -> MARZO | C47: ='ESSENTIA MAR'!O36 -> 25555.395 | D47: ='ESSENTIA MAR'!N36 -> 36261.15 | E47: =D47-C47 -> 10705.755 | F47: =D47/C47-1 -> 0.41892346 | G47: ='ESSENTIA MAR'!G36 -> 1472297 | H47: ='ESSENTIA MAR'!F36 -> 2063580.4 | I47: =H47-G47 -> 591283.4 | J47: =H47/G47-1 -> 0.40160607
B49: COMPOSICION BONO | G49: ALCANCE DE OBJETIVOS
B50: Bono | C50: Concepto | D50: % Bono | E50: Monto | G50: Concepto | H50: Presupuesto | I50: Real | J50: % Cobertura | K50: Bono
B51: 7000 | C51: Cumplimiento Presupuesto | D51: 0.5 | E51: =B51*D51 -> 3500 | G51: =C51 -> Cumplimiento Presupuesto | H51: =G47 -> 1472297 | I51: =H47 -> 2063580.4 | J51: =IFERROR(I51/H51,0) -> 1.4016061 | K51: =IF(J51<M52,0,J51*$E51) -> 4905.6212 | M51: Objetivo Minimo
C52: Aplicación de pruebas unidades de chorizo | D52: 0.2 | E52: =B51*D52 -> 1400 | G52: =C52 -> Aplicación de pruebas unidades de chorizo | H52: 1 | J52: =IFERROR(I52/H52,0) -> 0 | K52: =IF(J52<M53,0,J52*$E52) -> 0 | M52: 0.95
C53: Prospectación | D53: 0.2 | E53: =B51*D53 -> 1400 | G53: =C53 -> Prospectación | H53: 1 | J53: =IFERROR(I53/H53,0) -> 0 | K53: =IF(J53<M54,0,J53*$E53) -> 0 | M53: 0.75
C54: Cierre de venta con productos nuevos AGR | D54: 0.1 | E54: =+D54*B51 -> 700 | G54: =C54 -> Cierre de venta con productos nuevos AGR | H54: 1 | J54: =IFERROR(I54/H54,0) -> 0 | K54: =IF(J54<M55,0,J54*$E54) -> 0 | M54: 0.75
C55: Total | D55: =SUM(D51:D54) -> 1 | E55: =SUM(E51:E54) -> 7000 | J55: Total sin Presupuesto | K55: =SUM(K52:K54) -> 0 | M55: 0.75
J57: TOTAL | K57: =+K55+K51 -> 4905.6212
C61: ALTOS NORTE
C63: KILOS | E63: Variacion | G63: PESOS | I63: Variacion
B64: MES | C64: Presupuesto | D64: Real | E64: KG | F64: % | G64: Presupuesto | H64: Real | I64: $ | J64: %
B65: =$B$7 -> MARZO | C65: ='ESSENTIA MAR'!O35 -> 129458.37 | D65: ='ESSENTIA MAR'!N35 -> 76038.482 | E65: =D65-C65 -> -53419.888 | F65: =D65/C65-1 -> -0.41264144 | G65: ='ESSENTIA MAR'!G35 -> 3162345.5 | H65: ='ESSENTIA MAR'!F35 -> 2703189 | I65: =H65-G65 -> -459156.46 | J65: =H65/G65-1 -> -0.14519491
B67: COMPOSICION BONO | G67: ALCANCE DE OBJETIVOS
B68: Bono | C68: Concepto | D68: % Bono | E68: Monto | G68: Concepto | H68: Presupuesto | I68: Real | J68: % Cobertura | K68: Bono | M68: Objetivo Minimo
B69: 10000 | C69: Cumplimiento Presupuesto | D69: 0.6 | E69: =+D69*B69 -> 6000 | G69: =C69 -> Cumplimiento Presupuesto | H69: =G65 -> 3162345.5 | I69: =H65 -> 2703189 | J69: =IFERROR(I69/H69,0) -> 0.85480509 | K69: =IF(J69<M69,0,J69*$E69) -> 5128.8306 | M69: 0.8
C70: Cierre de 3 pedidos 300 Kgcon clientes actuales de FMC | D70: 0.1 | E70: =B69*D70 -> 1000 | G70: =C70 -> Cierre de 3 pedidos 300 Kgcon clientes actuales de FMC | H70: 1 | J70: =I70/H70 -> 0 | K70: =IF(J70<M70,0,J70*$E70) -> 0 | M70: 0.8
C71: Contar con calendario de pruebas inicios de año 2020 | D71: 0.12 | E71: =+D71*B69 -> 1200 | G71: =C71 -> Contar con calendario de pruebas inicios de año 2020 | H71: 1 | J71: =IFERROR(I71/H71,0) -> 0 | K71: =IF(J71<M71,0,J71*$E71) -> 0 | M71: 1
C72: Presentar estrategica por region 2020 | D72: 0.07 | E72: =+D72*B69 -> 700 | G72: =C72 -> Presentar estrategica por region 2020 | H72: 1 | J72: =IFERROR(I72/H72,0) -> 0 | K72: =IF(J72<M72,0,J72*$E72) -> 0 | M72: 1
C73: Presentar presupuesto lunes 6 de Diciembre | D73: 0.11 | E73: =+D73*B69 -> 1100 | G73: =C73 -> Presentar presupuesto lunes 6 de Diciembre | H73: 1 | J73: =IFERROR(I73/H73,0) -> 0 | K73: =IF(J73<M73,0,J73*$E73) -> 0 | M73: 1
C74: Total | D74: =SUM(D69:D73) -> 1 | E74: =SUM(E69:E73) -> 10000 | J74: Total sin Presupuesto | K74: =SUM(K70:K73) -> 0
J76: TOTAL | K76: =+K74+K69 -> 5128.8306
C80: COORDINACION DE VENTAS
C82: KILOS | E82: Variacion | G82: PESOS | I82: Variacion
B83: MES | C83: Presupuesto | D83: Real | E83: KG | F83: % | G83: Presupuesto | H83: Real | I83: $ | J83: %
B84: =$B$7 -> MARZO | C84: ='ESSENTIA MAR'!O32 -> 62872.68 | D84: ='ESSENTIA MAR'!N32 -> 80334.684 | E84: =D84-C84 -> 17462.004 | F84: =D84/C84-1 -> 0.27773596 | G84: ='ESSENTIA MAR'!G32 -> 1681788.4 | H84: ='ESSENTIA MAR'!F32 -> 2003033 | I84: =H84-G84 -> 321244.6 | J84: =H84/G84-1 -> 0.19101368
B86: COMPOSICION BONO | G86: ALCANCE DE OBJETIVOS
B87: Bono | C87: Concepto | D87: % Bono | E87: Monto | G87: Concepto | H87: Presupuesto | I87: Real | J87: % Cobertura | K87: Bono | M87: Objetivo Minimo
C88: Cumplimiento Presupuesto | D88: 1 | E88: =+D88*B88 -> 0 | G88: =C88 -> Cumplimiento Presupuesto | H88: =G84 -> 1681788.4 | I88: =H84 -> 2003033 | J88: =IFERROR(I88/H88,0) -> 1.1910137 | K88: =IF(J88<M88,0,J88*$E88) -> 0 | M88: 0.8
E89: =B88*D89 -> 0 | G89: =C89 -> 0 | H89: 1 | J89: =I89/H89 -> 0 | K89: =IF(J89<M89,0,J89*$E89) -> 0 | M89: 0.8
E90: =+D90*B88 -> 0 | G90: =C90 -> 0 | H90: 1 | J90: =IFERROR(I90/H90,0) -> 0 | K90: =IF(J90<M90,0,J90*$E90) -> 0 | M90: 1
E91: =+D91*B88 -> 0 | G91: =C91 -> 0 | H91: 1 | J91: =IFERROR(I91/H91,0) -> 0 | K91: =IF(J91<M91,0,J91*$E91) -> 0 | M91: 1
E92: =+D92*B88 -> 0 | G92: =C92 -> 0 | H92: 1 | J92: =IFERROR(I92/H92,0) -> 0 | K92: =IF(J92<M92,0,J92*$E92) -> 0 | M92: 1
C93: Total | D93: =SUM(D88:D92) -> 1 | E93: =SUM(E88:E92) -> 0 | J93: Total sin Presupuesto | K93: =SUM(K89:K92) -> 0
J95: TOTAL | K95: =+K93+K88 -> 0
N170: 3 | O170: 3.1 | P170: =+O170-N170 -> 0.1 | Q170: =+P170/O170 -> 0.032258065
P174: =2000*3*12 -> 72000
P177: =2000*12 -> 24000

Sheet ESSENTIA MAR
E3: PRESUPUESTO ORIGINAL | F3: Importes | N3: Kilogramos
D4: Clave | E4: Region | F4: 2020 | G4: Pres | H4: Dif | I4: % Inc | J4: 2019 | K4: Dif | L4: % Inc | N4: 2020 | O4: Pres | P4: Dif | Q4: % Inc | R4: 2019 | S4: Dif | T4: % Inc
D5: 1 | E5: Occidente | F5: 5866628.9 | G5: 4375397.8 | H5: 1491231 | I5: 0.34082182 | J5: 5842159.2 | K5: 24469.71 | L5: 0.0041884703 | N5: 197180.65 | O5: 145378.44 | P5: 51802.208 | Q5: 0.35632661 | R5: 173656.21 | S5: 23524.439 | T5: 0.13546558
D6: 2 | E6: Pacifico | F6: 2114853.9 | G6: 2519579.5 | H6: -404725.57 | I6: -0.16063219 | J6: 2674387.9 | K6: -559534.01 | L6: -0.20921947 | N6: 28197.388 | O6: 40319.12 | P6: -12121.732 | Q6: -0.30064476 | R6: 47224.03 | S6: -19026.642 | T6: -0.4029017
D7: 3 | E7: Coordinadora de Ventas | F7: 2003033 | G7: 1692873.7 | H7: 310159.27 | I7: 0.18321465 | J7: 1403179.9 | K7: 599853.09 | L7: 0.42749549 | N7: 80334.684 | O7: 62937.68 | P7: 17397.004 | Q7: 0.27641635 | R7: 36118.064 | S7: 44216.62 | T7: 1.2242245
D8: 4 | E8: Cuentas Clave | F8: 1402135.6 | G8: 2122986.7 | H8: -720851.19 | I8: -0.33954578 | J8: 1816329.8 | K8: -414194.21 | L8: -0.2280391 | N8: 53684.4 | O8: 103176.28 | P8: -49491.88 | Q8: -0.47968273 | R8: 79547.88 | S8: -25863.48 | T8: -0.32513098
D9: 5 | E9: Mexico | F9: 145340.3 | G9: 176526.42 | H9: -31186.12 | I9: -0.17666545 | J9: 191931.4 | K9: -46591.1 | L9: -0.24274871 | N9: 150 | O9: 200 | P9: -50 | Q9: -0.25 | R9: 230 | S9: -80 | T9: -0.34782609
D10: 6 | E10: Altos Norte | F10: 1301053.4 | G10: 1092915.9 | H10: 208137.54 | I10: 0.19044241 | J10: 1394843.9 | K10: -93790.47 | L10: -0.067240835 | N10: 22354.082 | O10: 26525.09 | P10: -4171.008 | Q10: -0.15724765 | R10: 25602.36 | S10: -3248.2779 | T10: -0.12687416
D11: 7 | E11: Bajio | F11: 2063580.4 | G11: 1498300 | H11: 565280.33 | I11: 0.37728113 | J11: 1359435.8 | K11: 704144.57 | L11: 0.51796824 | N11: 36261.15 | O11: 25644.645 | P11: 10616.505 | Q11: 0.41398524 | R11: 24423.472 | S11: 11837.678 | T11: 0.4846845
F12: =SUM(F5:F11) -> 14896625 | G12: =SUM(G5:G11) -> 13478580 | H12: =F12-G12 -> 1418045.3 | I12: =IFERROR(F12/G12-1,0) -> 0.10520732 | J12: =SUM(J5:J11) -> 14682268 | K12: =F12-J12 -> 214357.58 | L12: =IFERROR(F12/J12-1,0) -> 0.01459976 | N12: =SUM(N5:N11) -> 418162.36 | O12: =SUM(O5:O11) -> 404181.26 | P12: =N12-O12 -> 13981.097 | Q12: =IFERROR(N12/O12-1,0) -> 0.034591155 | R12: =SUM(R5:R11) -> 386802.02 | S12: =N12-R12 -> 31360.337 | T12: =IFERROR(N12/R12-1,0) -> 0.081075941
E15: PERDIDA VENTA ESSENTIA | F15: Importes | N15: Kilogramos
D16: Clave | E16: Region | F16: 2020 | G16: Pres | H16: Dif | I16: % Inc | J16: 2019 | K16: Dif | L16: % Inc | N16: 2020 | O16: Pres | P16: Dif | Q16: % Inc | R16: 2019 | S16: Dif | T16: % Inc
D17: 1 | E17: Occidente | G17: =SUM(L44:L55) -> -38128.941 | O17: =SUM(H44:H55) -> -348.5
D18: 2 | E18: Pacifico | G18: =SUM(L63:L65) -> -5825.8175 | O18: =SUM(H63:H65) -> -50
D19: 3 | E19: Coordinadora de Ventas | G19: =SUM(L73:L74) -> -11085.327 | O19: =SUM(H73:H74) -> -65
D20: 4 | E20: Cuentas Clave
D21: 5 | E21: Mexico
D22: 6 | E22: Altos Norte | G22: =SUM(L82:L88) -> -53557.191 | O22: =SUM(H82:H88) -> -243
D23: 7 | E23: Bajio | G23: =SUM(L96:L97) -> -26003.069 | O23: =SUM(H96:H97) -> -89.25
F24: =SUM(F17:F23) -> 0 | G24: =SUM(G17:G23) -> -134600.35 | H24: =F24-G24 -> 134600.35 | I24: =IFERROR(F24/G24-1,0) -> -1 | J24: =SUM(J17:J23) -> 0 | K24: =F24-J24 -> 0 | L24: =IFERROR(F24/J24-1,0) -> 0 | N24: =SUM(N17:N23) -> 0 | O24: =SUM(O17:O23) -> -795.75 | P24: =N24-O24 -> 795.75 | Q24: =IFERROR(N24/O24-1,0) -> -1 | R24: =SUM(R17:R23) -> 0 | S24: =N24-R24 -> 0 | T24: =IFERROR(N24/R24-1,0) -> 0
E28: PRESUPUESTO MODIFICADO | F28: Importes | N28: Kilogramos
D29: Clave | E29: Region | F29: 2020 | G29: Pres | H29: Dif | I29: % Inc | J29: 2019 | K29: Dif | L29: % Inc | N29: 2020 | O29: Pres | P29: Dif | Q29: % Inc | R29: 2019 | S29: Dif | T29: % Inc
D30: 1 | E30: Occidente | F30: =F5 -> 5866628.9 | G30: =G5+G17 -> 4337268.9 | H30: =F30-G30 -> 1529360 | I30: =IFERROR(F30/G30-1,0) -> 0.35260898 | J30: 5842159.2 | K30: =F30-J30 -> 24469.71 | L30: =IFERROR(F30/J30-1,0) -> 0.0041884703 | N30: =N5 -> 197180.65 | O30: =O5+O17 -> 145029.94 | P30: =N30-O30 -> 52150.708 | Q30: =IFERROR(N30/O30-1,0) -> 0.3595858 | R30: 173656.21 | S30: =N30-R30 -> 23524.439 | T30: =IFERROR(N30/R30-1,0) -> 0.13546558
D31: 2 | E31: Pacifico | F31: =F6 -> 2114853.9 | G31: =G6+G18 -> 2513753.7 | H31: =F31-G31 -> -398899.75 | I31: =IFERROR(F31/G31-1,0) -> -0.15868689 | J31: 2674387.9 | K31: =F31-J31 -> -559534.01 | L31: =IFERROR(F31/J31-1,0) -> -0.20921947 | N31: =N6 -> 28197.388 | O31: =O6+O18 -> 40269.12 | P31: =N31-O31 -> -12071.732 | Q31: =IFERROR(N31/O31-1,0) -> -0.2997764 | R31: 47224.03 | S31: =N31-R31 -> -19026.642 | T31: =IFERROR(N31/R31-1,0) -> -0.4029017
D32: 3 | E32: Coordinadora de Ventas | F32: =F7 -> 2003033 | G32: =G7+G19 -> 1681788.4 | H32: =F32-G32 -> 321244.6 | I32: =IFERROR(F32/G32-1,0) -> 0.19101368 | J32: 1403179.9 | K32: =F32-J32 -> 599853.09 | L32: =IFERROR(F32/J32-1,0) -> 0.42749549 | N32: =N7 -> 80334.684 | O32: =O7+O19 -> 62872.68 | P32: =N32-O32 -> 17462.004 | Q32: =IFERROR(N32/O32-1,0) -> 0.27773596 | R32: 36118.064 | S32: =N32-R32 -> 44216.62 | T32: =IFERROR(N32/R32-1,0) -> 1.2242245
F33: =F8 -> 1402135.6 | G33: =G8+G20 -> 2122986.7 | H33: =F33-G33 -> -720851.19 | I33: =IFERROR(F33/G33-1,0) -> -0.33954578 | J33: 1816329.8 | K33: =F33-J33 -> -414194.21 | L33: =IFERROR(F33/J33-1,0) -> -0.2280391 | N33: =N8 -> 53684.4 | O33: =O8+O20 -> 103176.28 | P33: =N33-O33 -> -49491.88 | Q33: =IFERROR(N33/O33-1,0) -> -0.47968273 | R33: 79547.88 | S33: =N33-R33 -> -25863.48 | T33: =IFERROR(N33/R33-1,0) -> -0.32513098
D34: 5 | E34: Mexico | F34: =F9 -> 145340.3 | G34: =G9+G21 -> 176526.42 | H34: =F34-G34 -> -31186.12 | I34: =IFERROR(F34/G34-1,0) -> -0.17666545 | J34: 191931.4 | K34: =F34-J34 -> -46591.1 | L34: =IFERROR(F34/J34-1,0) -> -0.24274871 | N34: =N9 -> 150 | O34: =O9+O21 -> 200 | P34: =N34-O34 -> -50 | Q34: =IFERROR(N34/O34-1,0) -> -0.25 | R34: 230 | S34: =N34-R34 -> -80 | T34: =IFERROR(N34/R34-1,0) -> -0.34782609
D35: 6 | E35: Altos Norte | F35: =F10+F8 -> 2703189 | G35: =+G8+G10+G22 -> 3162345.5 | H35: =F35-G35 -> -459156.46 | I35: =IFERROR(F35/G35-1,0) -> -0.14519491 | J35: =J10+J8 -> 3211173.7 | K35: =F35-J35 -> -507984.68 | L35: =IFERROR(F35/J35-1,0) -> -0.15819284 | N35: =N10+N8 -> 76038.482 | O35: =+O8+O10+O22 -> 129458.37 | P35: =N35-O35 -> -53419.888 | Q35: =IFERROR(N35/O35-1,0) -> -0.41264144 | R35: 25602.36 | S35: =N35-R35 -> 50436.122 | T35: =IFERROR(N35/R35-1,0) -> 1.9699794
D36: 7 | E36: Bajio | F36: =F11 -> 2063580.4 | G36: =G11+G23 -> 1472297 | H36: =F36-G36 -> 591283.4 | I36: =IFERROR(F36/G36-1,0) -> 0.40160607 | J36: 1359435.8 | K36: =F36-J36 -> 704144.57 | L36: =IFERROR(F36/J36-1,0) -> 0.51796824 | N36: =N11 -> 36261.15 | O36: =O11+O23 -> 25555.395 | P36: =N36-O36 -> 10705.755 | Q36: =IFERROR(N36/O36-1,0) -> 0.41892346 | R36: 24423.472 | S36: =N36-R36 -> 11837.678 | T36: =IFERROR(N36/R36-1,0) -> 0.4846845
F37: =SUM(F30:F36) -> 16298761 | G37: =SUM(G30:G36) -> 15466967 | H37: =F37-G37 -> 831794.46 | I37: =IFERROR(F37/G37-1,0) -> 0.053778772 | J37: =SUM(J30:J36) -> 16498598 | K37: =F37-J37 -> -199836.63 | L37: =IFERROR(F37/J37-1,0) -> -0.01211234 | N37: =SUM(N30:N36) -> 471846.76 | O37: =SUM(O30:O36) -> 506561.79 | P37: =N37-O37 -> -34715.033 | Q37: =IFERROR(N37/O37-1,0) -> -0.068530699 | R37: =SUM(R30:R36) -> 386802.02 | S37: =N37-R37 -> 85044.737 | T37: =IFERROR(N37/R37-1,0) -> 0.21986632
F41: MARZO
C42: OCCIDENTE | F42: KILOS | J42: PESOS
A43: Vend | B43: Cte | C43: Nombre | D43: Código | E43: Descripcion | F43: Pres | G43: 2020 | H43: DIF | I43: % | J43: Pres | K43: 2020 | L43: DIF | M43: %
A44: 1 | B44: 009 | C44: EMPACADORA EL CENTENARIO, SA DE CV | D44: PRO5500 | E44: APROPORK BOL 25 Kg | F44: 787.5 | G44: 720 | H44: -67.5 | I44: -0.085714286 | J44: 104268.94 | K44: 99594 | L44: -4674.9375 | M44: -0.044835381
A45: 1 | B45: 009 | C45: EMPACADORA EL CENTENARIO, SA DE CV | D45: PROAPR | E45: APRORED BOLSA 1KG | F45: 12.6 | G45: 0 | H45: -12.6 | I45: -1 | J45: 3683.0997 | K45: 0 | L45: -3683.0997 | M45: -1
A46: 1 | B46: 038 | C46: EMPACADORA BONNACARNE SA DE CV | D46: PROAPR | E46: APRORED BOLSA 1KG | F46: 15.75 | G46: 10 | H46: -5.75 | I46: -0.36507937 | J46: 4716.1642 | K46: 3118.31 | L46: -1597.8543 | M46: -0.33880377
A47: 1 | B47: 099 | C47: COMERCIALIZADORA DE EMBUTIDOS ICO SA DE CV | D47: PROAPR | E47: APRORED BOLSA 1KG | F47: 3.15 | G47: 0 | H47: -3.15 | I47: -1 | J47: 891.90045 | K47: 0 | L47: -891.90045 | M47: -1
A48: 1 | B48: 476 | C48: OMEX ALIMENTARIA SA DE CV | D48: PROAPR | E48: APRORED BOLSA 1KG | F48: 10.5 | G48: 7 | H48: -3.5 | I48: -0.33333333 | J48: 3144.1095 | K48: 2095.24 | L48: -1048.8695 | M48: -0.33359827
A49: 1 | B49: 481 | C49: GRUPO BRAVO NUÑO S.C. DE R.L. DE C.V. | D49: PROAPR | E49: APRORED BOLSA 1KG | F49: 126 | G49: 250 | H49: 124 | I49: 0.98412698 | J49: 32082.75 | K49: 60261.56 | L49: 28178.81 | M49: 0.87831654
A50: 1 | B50: 485 | C50: PRODUCTOS EL GRAN CHAPARRAL SA DE CV | D50: PROAPR | E50: APRORED BOLSA 1KG | F50: 42 | G50: 30 | H50: -12 | I50: -0.28571429 | J50: 12276.999 | K50: 9200.23 | L50: -3076.769 | M50: -0.25061247
A51: 1 | B51: 327 | C51: EMPACADORAS UNIDAS DE LA PIEDAD SA DE CV | D51: PROAPR | E51: APRORED BOLSA 1KG | F51: 5.25 | G51: 0 | H51: -5.25 | I51: -1 | J51: 1534.6249 | K51: 0 | L51: -1534.6249 | M51: -1
A52: 1 | B52: 553 | C52: INDUSTRIAS PECUARIAS AYENSE SPR DE RL DE CV | D52: PROAPR | E52: APRORED BOLSA 1KG | F52: 10.5 | G52: 0 | H52: -10.5 | I52: -1 | J52: 3069.2497 | K52: 0 | L52: -3069.2497 | M52: -1
A53: 1 | B53: 657 | C53: HECTOR ALONSO ZARATE QUIROZ | D53: PROAPR | E53: APRORED BOLSA 1KG | F53: 21 | G53: 0 | H53: -21 | I53: -1 | J53: 6138.4995 | K53: 0 | L53: -6138.4995 | M53: -1
A54: 1 | B54: 327 | C54: EMPACADORAS UNIDAS DE LA PIEDAD SA DE CV | D54: PRO5500 | E54: APROPORK BOL 25 Kg | F54: 341.25 | G54: 0 | H54: -341.25 | I54: -1 | J54: 44140.517 | K54: 0 | L54: -44140.517 | M54: -1
A55: 1 | B55: 657 | C55: HECTOR ALONSO ZARATE QUIROZ | D55: PROAPR10 | E55: COM0213 APRORED BOLSA 10KG | F55: 0 | G55: 10 | H55: 10 | I55: 0 | J55: 0 | K55: 3548.57 | L55: 3548.57 | M55: 0
F56: =SUM(F44:F55) -> 1375.5 | G56: =SUM(G44:G55) -> 1027 | H56: =SUM(H44:H55) -> -348.5 | I56: =H56/F56 -> -0.25336241 | J56: =SUM(J44:J55) -> 215946.85 | K56: =SUM(K44:K55) -> 177817.91 | L56: =SUM(L44:L55) -> -38128.941 | M56: =L56/J56 -> -0.17656632
F60: MARZO
C61: PACIFICO | F61: KILOS | J61: PESOS
A62: Vend | B62: Cte | C62: Nombre | D62: Código | E62: Descripcion | F62: Pres | G62: 2020 | H62: DIF | I62: % | J62: Pres | K62: 2020 | L62: DIF | M62: %
A63: 2 | B63: 012 | C63: KAREY ALIMENTOS, SA DE CV | D63: PROAPR | E63: APRORED BOLSA 1KG | F63: 15 | G63: 20 | H63: 5 | I63: 0.33333333 | J63: 4384.6425 | K63: 5949.84 | L63: 1565.1975 | M63: 0.35697266
A64: 2 | B64: 298 | C64: JOSE ADAN BERNAL GARCIA | D64: PRO5500 | E64: APROPORK BOL 25 Kg | F64: 75 | G64: 0 | H64: -75 | I64: -1 | J64: 9930.375 | K64: 0 | L64: -9930.375 | M64: -1
A65: 2 | B65: 773 | C65: JESUS ALBERTO BERNAL GARCIA | D65: PRO5500 | E65: APROPORK BOL 20 Kg | F65: 0 | G65: 20 | H65: 20 | I65: 0 | J65: 0 | K65: 2539.36 | L65: 2539.36 | M65: 0
F66: =SUM(F63:F65) -> 90 | G66: =SUM(G63:G65) -> 40 | H66: =SUM(H63:H65) -> -50 | I66: =H66/F66 -> -0.55555556 | J66: =SUM(J63:J65) -> 14315.017 | K66: =SUM(K63:K65) -> 8489.2 | L66: =SUM(L63:L65) -> -5825.8175 | M66: =L66/J66 -> -0.40697243
F70: MARZO
C71: COORDINADORA DE VENTAS | F71: KILOS | J71: PESOS
A72: Vend | B72: Cte | C72: Nombre | D72: Código | E72: Descripcion | F72: Pres | G72: 2020 | H72: DIF | I72: % | J72: Pres | K72: 2020 | L72: DIF | M72: %
A73: 3 | B73: 601 | C73: VILLESPA, SPR DE RL | D73: PROAPR | E73: APRORED BOLSA 1KG | F73: 25 | G73: 10 | H73: -15 | I73: -0.6 | J73: 7307.7375 | K73: 2842.66 | L73: -4465.0775 | M73: -0.61100683
A74: 3 | B74: 714 | C74: Cooperativa de produccion pesquera el palacio, SC de RL | D74: PRO5500 | E74: APROPORK BOL 25 Kg | F74: 50 | G74: 0 | H74: -50 | I74: -1 | J74: 6620.25 | K74: 0 | L74: -6620.25 | M74: -1
F75: =SUM(F73:F74) -> 75 | G75: =SUM(G73:G74) -> 10 | H75: =SUM(H73:H74) -> -65 | I75: =H75/F75 -> -0.86666667 | J75: =SUM(J73:J74) -> 13927.987 | K75: =SUM(K73:K74) -> 2842.66 | L75: =SUM(L73:L74) -> -11085.327 | M75: =L75/J75 -> -0.79590303
F79: MARZO
C80: ALTOS NORTE | F80: KILOS | J80: PESOS
A81: Vend | B81: Cte | C81: Nombre | D81: Código | E81: Descripcion | F81: Pres | G81: 2020 | H81: DIF | I81: % | J81: Pres | K81: 2020 | L81: DIF | M81: %
A82: 6 | B82: 013 | C82: EMBUTIDOS SUPREMOS, SA DE CV | D82: PROAPR | E82: APRORED BOLSA 1KG | F82: 7 | G82: 6 | H82: -1 | I82: -0.14285714 | J82: 2046.1665 | K82: 1840.05 | L82: -206.1165 | M82: -0.100733
A83: 6 | B83: 030 | C83: EMPACADORA ESTRELLA, SA DE CV | D83: PROAPR | E83: APRORED BOLSA 1KG | F83: 5 | G83: 8 | H83: 3 | I83: 0.6 | J83: 1427.937 | K83: 2221.83 | L83: 793.893 | M83: 0.55597201
A84: 6 | B84: 340 | C84: PRODUCTOS JAMEX SA DE CV | D84: PROAPR | E84: APRORED BOLSA 1KG | F84: 150 | G84: 40 | H84: -110 | I84: -0.73333333 | J84: 43846.425 | K84: 11370.65 | L84: -32475.775 | M84: -0.74067099
A85: 6 | B85: 515 | C85: CARNES SELECTAS EL CIEN, SA DE CV | D85: PROAPR | E85: APRORED BOLSA 1KG | F85: 60 | G85: 30 | H85: -30 | I85: -0.5 | J85: 17538.57 | K85: 8681.2 | L85: -8857.37 | M85: -0.50502236
A86: 6 | B86: 037 | C86: MAXIM ALIMENTOS SA DE CV | D86: PRO5500 | E86: APROPORK BOL 25 Kg | F86: 220 | G86: 60 | H86: -160 | I86: -0.72727273 | J86: 28008.75 | K86: 9032.55 | L86: -18976.2 | M86: -0.67750971
A87: 6 | B87: 708 | C87: EVANGELINA BAUTISTA SANCHEZ | D87: PROAPR | E87: APRORED BOLSA 1KG | F87: 15 | G87: 0 | H87: -15 | I87: -1 | J87: 4384.6425 | K87: 0 | L87: -4384.6425 | M87: -1
A88: 6 | B88: 515 | C88: CARNES SELECTAS EL CIEN, SA DE CV | D88: PRO5500 | E88: APROPORK BOL 25 Kg | F88: 150 | G88: 220 | H88: 70 | I88: 0.46666667 | J88: 19860.75 | K88: 30409.77 | L88: 10549.02 | M88: 0.53114913
F89: =SUM(F82:F88) -> 607 | G89: =SUM(G82:G88) -> 364 | H89: =SUM(H82:H88) -> -243 | I89: =H89/F89 -> -0.40032949 | J89: =SUM(J82:J88) -> 117113.24 | K89: =SUM(K82:K88) -> 63556.05 | L89: =SUM(L82:L88) -> -53557.191 | M89: =L89/J89 -> -0.45731115
F93: FEBRERO
C94: BAJIO | F94: KILOS | J94: PESOS
A95: Vend | B95: Cte | C95: Nombre | D95: Código | E95: Descripcion | F95: Pres | G95: 2020 | H95: DIF | I95: % | J95: Pres | K95: 2020 | L95: DIF | M95: %
A96: 7 | B96: 093 | C96: EMPACADORA CELAYA SA DE CV | D96: PROAPR10 | E96: COM0213 APRORED BOLSA 10KG | F96: 21 | G96: 0 | H96: -21 | I96: -1 | J96: 6052.9455 | K96: 0 | L96: -6052.9455 | M96: -1
A97: 7 | B97: 542 | C97: NESTOR LOZA QUISTIANO | D97: PROAPR | E97: APRORED BOLSA 1KG | F97: 68.25 | G97: 0 | H97: -68.25 | I97: -1 | J97: 19950.123 | K97: 0 | L97: -19950.123 | M97: -1
F98: =SUM(F96:F97) -> 89.25 | G98: =SUM(G96:G97) -> 0 | H98: =SUM(H96:H97) -> -89.25 | I98: =H98/F98 -> -1 | J98: =SUM(J96:J97) -> 26003.069 | K98: =SUM(K96:K97) -> 0 | L98: =SUM(L96:L97) -> -26003.069 | M98: =L98/J98 -> -1

Sheet ABRIL
C1: CALCULO DE BONOS ABRIL
C3: REGION OCCIDENTE
C5: KILOS | E5: Variacion | G5: PESOS | I5: Variacion
B6: MES | C6: Presupuesto | D6: Real | E6: KG | F6: % | G6: Presupuesto | H6: Real | I6: $ | J6: %
B7: ABRIL | C7: ='ESSENTIA ABR'!O30 -> 158697.14 | D7: ='ESSENTIA ABR'!N30 -> 132874.53 | E7: =D7-C7 -> -25822.611 | F7: =D7/C7-1 -> -0.1627163 | G7: ='ESSENTIA ABR'!G30 -> 4780259.9 | H7: ='ESSENTIA ABR'!F30 -> 5313807.2 | I7: =H7-G7 -> 533547.23 | J7: =H7/G7-1 -> 0.11161469
B9: COMPOSICION BONO | G9: ALCANCE DE OBJETIVOS
B10: Bono | C10: Concepto | D10: % Bono | E10: Monto | G10: Concepto | H10: Presupuesto | I10: Real | J10: % Cobertura | K10: Bono | M10: Objetivo Minimo
B11: 12000 | C11: Cumplimiento Presupuesto | D11: 0.7 | E11: =B11*D11 -> 8400 | G11: Cumplimiento Presupuesto | H11: =G7 -> 4780259.9 | I11: =H7 -> 5313807.2 | J11: =IFERROR(I11/H11,0) -> 1.1116147 | K11: =IF(J11<M11,0,J11*$E11) -> 9337.5634 | M11: 0.9
C12: Cierre de 3 pedidos 1000 Kgcon clientes actuales de FMC | D12: 0.12 | E12: =B11*D12 -> 1440 | G12: =C12 -> Cierre de 3 pedidos 1000 Kgcon clientes actuales de FMC | H12: 1 | J12: =I12/H12 -> 0 | K12: =IF(J12<M12,0,J12*$E12) -> 0 | M12: 0.8
C13: Contar con calendario de pruebas inicios de año 2020 | D13: 0.05 | E13: =B$11*D$13 -> 600 | G13: =C13 -> Contar con calendario de pruebas inicios de año 2020 | H13: 1 | J13: =I13/H13 -> 0 | K13: =IF(J13<M13,0,J13*$E13) -> 0 | M13: 1
C14: Presentar estrategica por region Occidente 2020 | D14: 0.05 | E14: =B$11*D$13 -> 600 | G14: =C14 -> Presentar estrategica por region Occidente 2020 | H14: 1 | J14: =I14/H14 -> 0 | K14: =IF(J14<M14,0,J14*$E14) -> 0 | M14: 0.75
C15: Presentar presupuesto lunes 6 de Diciembre | D15: 0.08 | E15: =B11*D15 -> 960 | G15: =C15 -> Presentar presupuesto lunes 6 de Diciembre | H15: 1 | J15: =I15/H15 -> 0 | K15: =IF(J15<M15,0,J15*$E15) -> 0 | M15: 0.75
C16: Total | D16: =SUM(D11:D15) -> 1 | E16: =SUM(E11:E15) -> 12000 | J16: Total sin Presupuesto | K16: =SUM(K12:K15) -> 0
J18: TOTAL | K18: =+K16+K11 -> 9337.5634
C24: REGION PACIFICO
C26: KILOS | E26: Variacion | G26: PESOS | I26: Variacion
B27: MES | C27: Presupuesto | D27: Real | E27: KG | F27: % | G27: Presupuesto | H27: Real | I27: $ | J27: %
B28: =$B$7 -> ABRIL | C28: ='ESSENTIA ABR'!O31 -> 31844 | D28: ='ESSENTIA ABR'!N31 -> 16035.98 | E28: =D28-C28 -> -15808.02 | F28: =D28/C28-1 -> -0.49642068 | G28: ='ESSENTIA ABR'!G31 -> 2220021.1 | H28: ='ESSENTIA ABR'!F31 -> 1066299.4 | I28: =H28-G28 -> -1153721.8 | J28: =H28/G28-1 -> -0.51968955
B30: COMPOSICION BONO
B31: Bono | C31: Concepto | D31: % Bono | E31: Monto | F31: Objetivo Minimo | G31: Concepto | H31: Presupuesto | I31: Real | J31: % Cobertura | K31: Bono | M31: Objetivo Minimo
B32: 1000 | C32: Cumplimiento Presupuesto | D32: =E32/$B$37 -> 0.15384615 | E32: 1000 | F32: 0.5 | G32: =C32 -> Cumplimiento Presupuesto | H32: =G28 -> 2220021.1 | I32: =H28 -> 1066299.4 | J32: =IFERROR(I32/H32,0) -> 0.48031045 | K32: =IF(J32<M32,0,J32*$E32) -> 0 | M32: 0.5
B33: 1000 | C33: Pruebas atorizadas por realizar con cliente | D33: =E33/$B$37 -> 0.15384615 | E33: 1000 | F33: 1 | G33: =C33 -> Pruebas atorizadas por realizar con cliente | H33: 1 | J33: =IFERROR(I33/H33,0) -> 0 | K33: =IF(J33<M33,0,J33*$E33) -> 0 | M33: 1
B34: 1500 | C34: Armado e implementación estrategia Baja California | D34: =E34/$B$37 -> 0.23076923 | E34: 1500 | F34: 1 | G34: =C34 -> Armado e implementación estrategia Baja California | H34: 1 | J34: =IFERROR(I34/H34,0) -> 0 | K34: =IF(J34<M34,0,J34*$E34) -> 0 | M34: 1
B35: 1500 | C35: Presentar estrategica por región 2020 | D35: =E35/$B$37 -> 0.23076923 | E35: 1500 | F35: 0.75 | G35: =C35 -> Presentar estrategica por región 2020 | H35: 1 | J35: =IFERROR(I35/H35,0) -> 0 | K35: =IF(J35<M35,0,J35*$E35) -> 0 | M35: 0.75
B36: 1500 | C36: Presentar presupuesto lunes 6 de Diciembre | D36: =E36/$B$37 -> 0.23076923 | E36: 1500 | F36: 0.75 | G36: =C36 -> Presentar presupuesto lunes 6 de Diciembre | H36: 1 | J36: =IFERROR(I36/H36,0) -> 0 | K36: =IF(J36<M36,0,J36*$E36) -> 0 | M36: 0.75
B37: =SUM(B32:B36) -> 6500 | C37: Total | E37: =SUM(E31:E36) -> 6500 | J37: Total sin Presupuesto | K37: =SUM(K34:K34) -> 0
J39: TOTAL | K39: =+K37+K32 -> 0
C43: REGION BAJIO
C45: KILOS | E45: Variacion | G45: PESOS | I45: Variacion
B46: MES | C46: Presupuesto | D46: Real | E46: KG | F46: % | G46: Presupuesto | H46: Real | I46: $ | J46: %
B47: =$B$7 -> ABRIL | C47: ='ESSENTIA ABR'!O36 -> 28358.021 | D47: ='ESSENTIA ABR'!N36 -> 17999.54 | E47: =D47-C47 -> -10358.481 | F47: =D47/C47-1 -> -0.36527518 | G47: ='ESSENTIA ABR'!G36 -> 1902243 | H47: ='ESSENTIA ABR'!F36 -> 1128176.3 | I47: =H47-G47 -> -774066.69 | J47: =H47/G47-1 -> -0.40692313
B49: COMPOSICION BONO | G49: ALCANCE DE OBJETIVOS
B50: Bono | C50: Concepto | D50: % Bono | E50: Monto | G50: Concepto | H50: Presupuesto | I50: Real | J50: % Cobertura | K50: Bono
B51: 7000 | C51: Cumplimiento Presupuesto | D51: 0.5 | E51: =B51*D51 -> 3500 | G51: =C51 -> Cumplimiento Presupuesto | H51: =G47 -> 1902243 | I51: =H47 -> 1128176.3 | J51: =IFERROR(I51/H51,0) -> 0.59307687 | K51: =IF(J51<M52,0,J51*$E51) -> 0 | M51: Objetivo Minimo
C52: Aplicación de pruebas unidades de chorizo | D52: 0.2 | E52: =B51*D52 -> 1400 | G52: =C52 -> Aplicación de pruebas unidades de chorizo | H52: 1 | J52: =IFERROR(I52/H52,0) -> 0 | K52: =IF(J52<M53,0,J52*$E52) -> 0 | M52: 0.95
C53: Prospectación | D53: 0.2 | E53: =B51*D53 -> 1400 | G53: =C53 -> Prospectación | H53: 1 | J53: =IFERROR(I53/H53,0) -> 0 | K53: =IF(J53<M54,0,J53*$E53) -> 0 | M53: 0.75
C54: Cierre de venta con productos nuevos AGR | D54: 0.1 | E54: =+D54*B51 -> 700 | G54: =C54 -> Cierre de venta con productos nuevos AGR | H54: 1 | J54: =IFERROR(I54/H54,0) -> 0 | K54: =IF(J54<M55,0,J54*$E54) -> 0 | M54: 0.75
C55: Total | D55: =SUM(D51:D54) -> 1 | E55: =SUM(E51:E54) -> 7000 | J55: Total sin Presupuesto | K55: =SUM(K52:K54) -> 0 | M55: 0.75
J57: TOTAL | K57: =+K55+K51 -> 0
C61: ALTOS NORTE
C63: KILOS | E63: Variacion | G63: PESOS | I63: Variacion
B64: MES | C64: Presupuesto | D64: Real | E64: KG | F64: % | G64: Presupuesto | H64: Real | I64: $ | J64: %
B65: =$B$7 -> ABRIL | C65: ='ESSENTIA ABR'!O35 -> 132129.24 | D65: ='ESSENTIA ABR'!N35 -> 95115.822 | E65: =D65-C65 -> -37013.418 | F65: =D65/C65-1 -> -0.28013041 | G65: ='ESSENTIA ABR'!G35 -> 3340063.6 | H65: ='ESSENTIA ABR'!F35 -> 3267713 | I65: =H65-G65 -> -72350.613 | J65: =H65/G65-1 -> -0.021661448
B67: COMPOSICION BONO | G67: ALCANCE DE OBJETIVOS
B68: Bono | C68: Concepto | D68: % Bono | E68: Monto | G68: Concepto | H68: Presupuesto | I68: Real | J68: % Cobertura | K68: Bono | M68: Objetivo Minimo
B69: 10000 | C69: Cumplimiento Presupuesto | D69: 0.6 | E69: =+D69*B69 -> 6000 | G69: =C69 -> Cumplimiento Presupuesto | H69: =G65 -> 3340063.6 | I69: =H65 -> 3267713 | J69: =IFERROR(I69/H69,0) -> 0.97833855 | K69: =IF(J69<M69,0,J69*$E69) -> 5870.0313 | M69: 0.8
C70: Cierre de 3 pedidos 300 Kgcon clientes actuales de FMC | D70: 0.1 | E70: =B69*D70 -> 1000 | G70: =C70 -> Cierre de 3 pedidos 300 Kgcon clientes actuales de FMC | H70: 1 | J70: =I70/H70 -> 0 | K70: =IF(J70<M70,0,J70*$E70) -> 0 | M70: 0.8
C71: Contar con calendario de pruebas inicios de año 2020 | D71: 0.12 | E71: =+D71*B69 -> 1200 | G71: =C71 -> Contar con calendario de pruebas inicios de año 2020 | H71: 1 | J71: =IFERROR(I71/H71,0) -> 0 | K71: =IF(J71<M71,0,J71*$E71) -> 0 | M71: 1
C72: Presentar estrategica por region 2020 | D72: 0.07 | E72: =+D72*B69 -> 700 | G72: =C72 -> Presentar estrategica por region 2020 | H72: 1 | J72: =IFERROR(I72/H72,0) -> 0 | K72: =IF(J72<M72,0,J72*$E72) -> 0 | M72: 1
C73: Presentar presupuesto lunes 6 de Diciembre | D73: 0.11 | E73: =+D73*B69 -> 1100 | G73: =C73 -> Presentar presupuesto lunes 6 de Diciembre | H73: 1 | J73: =IFERROR(I73/H73,0) -> 0 | K73: =IF(J73<M73,0,J73*$E73) -> 0 | M73: 1
C74: Total | D74: =SUM(D69:D73) -> 1 | E74: =SUM(E69:E73) -> 10000 | J74: Total sin Presupuesto | K74: =SUM(K70:K73) -> 0
J76: TOTAL | K76: =+K74+K69 -> 5870.0313
C80: COORDINACION DE VENTAS
C82: KILOS | E82: Variacion | G82: PESOS | I82: Variacion
B83: MES | C83: Presupuesto | D83: Real | E83: KG | F83: % | G83: Presupuesto | H83: Real | I83: $ | J83: %
B84: =$B$7 -> ABRIL | C84: ='ESSENTIA ABR'!O32 -> 47134 | D84: ='ESSENTIA ABR'!N32 -> 38260.164 | E84: =D84-C84 -> -8873.836 | F84: =D84/C84-1 -> -0.18826826 | G84: ='ESSENTIA ABR'!G32 -> 1500194.6 | H84: ='ESSENTIA ABR'!F32 -> 1569643 | I84: =H84-G84 -> 69448.355 | J84: =H84/G84-1 -> 0.046292898
B86: COMPOSICION BONO | G86: ALCANCE DE OBJETIVOS
B87: Bono | C87: Concepto | D87: % Bono | E87: Monto | G87: Concepto | H87: Presupuesto | I87: Real | J87: % Cobertura | K87: Bono | M87: Objetivo Minimo
C88: Cumplimiento Presupuesto | D88: 1 | E88: =+D88*B88 -> 0 | G88: =C88 -> Cumplimiento Presupuesto | H88: =G84 -> 1500194.6 | I88: =H84 -> 1569643 | J88: =IFERROR(I88/H88,0) -> 1.0462929 | K88: =IF(J88<M88,0,J88*$E88) -> 0 | M88: 0.8
E89: =B88*D89 -> 0 | G89: =C89 -> 0 | H89: 1 | J89: =I89/H89 -> 0 | K89: =IF(J89<M89,0,J89*$E89) -> 0 | M89: 0.8
E90: =+D90*B88 -> 0 | G90: =C90 -> 0 | H90: 1 | J90: =IFERROR(I90/H90,0) -> 0 | K90: =IF(J90<M90,0,J90*$E90) -> 0 | M90: 1
E91: =+D91*B88 -> 0 | G91: =C91 -> 0 | H91: 1 | J91: =IFERROR(I91/H91,0) -> 0 | K91: =IF(J91<M91,0,J91*$E91) -> 0 | M91: 1
E92: =+D92*B88 -> 0 | G92: =C92 -> 0 | H92: 1 | J92: =IFERROR(I92/H92,0) -> 0 | K92: =IF(J92<M92,0,J92*$E92) -> 0 | M92: 1
C93: Total | D93: =SUM(D88:D92) -> 1 | E93: =SUM(E88:E92) -> 0 | J93: Total sin Presupuesto | K93: =SUM(K89:K92) -> 0
J95: TOTAL | K95: =+K93+K88 -> 0
N170: 3 | O170: 3.1 | P170: =+O170-N170 -> 0.1 | Q170: =+P170/O170 -> 0.032258065
P174: =2000*3*12 -> 72000
P177: =2000*12 -> 24000

Sheet ESSENTIA ABR
E3: PRESUPUESTO ORIGINAL | F3: Importes | N3: Kilogramos
D4: Clave | E4: Region | F4: 2020 | G4: Pres | H4: Dif | I4: % Inc | J4: 2019 | K4: Dif | L4: % Inc | N4: 2020 | O4: Pres | P4: Dif | Q4: % Inc | R4: 2019 | S4: Dif | T4: % Inc
D5: 1 | E5: Occidente | F5: 5313807.2 | G5: 4793765.6 | H5: =F5-G5 -> 520041.55 | I5: =IFERROR(F5/G5-1,0) -> 0.10848289 | J5: 5883519.2 | K5: =F5-J5 -> -569711.98 | L5: =IFERROR(F5/J5-1,0) -> -0.096831839 | N5: 132874.53 | O5: 158923.64 | P5: =N5-O5 -> -26049.111 | Q5: =IFERROR(N5/O5-1,0) -> -0.16390961 | R5: 179310.23 | S5: =N5-R5 -> -46435.698 | T5: =IFERROR(N5/R5-1,0) -> -0.25896848
D6: 2 | E6: Pacifico | F6: 1066299.4 | G6: 2222720.1 | H6: =F6-G6 -> -1156420.7 | I6: =IFERROR(F6/G6-1,0) -> -0.52027276 | J6: 2460058.2 | K6: =F6-J6 -> -1393758.8 | L6: =IFERROR(F6/J6-1,0) -> -0.56655522 | N6: 16035.98 | O6: 31844 | P6: =N6-O6 -> -15808.02 | Q6: =IFERROR(N6/O6-1,0) -> -0.49642068 | R6: 52118.003 | S6: =N6-R6 -> -36082.023 | T6: =IFERROR(N6/R6-1,0) -> -0.692314
D7: 3 | E7: Servicio al cliente | F7: 1569643 | G7: 1506074.1 | H7: =F7-G7 -> 63568.833 | I7: =IFERROR(F7/G7-1,0) -> 0.042208303 | J7: 1143991.1 | K7: =F7-J7 -> 425651.9 | L7: =IFERROR(F7/J7-1,0) -> 0.37207625 | N7: 38260.164 | O7: 47169 | P7: =N7-O7 -> -8908.836 | Q7: =IFERROR(N7/O7-1,0) -> -0.18887057 | R7: 37083.39 | S7: =N7-R7 -> 1176.7741 | T7: =IFERROR(N7/R7-1,0) -> 0.031733186
D8: 4 | E8: Cuentas Clave | F8: 2064306.8 | G8: 2252396 | H8: =F8-G8 -> -188089.15 | I8: =IFERROR(F8/G8-1,0) -> -0.083506254 | J8: 2279686.2 | K8: =F8-J8 -> -215379.4 | L8: =IFERROR(F8/J8-1,0) -> -0.094477651 | N8: 76524.32 | O8: 111960 | P8: =N8-O8 -> -35435.68 | Q8: =IFERROR(N8/O8-1,0) -> -0.31650304 | R8: 102460 | S8: =N8-R8 -> -25935.68 | T8: =IFERROR(N8/R8-1,0) -> -0.25312981
D9: 5 | E9: Mexico | F9: 203864.18 | G9: 150047.46 | H9: =F9-G9 -> 53816.723 | I9: =IFERROR(F9/G9-1,0) -> 0.35866468 | J9: 83401.35 | K9: =F9-J9 -> 120462.83 | L9: =IFERROR(F9/J9-1,0) -> 1.4443751 | N9: 200 | O9: 170 | P9: =N9-O9 -> 30 | Q9: =IFERROR(N9/O9-1,0) -> 0.17647059 | R9: 90.84 | S9: =N9-R9 -> 109.16 | T9: =IFERROR(N9/R9-1,0) -> 1.2016733
D10: 6 | E10: Altos Norte | F10: 1203406.2 | G10: 1134739.1 | H10: =F10-G10 -> 68667.126 | I10: =IFERROR(F10/G10-1,0) -> 0.060513583 | J10: 1435051.2 | K10: =F10-J10 -> -231645.05 | L10: =IFERROR(F10/J10-1,0) -> -0.16141936 | N10: 18591.502 | O10: 20501.24 | P10: =N10-O10 -> -1909.7381 | Q10: =IFERROR(N10/O10-1,0) -> -0.093152322 | R10: 24134.32 | S10: =N10-R10 -> -5542.8181 | T10: =IFERROR(N10/R10-1,0) -> -0.22966539
D11: 7 | E11: Bajio | F11: 1128176.3 | G11: 1900550 | H11: =F11-G11 -> -772373.64 | I11: =IFERROR(F11/G11-1,0) -> -0.40639481 | J11: 1674568 | K11: =F11-J11 -> -546391.7 | L11: =IFERROR(F11/J11-1,0) -> -0.32628815 | N11: 17999.54 | O11: 28360.021 | P11: =N11-O11 -> -10360.481 | Q11: =IFERROR(N11/O11-1,0) -> -0.36531994 | R11: 27009.544 | S11: =N11-R11 -> -9010.004 | T11: =IFERROR(N11/R11-1,0) -> -0.33358594
F12: =SUM(F5:F11) -> 12549503 | G12: =SUM(G5:G11) -> 13960292 | H12: =F12-G12 -> -1410789.3 | I12: =IFERROR(F12/G12-1,0) -> -0.10105729 | J12: =SUM(J5:J11) -> 14960275 | K12: =F12-J12 -> -2410772.2 | L12: =IFERROR(F12/J12-1,0) -> -0.16114491 | N12: =SUM(N5:N11) -> 300486.04 | O12: =SUM(O5:O11) -> 398927.9 | P12: =N12-O12 -> -98441.867 | Q12: =IFERROR(N12/O12-1,0) -> -0.24676606 | R12: =SUM(R5:R11) -> 422206.32 | S12: =N12-R12 -> -121720.29 | T12: =IFERROR(N12/R12-1,0) -> -0.28829575
E15: PERDIDA VENTA ESSENTIA | F15: Importes | N15: Kilogramos
D16: Clave | E16: Region | F16: 2020 | G16: Pres | H16: Dif | I16: % Inc | J16: 2019 | K16: Dif | L16: % Inc | N16: 2020 | O16: Pres | P16: Dif | Q16: % Inc | R16: 2019 | S16: Dif | T16: % Inc
D17: 1 | E17: Occidente | G17: =SUM(L44:L55) -> -13505.686 | O17: =SUM(H44:H55) -> -226.5
D18: 2 | E18: Pacifico | G18: =SUM(L63:L65) -> -2698.92 | O18: =SUM(H63:H65) -> 0
D19: 3 | E19: Coordinadora de Ventas | G19: =SUM(L73:L75) -> -5879.5225 | O19: =SUM(H73:H75) -> -35
D20: 4 | E20: Cuentas Clave
D21: 5 | E21: Mexico
D22: 6 | E22: Altos Norte | G22: =SUM(L83:L89) -> -47071.41 | O22: =SUM(H83:H89) -> -332
D23: 7 | E23: Bajio | G23: =SUM(L97:L98) -> 1693.049 | O23: =SUM(H97:H98) -> -2
F24: =SUM(F17:F23) -> 0 | G24: =SUM(G17:G23) -> -67462.489 | H24: =F24-G24 -> 67462.489 | I24: =IFERROR(F24/G24-1,0) -> -1 | J24: =SUM(J17:J23) -> 0 | K24: =F24-J24 -> 0 | L24: =IFERROR(F24/J24-1,0) -> 0 | N24: =SUM(N17:N23) -> 0 | O24: =SUM(O17:O23) -> -595.5 | P24: =N24-O24 -> 595.5 | Q24: =IFERROR(N24/O24-1,0) -> -1 | R24: =SUM(R17:R23) -> 0 | S24: =N24-R24 -> 0 | T24: =IFERROR(N24/R24-1,0) -> 0
E28: PRESUPUESTO MODIFICADO | F28: Importes | N28: Kilogramos
D29: Clave | E29: Region | F29: 2020 | G29: Pres | H29: Dif | I29: % Inc | J29: 2019 | K29: Dif | L29: % Inc | N29: 2020 | O29: Pres | P29: Dif | Q29: % Inc | R29: 2019 | S29: Dif | T29: % Inc
D30: 1 | E30: Occidente | F30: =F5 -> 5313807.2 | G30: =G5+G17 -> 4780259.9 | H30: =F30-G30 -> 533547.23 | I30: =IFERROR(F30/G30-1,0) -> 0.11161469 | J30: 5842159.2 | K30: =F30-J30 -> -528351.99 | L30: =IFERROR(F30/J30-1,0) -> -0.090437794 | N30: =N5 -> 132874.53 | O30: =O5+O17 -> 158697.14 | P30: =N30-O30 -> -25822.611 | Q30: =IFERROR(N30/O30-1,0) -> -0.1627163 | R30: 173656.21 | S30: =N30-R30 -> -40781.682 | T30: =IFERROR(N30/R30-1,0) -> -0.23484148
D31: 2 | E31: Pacifico | F31: =F6 -> 1066299.4 | G31: =G6+G18 -> 2220021.1 | H31: =F31-G31 -> -1153721.8 | I31: =IFERROR(F31/G31-1,0) -> -0.51968955 | J31: 2674387.9 | K31: =F31-J31 -> -1608088.6 | L31: =IFERROR(F31/J31-1,0) -> -0.60129219 | N31: =N6 -> 16035.98 | O31: =O6+O18 -> 31844 | P31: =N31-O31 -> -15808.02 | Q31: =IFERROR(N31/O31-1,0) -> -0.49642068 | R31: 47224.03 | S31: =N31-R31 -> -31188.05 | T31: =IFERROR(N31/R31-1,0) -> -0.66042754
D32: 3 | E32: Coordinadora de Ventas | F32: =F7 -> 1569643 | G32: =G7+G19 -> 1500194.6 | H32: =F32-G32 -> 69448.355 | I32: =IFERROR(F32/G32-1,0) -> 0.046292898 | J32: 1403179.9 | K32: =F32-J32 -> 166463.05 | L32: =IFERROR(F32/J32-1,0) -> 0.11863272 | N32: =N7 -> 38260.164 | O32: =O7+O19 -> 47134 | P32: =N32-O32 -> -8873.836 | Q32: =IFERROR(N32/O32-1,0) -> -0.18826826 | R32: 36118.064 | S32: =N32-R32 -> 2142.1001 | T32: =IFERROR(N32/R32-1,0) -> 0.059308276
D33: 4 | E33: Cuentas Clave | F33: =F8 -> 2064306.8 | G33: =G8+G20 -> 2252396 | H33: =F33-G33 -> -188089.15 | I33: =IFERROR(F33/G33-1,0) -> -0.083506254 | J33: 1816329.8 | K33: =F33-J33 -> 247977.06 | L33: =IFERROR(F33/J33-1,0) -> 0.13652645 | N33: =N8 -> 76524.32 | O33: =O8+O20 -> 111960 | P33: =N33-O33 -> -35435.68 | Q33: =IFERROR(N33/O33-1,0) -> -0.31650304 | R33: 79547.88 | S33: =N33-R33 -> -3023.56 | T33: =IFERROR(N33/R33-1,0) -> -0.03800931
D34: 5 | E34: Mexico | F34: =F9 -> 203864.18 | G34: =G9+G21 -> 150047.46 | H34: =F34-G34 -> 53816.723 | I34: =IFERROR(F34/G34-1,0) -> 0.35866468 | J34: 191931.4 | K34: =F34-J34 -> 11932.78 | L34: =IFERROR(F34/J34-1,0) -> 0.062172109 | N34: =N9 -> 200 | O34: =O9+O21 -> 170 | P34: =N34-O34 -> 30 | Q34: =IFERROR(N34/O34-1,0) -> 0.17647059 | R34: 230 | S34: =N34-R34 -> -30 | T34: =IFERROR(N34/R34-1,0) -> -0.13043478
D35: 6 | E35: Altos Norte | F35: =F10+F8 -> 3267713 | G35: =+G8+G10+G22 -> 3340063.6 | H35: =F35-G35 -> -72350.613 | I35: =IFERROR(F35/G35-1,0) -> -0.021661448 | J35: =J10+J8 -> 3714737.5 | K35: =F35-J35 -> -447024.45 | L35: =IFERROR(F35/J35-1,0) -> -0.1203381 | N35: =N10+N8 -> 95115.822 | O35: =+O8+O10+O22 -> 132129.24 | P35: =N35-O35 -> -37013.418 | Q35: =IFERROR(N35/O35-1,0) -> -0.28013041 | R35: 25602.36 | S35: =N35-R35 -> 69513.462 | T35: =IFERROR(N35/R35-1,0) -> 2.7151193
D36: 7 | E36: Bajio | F36: =F11 -> 1128176.3 | G36: =G11+G23 -> 1902243 | H36: =F36-G36 -> -774066.69 | I36: =IFERROR(F36/G36-1,0) -> -0.40692313 | J36: 1359435.8 | K36: =F36-J36 -> -231259.49 | L36: =IFERROR(F36/J36-1,0) -> -0.17011431 | N36: =N11 -> 17999.54 | O36: =O11+O23 -> 28358.021 | P36: =N36-O36 -> -10358.481 | Q36: =IFERROR(N36/O36-1,0) -> -0.36527518 | R36: 24423.472 | S36: =N36-R36 -> -6423.9318 | T36: =IFERROR(N36/R36-1,0) -> -0.26302288
F37: =SUM(F30:F36) -> 14613810 | G37: =SUM(G30:G36) -> 16145226 | H37: =F37-G37 -> -1531415.9 | I37: =IFERROR(F37/G37-1,0) -> -0.094852556 | J37: =SUM(J30:J36) -> 17002161 | K37: =F37-J37 -> -2388351.6 | L37: =IFERROR(F37/J37-1,0) -> -0.14047341 | N37: =SUM(N30:N36) -> 377010.36 | O37: =SUM(O30:O36) -> 510292.4 | P37: =N37-O37 -> -133282.05 | Q37: =IFERROR(N37/O37-1,0) -> -0.2611876 | R37: =SUM(R30:R36) -> 386802.02 | S37: =N37-R37 -> -9791.6617 | T37: =IFERROR(N37/R37-1,0) -> -0.025314402
F41: ABRIL
C42: OCCIDENTE | F42: KILOS | J42: PESOS
A43: Vend | B43: Cte | C43: Nombre | D43: Código | E43: Descripcion | F43: Pres | G43: 2020 | H43: DIF | I43: % | J43: Pres | K43: 2020 | L43: DIF | M43: %
A44: 1 | B44: 009 | C44: EMPACADORA EL CENTENARIO, SA DE CV | D44: PRO5500 | E44: APROPORK BOL 25 Kg | F44: 787.5 | G44: 740 | H44: =G44-F44 -> -47.5 | I44: =IFERROR(G44/F44-1,0) -> -0.06031746 | J44: 104268.94 | K44: 116257.62 | L44: =K44-J44 -> 11988.682 | M44: =IFERROR(K44/J44-1,0) -> 0.11497847
A45: 1 | B45: 009 | C45: EMPACADORA EL CENTENARIO, SA DE CV | D45: PROAPR | E45: APRORED BOLSA 1KG | F45: 11.55 | G45: 0 | H45: =G45-F45 -> -11.55 | I45: =IFERROR(G45/F45-1,0) -> -1 | J45: 3376.1747 | K45: 0 | L45: =K45-J45 -> -3376.1747 | M45: =IFERROR(K45/J45-1,0) -> -1
A46: 1 | B46: 038 | C46: EMPACADORA BONNACARNE SA DE CV | D46: PROAPR | E46: APRORED BOLSA 1KG | F46: 21 | G46: 0 | H46: =G46-F46 -> -21 | I46: =IFERROR(G46/F46-1,0) -> -1 | J46: 6288.219 | K46: 0 | L46: =K46-J46 -> -6288.219 | M46: =IFERROR(K46/J46-1,0) -> -1
A47: 1 | B47: 099 | C47: COMERCIALIZADORA DE EMBUTIDOS ICO SA DE CV | D47: PROAPR | E47: APRORED BOLSA 1KG | F47: 14.7 | G47: 0 | H47: =G47-F47 -> -14.7 | I47: =IFERROR(G47/F47-1,0) -> -1 | J47: 4162.2021 | K47: 0 | L47: =K47-J47 -> -4162.2021 | M47: =IFERROR(K47/J47-1,0) -> -1
A48: 1 | B48: 313 | C48: CARNES FINAS DE LA SIERRA SA DE CV | D48: PROAPR | E48: APRORED BOLSA 1KG | F48: 105 | G48: 0 | H48: =G48-F48 -> -105 | I48: =IFERROR(G48/F48-1,0) -> -1 | J48: 30692.498 | K48: 0 | L48: =K48-J48 -> -30692.498 | M48: =IFERROR(K48/J48-1,0) -> -1
A49: 1 | B49: 476 | C49: OMEX ALIMENTARIA SA DE CV | D49: PROAPR | E49: APRORED BOLSA 1KG | F49: 0 | G49: 5 | H49: =G49-F49 -> 5 | I49: =IFERROR(G49/F49-1,0) -> 0 | J49: 0 | K49: 1795.22 | L49: =K49-J49 -> 1795.22 | M49: =IFERROR(K49/J49-1,0) -> 0
A50: 1 | B50: 481 | C50: GRUPO BRAVO NUÑO S.C. DE R.L. DE C.V. | D50: PROAPR | E50: APRORED BOLSA 1KG | F50: 147 | G50: 250 | H50: =G50-F50 -> 103 | I50: =IFERROR(G50/F50-1,0) -> 0.70068027 | J50: 37429.875 | K50: 76281.75 | L50: =K50-J50 -> 38851.875 | M50: =IFERROR(K50/J50-1,0) -> 1.037991
A51: 1 | B51: 485 | C51: PRODUCTOS EL GRAN CHAPARRAL SA DE CV | D51: PROAPR | E51: APRORED BOLSA 1KG | F51: 42 | G51: 20 | H51: =G51-F51 -> -22 | I51: =IFERROR(G51/F51-1,0) -> -0.52380952 | J51: 12276.999 | K51: 7134.33 | L51: =K51-J51 -> -5142.669 | M51: =IFERROR(K51/J51-1,0) -> -0.41888649
A52: 1 | B52: 553 | C52: INDUSTRIAS PECUARIAS AYENSE SPR DE RL DE CV | D52: PROAPR | E52: APRORED BOLSA 1KG | F52: 10.5 | G52: 0 | H52: =G52-F52 -> -10.5 | I52: =IFERROR(G52/F52-1,0) -> -1 | J52: 3069.2497 | K52: 0 | L52: =K52-J52 -> -3069.2497 | M52: =IFERROR(K52/J52-1,0) -> -1
A53: 1 | B53: 657 | C53: HECTOR ALONSO ZARATE QUIROZ | D53: PROAPR | E53: APRORED BOLSA 1KG | F53: 21 | G53: 0 | H53: =G53-F53 -> -21 | I53: =IFERROR(G53/F53-1,0) -> -1 | J53: 6138.4995 | K53: 0 | L53: =K53-J53 -> -6138.4995 | M53: =IFERROR(K53/J53-1,0) -> -1
A54: 1 | B54: 327 | C54: EMPACADORAS UNIDAS DE LA PIEDAD SA DE CV | D54: PRO5500 | E54: APROPORK BOL 25 Kg | F54: 131.25 | G54: 40 | H54: =G54-F54 -> -91.25 | I54: =IFERROR(G54/F54-1,0) -> -0.6952381 | J54: 16977.122 | K54: 6254.24 | L54: =K54-J54 -> -10722.882 | M54: =IFERROR(K54/J54-1,0) -> -0.63160776
A55: 1 | B55: 657 | C55: HECTOR ALONSO ZARATE QUIROZ | D55: PROAPR10 | E55: COM0213 APRORED BOLSA 10KG | F55: 0 | G55: 10 | H55: =G55-F55 -> 10 | I55: =IFERROR(G55/F55-1,0) -> 0 | J55: 0 | K55: 3450.93 | L55: =K55-J55 -> 3450.93 | M55: =IFERROR(K55/J55-1,0) -> 0
F56: =SUM(F44:F55) -> 1291.5 | G56: =SUM(G44:G55) -> 1065 | H56: =SUM(H44:H55) -> -226.5 | I56: =H56/F56 -> -0.17537747 | J56: =SUM(J44:J55) -> 224679.78 | K56: =SUM(K44:K55) -> 211174.09 | L56: =SUM(L44:L55) -> -13505.686 | M56: =L56/J56 -> -0.060110822
F60: ABRIL
C61: PACIFICO | F61: KILOS | J61: PESOS
A62: Vend | B62: Cte | C62: Nombre | D62: Código | E62: Descripcion | F62: Pres | G62: 2020 | H62: DIF | I62: % | J62: Pres | K62: 2020 | L62: DIF | M62: %
A63: 2 | B63: 012 | C63: KAREY ALIMENTOS, SA DE CV | D63: PROAPR | E63: APRORED BOLSA 1KG | F63: 20 | G63: 0 | H63: =G63-F63 -> -20 | I63: =IFERROR(G63/F63-1,0) -> -1 | J63: 5846.19 | K63: 0 | L63: =K63-J63 -> -5846.19 | M63: =IFERROR(K63/J63-1,0) -> -1
A64: 2 | B64: 773 | C64: JESUS ALBERTO BERNAL GARCIA | D64: PRO5500 | E64: APROPORK BOL 20 Kg | F64: 0 | G64: 20 | H64: =G64-F64 -> 20 | I64: =IFERROR(G64/F64-1,0) -> 0 | J64: 0 | K64: 3147.27 | L64: =K64-J64 -> 3147.27 | M64: =IFERROR(K64/J64-1,0) -> 0
A65: 2 | F65: 0 | G65: 0 | H65: =G65-F65 -> 0 | I65: =IFERROR(G65/F65-1,0) -> 0 | J65: 0 | L65: =K65-J65 -> 0 | M65: =IFERROR(K65/J65-1,0) -> 0
F66: =SUM(F63:F65) -> 20 | G66: =SUM(G63:G65) -> 20 | H66: =SUM(H63:H65) -> 0 | I66: =H66/F66 -> 0 | J66: =SUM(J63:J65) -> 5846.19 | K66: =SUM(K63:K65) -> 3147.27 | L66: =SUM(L63:L65) -> -2698.92 | M66: =L66/J66 -> -0.46165451
F70: ABRIL
C71: COORDINADORA DE VENTAS | F71: KILOS | J71: PESOS
A72: Vend | B72: Cte | C72: Nombre | D72: Código | E72: Descripcion | F72: Pres | G72: 2020 | H72: DIF | I72: % | J72: Pres | K72: 2020 | L72: DIF | M72: %
A73: 3 | B73: 518 | C73: INTEGRADORA PECUARIA GURMA S.P.R. DE R.L. DE C.V. | D73: PROAPR | E73: APRORED BOLSA 1KG | F73: 5 | G73: 0 | H73: =G73-F73 -> -5 | I73: =IFERROR(G73/F73-1,0) -> -1 | J73: 1461.5475 | K73: 0 | L73: =K73-J73 -> -1461.5475 | M73: =IFERROR(K73/J73-1,0) -> -1
A74: 3 | B74: 601 | C74: VILLESPA, SPR DE RL | D74: PROAPR | E74: APRORED BOLSA 1KG | F74: 30 | G74: 20 | H74: =G74-F74 -> -10 | I74: =IFERROR(G74/F74-1,0) -> -0.33333333 | J74: 8769.285 | K74: 6999.41 | L74: =K74-J74 -> -1769.875 | M74: =IFERROR(K74/J74-1,0) -> -0.2018266
A75: 3 | B75: 103 | C75: MARIA ESTHER JAUREGUI VELASCO | D75: PRO5500 | E75: APROPORK BOL 20 Kg | F75: 20 | G75: 0 | H75: =G75-F75 -> -20 | I75: =IFERROR(G75/F75-1,0) -> -1 | J75: 2648.1 | K75: 0 | L75: =K75-J75 -> -2648.1 | M75: =IFERROR(K75/J75-1,0) -> -1
F76: =SUM(F73:F75) -> 55 | G76: =SUM(G73:G75) -> 20 | H76: =SUM(H73:H75) -> -35 | I76: =H76/F76 -> -0.63636364 | J76: =SUM(J73:J75) -> 12878.933 | K76: =SUM(K73:K75) -> 6999.41 | L76: =SUM(L73:L75) -> -5879.5225 | M76: =L76/J76 -> -0.4565225
F80: ABRIL
C81: ALTOS NORTE | F81: KILOS | J81: PESOS
A82: Vend | B82: Cte | C82: Nombre | D82: Código | E82: Descripcion | F82: Pres | G82: 2020 | H82: DIF | I82: % | J82: Pres | K82: 2020 | L82: DIF | M82: %
A83: 6 | B83: 013 | C83: EMBUTIDOS SUPREMOS, SA DE CV | D83: PROAPR | E83: APRORED BOLSA 1KG | F83: 5 | G83: 5 | H83: =G83-F83 -> 0 | I83: =IFERROR(G83/F83-1,0) -> 0 | J83: 1461.5475 | K83: 1714.91 | L83: =K83-J83 -> 253.3625 | M83: =IFERROR(K83/J83-1,0) -> 0.17335222
A84: 6 | B84: 030 | C84: EMPACADORA ESTRELLA, SA DE CV | D84: PROAPR | E84: APRORED BOLSA 1KG | F84: 5 | G84: 5 | H84: =G84-F84 -> 0 | I84: =IFERROR(G84/F84-1,0) -> 0 | J84: 1427.937 | K84: 1675.47 | L84: =K84-J84 -> 247.533 | M84: =IFERROR(K84/J84-1,0) -> 0.17335008
A85: 6 | B85: 340 | C85: PRODUCTOS JAMEX SA DE CV | D85: PROAPR | E85: APRORED BOLSA 1KG | F85: 100 | G85: 0 | H85: =G85-F85 -> -100 | I85: =IFERROR(G85/F85-1,0) -> -1 | J85: 29230.95 | K85: 0 | L85: =K85-J85 -> -29230.95 | M85: =IFERROR(K85/J85-1,0) -> -1
A86: 6 | B86: 515 | C86: CARNES SELECTAS EL CIEN, SA DE CV | D86: PROAPR | E86: APRORED BOLSA 1KG | F86: 40 | G86: 68 | H86: =G86-F86 -> 28 | I86: =IFERROR(G86/F86-1,0) -> 0.7 | J86: 11692.38 | K86: 23896.19 | L86: =K86-J86 -> 12203.81 | M86: =IFERROR(K86/J86-1,0) -> 1.0437405
A87: 6 | B87: 037 | C87: MAXIM ALIMENTOS SA DE CV | D87: PRO5500 | E87: APROPORK BOL 25 Kg | F87: 180 | G87: 80 | H87: =G87-F87 -> -100 | I87: =IFERROR(G87/F87-1,0) -> -0.55555556 | J87: 22916.25 | K87: 12243.45 | L87: =K87-J87 -> -10672.8 | M87: =IFERROR(K87/J87-1,0) -> -0.46573065
A88: 6 | B88: 708 | C88: EVANGELINA BAUTISTA SANCHEZ | D88: PROAPR | E88: APRORED BOLSA 1KG | F88: 10 | G88: 0 | H88: =G88-F88 -> -10 | I88: =IFERROR(G88/F88-1,0) -> -1 | J88: 2923.095 | K88: 0 | L88: =K88-J88 -> -2923.095 | M88: =IFERROR(K88/J88-1,0) -> -1
A89: 6 | B89: 515 | C89: CARNES SELECTAS EL CIEN, SA DE CV | D89: PRO5500 | E89: APROPORK BOL 25 Kg | F89: 250 | G89: 100 | H89: =G89-F89 -> -150 | I89: =IFERROR(G89/F89-1,0) -> -0.6 | J89: 33101.25 | K89: 16151.98 | L89: =K89-J89 -> -16949.27 | M89: =IFERROR(K89/J89-1,0) -> -0.5120432
F90: =SUM(F83:F89) -> 590 | G90: =SUM(G83:G89) -> 258 | H90: =SUM(H83:H89) -> -332 | I90: =H90/F90 -> -0.56271186 | J90: =SUM(J83:J89) -> 102753.41 | K90: =SUM(K83:K89) -> 55682 | L90: =SUM(L83:L89) -> -47071.41 | M90: =L90/J90 -> -0.45810071
F94: ABRIL
C95: BAJIO | F95: KILOS | J95: PESOS
A96: Vend | B96: Cte | C96: Nombre | D96: Código | E96: Descripcion | F96: Pres | G96: 2020 | H96: DIF | I96: % | J96: Pres | K96: 2020 | L96: DIF | M96: %
A97: 7 | B97: 093 | C97: EMPACADORA CELAYA SA DE CV | D97: PROAPR10 | E97: COM0213 APRORED BOLSA 10KG | F97: 42 | G97: 40 | H97: =G97-F97 -> -2 | I97: =IFERROR(G97/F97-1,0) -> -0.047619048 | J97: 12105.891 | K97: 13798.94 | L97: =K97-J97 -> 1693.049 | M97: =IFERROR(K97/J97-1,0) -> 0.13985332
A98: 7 | B98: 542 | C98: NESTOR LOZA QUISTIANO | D98: PROAPR | E98: APRORED BOLSA 1KG | F98: 0 | G98: 0 | H98: =G98-F98 -> 0 | I98: =IFERROR(G98/F98-1,0) -> 0 | J98: 0 | K98: 0 | L98: =K98-J98 -> 0 | M98: =IFERROR(K98/J98-1,0) -> 0
F99: =SUM(F97:F98) -> 42 | G99: =SUM(G97:G98) -> 40 | H99: =SUM(H97:H98) -> -2 | I99: =H99/F99 -> -0.047619048 | J99: =SUM(J97:J98) -> 12105.891 | K99: =SUM(K97:K98) -> 13798.94 | L99: =SUM(L97:L98) -> 1693.049 | M99: =L99/J99 -> 0.13985332

Sheet MAYO
C1: CALCULO DE BONOS MAYO
C3: REGION OCCIDENTE
C5: KILOS | E5: Variacion | G5: PESOS | I5: Variacion
B6: MES | C6: Presupuesto | D6: Real | E6: KG | F6: % | G6: Presupuesto | H6: Real | I6: $ | J6: %
B7: MAYO | C7: ='ESSENTIA MAYO'!O30 -> 163628.76 | D7: ='ESSENTIA MAYO'!N30 -> 145456.34 | E7: =D7-C7 -> -18172.42 | F7: =D7/C7-1 -> -0.11105884 | G7: ='ESSENTIA MAYO'!G30 -> 5170577 | H7: ='ESSENTIA MAYO'!F30 -> 4759735 | I7: =H7-G7 -> -410842 | J7: =H7/G7-1 -> -0.079457668
B9: COMPOSICION BONO | G9: ALCANCE DE OBJETIVOS
B10: Bono | C10: Concepto | D10: % Bono | E10: Monto | G10: Concepto | H10: Presupuesto | I10: Real | J10: % Cobertura | K10: Bono | M10: Objetivo Minimo
B11: 12000 | C11: Cumplimiento Presupuesto | D11: 0.7 | E11: =B11*D11 -> 8400 | G11: Cumplimiento Presupuesto | H11: =G7 -> 5170577 | I11: =H7 -> 4759735 | J11: =IFERROR(I11/H11,0) -> 0.92054233 | K11: =IF(J11<M11,0,J11*$E11) -> 7732.5556 | M11: 0.9
C12: Cierre de 3 pedidos 1000 Kgcon clientes actuales de FMC | D12: 0.12 | E12: =B11*D12 -> 1440 | G12: =C12 -> Cierre de 3 pedidos 1000 Kgcon clientes actuales de FMC | H12: 1 | J12: =I12/H12 -> 0 | K12: =IF(J12<M12,0,J12*$E12) -> 0 | M12: 0.8
C13: Contar con calendario de pruebas inicios de año 2020 | D13: 0.05 | E13: =B$11*D$13 -> 600 | G13: =C13 -> Contar con calendario de pruebas inicios de año 2020 | H13: 1 | J13: =I13/H13 -> 0 | K13: =IF(J13<M13,0,J13*$E13) -> 0 | M13: 1
C14: Presentar estrategica por region Occidente 2020 | D14: 0.05 | E14: =B$11*D$13 -> 600 | G14: =C14 -> Presentar estrategica por region Occidente 2020 | H14: 1 | J14: =I14/H14 -> 0 | K14: =IF(J14<M14,0,J14*$E14) -> 0 | M14: 0.75
C15: Presentar presupuesto lunes 6 de Diciembre | D15: 0.08 | E15: =B11*D15 -> 960 | G15: =C15 -> Presentar presupuesto lunes 6 de Diciembre | H15: 1 | J15: =I15/H15 -> 0 | K15: =IF(J15<M15,0,J15*$E15) -> 0 | M15: 0.75
C16: Total | D16: =SUM(D11:D15) -> 1 | E16: =SUM(E11:E15) -> 12000 | J16: Total sin Presupuesto | K16: =SUM(K12:K15) -> 0
J18: TOTAL | K18: =+K16+K11 -> 7732.5556
C24: REGION PACIFICO
C26: KILOS | E26: Variacion | G26: PESOS | I26: Variacion
B27: MES | C27: Presupuesto | D27: Real | E27: KG | F27: % | G27: Presupuesto | H27: Real | I27: $ | J27: %
B28: =$B$7 -> MAYO | C28: ='ESSENTIA MAYO'!O31 -> 36553 | D28: ='ESSENTIA MAYO'!N31 -> 23178.992 | E28: =D28-C28 -> -13374.008 | F28: =D28/C28-1 -> -0.3658799 | G28: ='ESSENTIA MAYO'!G31 -> 2421147.9 | H28: ='ESSENTIA MAYO'!F31 -> 1727675.3 | I28: =H28-G28 -> -693472.62 | J28: =H28/G28-1 -> -0.28642308
B30: COMPOSICION BONO
B31: Bono | C31: Concepto | D31: % Bono | E31: Monto | F31: Objetivo Minimo | G31: Concepto | H31: Presupuesto | I31: Real | J31: % Cobertura | K31: Bono | M31: Objetivo Minimo
B32: 1000 | C32: Cumplimiento Presupuesto | D32: =E32/$B$37 -> 0.15384615 | E32: 1000 | F32: 0.5 | G32: =C32 -> Cumplimiento Presupuesto | H32: =G28 -> 2421147.9 | I32: =H28 -> 1727675.3 | J32: =IFERROR(I32/H32,0) -> 0.71357692 | K32: =IF(J32<M32,0,J32*$E32) -> 713.57692 | M32: 0.5
B33: 1000 | C33: Pruebas atorizadas por realizar con cliente | D33: =E33/$B$37 -> 0.15384615 | E33: 1000 | F33: 1 | G33: =C33 -> Pruebas atorizadas por realizar con cliente | H33: 1 | J33: =IFERROR(I33/H33,0) -> 0 | K33: =IF(J33<M33,0,J33*$E33) -> 0 | M33: 1
B34: 1500 | C34: Armado e implementación estrategia Baja California | D34: =E34/$B$37 -> 0.23076923 | E34: 1500 | F34: 1 | G34: =C34 -> Armado e implementación estrategia Baja California | H34: 1 | J34: =IFERROR(I34/H34,0) -> 0 | K34: =IF(J34<M34,0,J34*$E34) -> 0 | M34: 1
B35: 1500 | C35: Presentar estrategica por región 2020 | D35: =E35/$B$37 -> 0.23076923 | E35: 1500 | F35: 0.75 | G35: =C35 -> Presentar estrategica por región 2020 | H35: 1 | J35: =IFERROR(I35/H35,0) -> 0 | K35: =IF(J35<M35,0,J35*$E35) -> 0 | M35: 0.75
B36: 1500 | C36: Presentar presupuesto lunes 6 de Diciembre | D36: =E36/$B$37 -> 0.23076923 | E36: 1500 | F36: 0.75 | G36: =C36 -> Presentar presupuesto lunes 6 de Diciembre | H36: 1 | J36: =IFERROR(I36/H36,0) -> 0 | K36: =IF(J36<M36,0,J36*$E36) -> 0 | M36: 0.75
B37: =SUM(B32:B36) -> 6500 | C37: Total | E37: =SUM(E31:E36) -> 6500 | J37: Total sin Presupuesto | K37: =SUM(K34:K34) -> 0
J39: TOTAL | K39: =+K37+K32 -> 713.57692
C43: REGION BAJIO
C45: KILOS | E45: Variacion | G45: PESOS | I45: Variacion
B46: MES | C46: Presupuesto | D46: Real | E46: KG | F46: % | G46: Presupuesto | H46: Real | I46: $ | J46: %
B47: =$B$7 -> MAYO | C47: ='ESSENTIA MAYO'!O36 -> 28902.142 | D47: ='ESSENTIA MAYO'!N36 -> 26639.24 | E47: =D47-C47 -> -2262.902 | F47: =D47/C47-1 -> -0.078295304 | G47: ='ESSENTIA MAYO'!G36 -> 1694685.6 | H47: ='ESSENTIA MAYO'!F36 -> 1452368.4 | I47: =H47-G47 -> -242317.2 | J47: =H47/G47-1 -> -0.14298652
B49: COMPOSICION BONO | G49: ALCANCE DE OBJETIVOS
B50: Bono | C50: Concepto | D50: % Bono | E50: Monto | G50: Concepto | H50: Presupuesto | I50: Real | J50: % Cobertura | K50: Bono
B51: 7000 | C51: Cumplimiento Presupuesto | D51: 0.5 | E51: =B51*D51 -> 3500 | G51: =C51 -> Cumplimiento Presupuesto | H51: =G47 -> 1694685.6 | I51: =H47 -> 1452368.4 | J51: =IFERROR(I51/H51,0) -> 0.85701348 | K51: =IF(J51<M52,0,J51*$E51) -> 0 | M51: Objetivo Minimo
C52: Aplicación de pruebas unidades de chorizo | D52: 0.2 | E52: =B51*D52 -> 1400 | G52: =C52 -> Aplicación de pruebas unidades de chorizo | H52: 1 | J52: =IFERROR(I52/H52,0) -> 0 | K52: =IF(J52<M53,0,J52*$E52) -> 0 | M52: 0.95
C53: Prospectación | D53: 0.2 | E53: =B51*D53 -> 1400 | G53: =C53 -> Prospectación | H53: 1 | J53: =IFERROR(I53/H53,0) -> 0 | K53: =IF(J53<M54,0,J53*$E53) -> 0 | M53: 0.75
C54: Cierre de venta con productos nuevos AGR | D54: 0.1 | E54: =+D54*B51 -> 700 | G54: =C54 -> Cierre de venta con productos nuevos AGR | H54: 1 | J54: =IFERROR(I54/H54,0) -> 0 | K54: =IF(J54<M55,0,J54*$E54) -> 0 | M54: 0.75
C55: Total | D55: =SUM(D51:D54) -> 1 | E55: =SUM(E51:E54) -> 7000 | J55: Total sin Presupuesto | K55: =SUM(K52:K54) -> 0 | M55: 0.75
J57: TOTAL | K57: =+K55+K51 -> 0
C61: ALTOS NORTE
C63: KILOS | E63: Variacion | G63: PESOS | I63: Variacion
B64: MES | C64: Presupuesto | D64: Real | E64: KG | F64: % | G64: Presupuesto | H64: Real | I64: $ | J64: %
B65: =$B$7 -> MAYO | C65: ='ESSENTIA MAYO'!O35 -> 119122.81 | D65: ='ESSENTIA MAYO'!N35 -> 68281.326 | E65: =D65-C65 -> -50841.484 | F65: =D65/C65-1 -> -0.4267989 | G65: ='ESSENTIA MAYO'!G35 -> 3334340.5 | H65: ='ESSENTIA MAYO'!F35 -> 2351766.2 | I65: =H65-G65 -> -982574.29 | J65: =H65/G65-1 -> -0.29468325
B67: COMPOSICION BONO | G67: ALCANCE DE OBJETIVOS
B68: Bono | C68: Concepto | D68: % Bono | E68: Monto | G68: Concepto | H68: Presupuesto | I68: Real | J68: % Cobertura | K68: Bono | M68: Objetivo Minimo
B69: 10000 | C69: Cumplimiento Presupuesto | D69: 0.6 | E69: =+D69*B69 -> 6000 | G69: =C69 -> Cumplimiento Presupuesto | H69: =G65 -> 3334340.5 | I69: =H65 -> 2351766.2 | J69: =IFERROR(I69/H69,0) -> 0.70531675 | K69: =IF(J69<M69,0,J69*$E69) -> 0 | M69: 0.8
C70: Cierre de 3 pedidos 300 Kgcon clientes actuales de FMC | D70: 0.1 | E70: =B69*D70 -> 1000 | G70: =C70 -> Cierre de 3 pedidos 300 Kgcon clientes actuales de FMC | H70: 1 | J70: =I70/H70 -> 0 | K70: =IF(J70<M70,0,J70*$E70) -> 0 | M70: 0.8
C71: Contar con calendario de pruebas inicios de año 2020 | D71: 0.12 | E71: =+D71*B69 -> 1200 | G71: =C71 -> Contar con calendario de pruebas inicios de año 2020 | H71: 1 | J71: =IFERROR(I71/H71,0) -> 0 | K71: =IF(J71<M71,0,J71*$E71) -> 0 | M71: 1
C72: Presentar estrategica por region 2020 | D72: 0.07 | E72: =+D72*B69 -> 700 | G72: =C72 -> Presentar estrategica por region 2020 | H72: 1 | J72: =IFERROR(I72/H72,0) -> 0 | K72: =IF(J72<M72,0,J72*$E72) -> 0 | M72: 1
C73: Presentar presupuesto lunes 6 de Diciembre | D73: 0.11 | E73: =+D73*B69 -> 1100 | G73: =C73 -> Presentar presupuesto lunes 6 de Diciembre | H73: 1 | J73: =IFERROR(I73/H73,0) -> 0 | K73: =IF(J73<M73,0,J73*$E73) -> 0 | M73: 1
C74: Total | D74: =SUM(D69:D73) -> 1 | E74: =SUM(E69:E73) -> 10000 | J74: Total sin Presupuesto | K74: =SUM(K70:K73) -> 0
J76: TOTAL | K76: =+K74+K69 -> 0
C80: COORDINACION DE VENTAS
C82: KILOS | E82: Variacion | G82: PESOS | I82: Variacion
B83: MES | C83: Presupuesto | D83: Real | E83: KG | F83: % | G83: Presupuesto | H83: Real | I83: $ | J83: %
B84: =$B$7 -> MAYO | C84: ='ESSENTIA MAYO'!O32 -> 62012.44 | D84: ='ESSENTIA MAYO'!N32 -> 27229.58 | E84: =D84-C84 -> -34782.86 | F84: =D84/C84-1 -> -0.56090133 | G84: ='ESSENTIA MAYO'!G32 -> 1921652.6 | H84: ='ESSENTIA MAYO'!F32 -> 1230584 | I84: =H84-G84 -> -691068.64 | J84: =H84/G84-1 -> -0.35962205
B86: COMPOSICION BONO | G86: ALCANCE DE OBJETIVOS
B87: Bono | C87: Concepto | D87: % Bono | E87: Monto | G87: Concepto | H87: Presupuesto | I87: Real | J87: % Cobertura | K87: Bono | M87: Objetivo Minimo
C88: Cumplimiento Presupuesto | D88: 1 | E88: =+D88*B88 -> 0 | G88: =C88 -> Cumplimiento Presupuesto | H88: =G84 -> 1921652.6 | I88: =H84 -> 1230584 | J88: =IFERROR(I88/H88,0) -> 0.64037795 | K88: =IF(J88<M88,0,J88*$E88) -> 0 | M88: 0.8
E89: =B88*D89 -> 0 | G89: =C89 -> 0 | H89: 1 | J89: =I89/H89 -> 0 | K89: =IF(J89<M89,0,J89*$E89) -> 0 | M89: 0.8
E90: =+D90*B88 -> 0 | G90: =C90 -> 0 | H90: 1 | J90: =IFERROR(I90/H90,0) -> 0 | K90: =IF(J90<M90,0,J90*$E90) -> 0 | M90: 1
E91: =+D91*B88 -> 0 | G91: =C91 -> 0 | H91: 1 | J91: =IFERROR(I91/H91,0) -> 0 | K91: =IF(J91<M91,0,J91*$E91) -> 0 | M91: 1
E92: =+D92*B88 -> 0 | G92: =C92 -> 0 | H92: 1 | J92: =IFERROR(I92/H92,0) -> 0 | K92: =IF(J92<M92,0,J92*$E92) -> 0 | M92: 1
C93: Total | D93: =SUM(D88:D92) -> 1 | E93: =SUM(E88:E92) -> 0 | J93: Total sin Presupuesto | K93: =SUM(K89:K92) -> 0
J95: TOTAL | K95: =+K93+K88 -> 0
N170: 3 | O170: 3.1 | P170: =+O170-N170 -> 0.1 | Q170: =+P170/O170 -> 0.032258065
P174: =2000*3*12 -> 72000
P177: =2000*12 -> 24000

Sheet ESSENTIA MAYO
E3: PRESUPUESTO ORIGINAL | F3: Importes | N3: Kilogramos
D4: Clave | E4: Region | F4: 2020 | G4: Pres | H4: Dif | I4: % Inc | J4: 2019 | K4: Dif | L4: % Inc | N4: 2020 | O4: Pres | P4: Dif | Q4: % Inc | R4: 2019 | S4: Dif | T4: % Inc
D5: 1 | E5: Occidente | F5: 4759735 | G5: 5222673.8 | H5: -462938.75 | I5: -0.088640181 | J5: 6271545.1 | K5: -1511810 | L5: -0.24105862 | N5: 145456.34 | O5: 163834.11 | P5: -18377.77 | Q5: -0.11217304 | R5: 192081.38 | S5: -46625.044 | T5: -0.24273589
D6: 2 | E6: Pacifico | F6: 1727675.3 | G6: 2421147.9 | H6: -693472.62 | I6: -0.28642308 | J6: 4500988.4 | K6: -2773313.1 | L6: -0.61615647 | N6: 23178.992 | O6: 36553 | P6: -13374.008 | Q6: -0.3658799 | R6: 76959.84 | S6: -53780.848 | T6: -0.69881704
D7: 3 | E7: Coord Ventas | F7: 1230584 | G7: 1926823.8 | H7: -696239.82 | I7: -0.36134068 | J7: 1786123.8 | K7: -555539.79 | L7: -0.31103096 | N7: 27229.58 | O7: 62035.44 | P7: -34805.86 | Q7: -0.56106413 | R7: 57409.095 | S7: -30179.515 | T7: -0.52569223
D8: 4 | E8: Cuentas Clave | F8: 1019534.2 | G8: 2035056.7 | H8: -1015522.5 | I8: -0.49901434 | J8: 2401929.9 | K8: -1382395.7 | L8: -0.57553541 | N8: 46994.84 | O8: 97410.2 | P8: -50415.36 | Q8: -0.5175573 | R8: 119432.52 | S8: -72437.68 | T8: -0.60651555
D9: 5 | E9: Mexico | F9: 51637.01 | G9: 105915.85 | H9: -54278.842 | I9: -0.51247137 | J9: 150475.75 | K9: -98838.74 | L9: -0.65684165 | N9: 50 | O9: 120 | P9: -70 | Q9: -0.58333333 | R9: 180 | S9: -130 | T9: -0.72222222
D10: 6 | E10: Altos Norte | F10: 1332232 | G10: 1363846.5 | H10: -31614.523 | I10: -0.023180411 | J10: 1472631.9 | K10: -140399.92 | L10: -0.095339454 | N10: 21286.486 | O10: 21942.61 | P10: -656.124 | Q10: -0.029901821 | R10: 22572.625 | S10: -1286.139 | T10: -0.056977822
D11: 7 | E11: Bajio | F11: 1452368.4 | G11: 1740218.6 | H11: -287850.15 | I11: -0.16541034 | J11: 1554864.5 | K11: -102496.07 | L11: -0.065919616 | N11: 26639.24 | O11: 29061.692 | P11: -2422.452 | Q11: -0.083355504 | R11: 27677.802 | S11: -1038.5619 | T11: -0.03752328
F12: =SUM(F5:F11) -> 11573766 | G12: =SUM(G5:G11) -> 14815683 | H12: =F12-G12 -> -3241917.2 | I12: =IFERROR(F12/G12-1,0) -> -0.21881658 | J12: =SUM(J5:J11) -> 18138559 | K12: =F12-J12 -> -6564793.4 | L12: =IFERROR(F12/J12-1,0) -> -0.36192474 | N12: =SUM(N5:N11) -> 290835.47 | O12: =SUM(O5:O11) -> 410957.05 | P12: =N12-O12 -> -120121.57 | Q12: =IFERROR(N12/O12-1,0) -> -0.29229715 | R12: =SUM(R5:R11) -> 496313.26 | S12: =N12-R12 -> -205477.79 | T12: =IFERROR(N12/R12-1,0) -> -0.41400826
E15: PERDIDA VENTA ESSENTIA | F15: Importes | N15: Kilogramos
D16: Clave | E16: Region | F16: 2020 | G16: Pres | H16: Dif | I16: % Inc | J16: 2019 | K16: Dif | L16: % Inc | N16: 2020 | O16: Pres | P16: Dif | Q16: % Inc | R16: 2019 | S16: Dif | T16: % Inc
D17: 1 | E17: Occidente | G17: =SUM(L44:L55) -> -52096.754 | O17: =SUM(H44:H55) -> -205.35
D18: 2 | E18: Pacifico
D19: 3 | E19: Coordinadora de Ventas | G19: =SUM(L73:L76) -> -5171.1775 | O19: =SUM(H73:H76) -> -23
D20: 4 | E20: Cuentas Clave
D21: 5 | E21: Mexico
D22: 6 | E22: Altos Norte | G22: =SUM(L84:L90) -> -64562.694 | O22: =SUM(H84:H90) -> -230
D23: 7 | E23: Bajio | G23: =SUM(L98:L101) -> -45532.953 | O23: =SUM(H98:H101) -> -159.55
F24: =SUM(F17:F23) -> 0 | G24: =SUM(G17:G23) -> -167363.58 | H24: =F24-G24 -> 167363.58 | I24: =IFERROR(F24/G24-1,0) -> -1 | J24: =SUM(J17:J23) -> 0 | K24: =F24-J24 -> 0 | L24: =IFERROR(F24/J24-1,0) -> 0 | N24: =SUM(N17:N23) -> 0 | O24: =SUM(O17:O23) -> -617.9 | P24: =N24-O24 -> 617.9 | Q24: =IFERROR(N24/O24-1,0) -> -1 | R24: =SUM(R17:R23) -> 0 | S24: =N24-R24 -> 0 | T24: =IFERROR(N24/R24-1,0) -> 0
E28: PRESUPUESTO MODIFICADO | F28: Importes | N28: Kilogramos
D29: Clave | E29: Region | F29: 2020 | G29: Pres | H29: Dif | I29: % Inc | J29: 2019 | K29: Dif | L29: % Inc | N29: 2020 | O29: Pres | P29: Dif | Q29: % Inc | R29: 2019 | S29: Dif | T29: % Inc
D30: 1 | E30: Occidente | F30: =F5 -> 4759735 | G30: =G5+G17 -> 5170577 | H30: =F30-G30 -> -410842 | I30: =IFERROR(F30/G30-1,0) -> -0.079457668 | J30: 5842159.2 | K30: =F30-J30 -> -1082424.1 | L30: =IFERROR(F30/J30-1,0) -> -0.18527809 | N30: =N5 -> 145456.34 | O30: =O5+O17 -> 163628.76 | P30: =N30-O30 -> -18172.42 | Q30: =IFERROR(N30/O30-1,0) -> -0.11105884 | R30: 173656.21 | S30: =N30-R30 -> -28199.876 | T30: =IFERROR(N30/R30-1,0) -> -0.1623891
D31: 2 | E31: Pacifico | F31: =F6 -> 1727675.3 | G31: =G6+G18 -> 2421147.9 | H31: =F31-G31 -> -693472.62 | I31: =IFERROR(F31/G31-1,0) -> -0.28642308 | J31: 2674387.9 | K31: =F31-J31 -> -946712.65 | L31: =IFERROR(F31/J31-1,0) -> -0.35399227 | N31: =N6 -> 23178.992 | O31: =O6+O18 -> 36553 | P31: =N31-O31 -> -13374.008 | Q31: =IFERROR(N31/O31-1,0) -> -0.3658799 | R31: 47224.03 | S31: =N31-R31 -> -24045.038 | T31: =IFERROR(N31/R31-1,0) -> -0.50916954
D32: 3 | E32: Coordinadora de Ventas | F32: =F7 -> 1230584 | G32: =G7+G19 -> 1921652.6 | H32: =F32-G32 -> -691068.64 | I32: =IFERROR(F32/G32-1,0) -> -0.35962205 | J32: 1403179.9 | K32: =F32-J32 -> -172595.95 | L32: =IFERROR(F32/J32-1,0) -> -0.12300344 | N32: =N7 -> 27229.58 | O32: =O7+O19 -> 62012.44 | P32: =N32-O32 -> -34782.86 | Q32: =IFERROR(N32/O32-1,0) -> -0.56090133 | R32: 36118.064 | S32: =N32-R32 -> -8888.4839 | T32: =IFERROR(N32/R32-1,0) -> -0.24609525
D33: 4 | E33: Cuentas Clave | F33: =F8 -> 1019534.2 | G33: =G8+G20 -> 2035056.7 | H33: =F33-G33 -> -1015522.5 | I33: =IFERROR(F33/G33-1,0) -> -0.49901434 | J33: 1816329.8 | K33: =F33-J33 -> -796795.56 | L33: =IFERROR(F33/J33-1,0) -> -0.43868442 | N33: =N8 -> 46994.84 | O33: =O8+O20 -> 97410.2 | P33: =N33-O33 -> -50415.36 | Q33: =IFERROR(N33/O33-1,0) -> -0.5175573 | R33: 79547.88 | S33: =N33-R33 -> -32553.04 | T33: =IFERROR(N33/R33-1,0) -> -0.40922574
D34: 5 | E34: Mexico | F34: =F9 -> 51637.01 | G34: =G9+G21 -> 105915.85 | H34: =F34-G34 -> -54278.842 | I34: =IFERROR(F34/G34-1,0) -> -0.51247137 | J34: 191931.4 | K34: =F34-J34 -> -140294.39 | L34: =IFERROR(F34/J34-1,0) -> -0.73096111 | N34: =N9 -> 50 | O34: =O9+O21 -> 120 | P34: =N34-O34 -> -70 | Q34: =IFERROR(N34/O34-1,0) -> -0.58333333 | R34: 230 | S34: =N34-R34 -> -180 | T34: =IFERROR(N34/R34-1,0) -> -0.7826087
D35: 6 | E35: Altos Norte | F35: =F10+F8 -> 2351766.2 | G35: =+G8+G10+G22 -> 3334340.5 | H35: =F35-G35 -> -982574.29 | I35: =IFERROR(F35/G35-1,0) -> -0.29468325 | J35: =J10+J8 -> 3874561.8 | K35: =F35-J35 -> -1522795.6 | L35: =IFERROR(F35/J35-1,0) -> -0.39302396 | N35: =N10+N8 -> 68281.326 | O35: =+O8+O10+O22 -> 119122.81 | P35: =N35-O35 -> -50841.484 | Q35: =IFERROR(N35/O35-1,0) -> -0.4267989 | R35: 25602.36 | S35: =N35-R35 -> 42678.966 | T35: =IFERROR(N35/R35-1,0) -> 1.6669935
D36: 7 | E36: Bajio | F36: =F11 -> 1452368.4 | G36: =G11+G23 -> 1694685.6 | H36: =F36-G36 -> -242317.2 | I36: =IFERROR(F36/G36-1,0) -> -0.14298652 | J36: 1359435.8 | K36: =F36-J36 -> 92932.61 | L36: =IFERROR(F36/J36-1,0) -> 0.068361161 | N36: =N11 -> 26639.24 | O36: =O11+O23 -> 28902.142 | P36: =N36-O36 -> -2262.902 | Q36: =IFERROR(N36/O36-1,0) -> -0.078295304 | R36: 24423.472 | S36: =N36-R36 -> 2215.7682 | T36: =IFERROR(N36/R36-1,0) -> 0.0907229
F37: =SUM(F30:F36) -> 12593300 | G37: =SUM(G30:G36) -> 16683376 | H37: =F37-G37 -> -4090076 | I37: =IFERROR(F37/G37-1,0) -> -0.24515877 | J37: =SUM(J30:J36) -> 17161986 | K37: =F37-J37 -> -4568685.7 | L37: =IFERROR(F37/J37-1,0) -> -0.26620962 | N37: =SUM(N30:N36) -> 337830.31 | O37: =SUM(O30:O36) -> 507749.35 | P37: =N37-O37 -> -169919.03 | Q37: =IFERROR(N37/O37-1,0) -> -0.33465141 | R37: =SUM(R30:R36) -> 386802.02 | S37: =N37-R37 -> -48971.704 | T37: =IFERROR(N37/R37-1,0) -> -0.12660664
F41: MAYO
C42: OCCIDENTE | F42: KILOS | J42: PESOS
A43: Vend | B43: Cte | C43: Nombre | D43: Código | E43: Descripcion | F43: Pres | G43: 2020 | H43: DIF | I43: % | J43: Pres | K43: 2020 | L43: DIF | M43: %
A44: 1 | B44: 009 | C44: EMPACADORA EL CENTENARIO, SA DE CV | D44: PROAPR | E44: APRORED BOLSA 1KG | F44: 13.65 | G44: 0 | H44: =G44-F44 -> -13.65 | I44: =IFERROR(G44/F44-1,0) -> -1 | J44: 3990.0247 | K44: 0 | L44: =K44-J44 -> -3990.0247 | M44: =IFERROR(K44/J44-1,0) -> -1
A45: 1 | B45: 038 | C45: EMPACADORA BONNACARNE SA DE CV | D45: PROAPR | E45: APRORED BOLSA 1KG | F45: 15.75 | G45: 0 | H45: =G45-F45 -> -15.75 | I45: =IFERROR(G45/F45-1,0) -> -1 | J45: 4716.1642 | K45: 0 | L45: =K45-J45 -> -4716.1642 | M45: =IFERROR(K45/J45-1,0) -> -1
A46: 1 | B46: 099 | C46: COMERCIALIZADORA DE EMBUTIDOS ICO SA DE CV | D46: PROAPR | E46: APRORED BOLSA 1KG | F46: 3.15 | G46: 0 | H46: =G46-F46 -> -3.15 | I46: =IFERROR(G46/F46-1,0) -> -1 | J46: 891.90045 | K46: 0 | L46: =K46-J46 -> -891.90045 | M46: =IFERROR(K46/J46-1,0) -> -1
A47: 1 | B47: 313 | C47: CARNES FINAS DE LA SIERRA SA DE CV | D47: PROAPR | E47: APRORED BOLSA 1KG | F47: 63 | G47: 0 | H47: =G47-F47 -> -63 | I47: =IFERROR(G47/F47-1,0) -> -1 | J47: 18415.499 | K47: 0 | L47: =K47-J47 -> -18415.499 | M47: =IFERROR(K47/J47-1,0) -> -1
A48: 1 | B48: 476 | C48: OMEX ALIMENTARIA SA DE CV | D48: PROAPR | E48: APRORED BOLSA 1KG | F48: 15.75 | G48: 10 | H48: =G48-F48 -> -5.75 | I48: =IFERROR(G48/F48-1,0) -> -0.36507937 | J48: 4716.1642 | K48: 3412.77 | L48: =K48-J48 -> -1303.3942 | M48: =IFERROR(K48/J48-1,0) -> -0.27636744
A49: 1 | B49: 481 | C49: GRUPO BRAVO NUÑO S.C. DE R.L. DE C.V. | D49: PROAPR | E49: APRORED BOLSA 1KG | F49: 231 | G49: 10 | H49: =G49-F49 -> -221 | I49: =IFERROR(G49/F49-1,0) -> -0.95670996 | J49: 58818.375 | K49: 3007.04 | L49: =K49-J49 -> -55811.335 | M49: =IFERROR(K49/J49-1,0) -> -0.94887584
A50: 1 | B50: 485 | C50: PRODUCTOS EL GRAN CHAPARRAL SA DE CV | D50: PROAPR | E50: APRORED BOLSA 1KG | F50: 21 | G50: 0 | H50: =G50-F50 -> -21 | I50: =IFERROR(G50/F50-1,0) -> -1 | J50: 6138.4995 | K50: 0 | L50: =K50-J50 -> -6138.4995 | M50: =IFERROR(K50/J50-1,0) -> -1
A51: 1 | B51: 481 | C51: GRUPO BRAVO NUÑO S.C. DE R.L. DE C.V. | D51: PROAPR10 | E51: COM0213 APRORED BOLSA 10KG | F51: 0 | G51: 160 | H51: =G51-F51 -> 160 | I51: =IFERROR(G51/F51-1,0) -> 0 | J51: 0 | K51: 45624.98 | L51: =K51-J51 -> 45624.98 | M51: =IFERROR(K51/J51-1,0) -> 0
A52: 1 | B52: 657 | C52: HECTOR ALONSO ZARATE QUIROZ | D52: PROAPR | E52: APRORED BOLSA 1KG | F52: 21 | G52: 0 | H52: =G52-F52 -> -21 | I52: =IFERROR(G52/F52-1,0) -> -1 | J52: 6138.4995 | K52: 0 | L52: =K52-J52 -> -6138.4995 | M52: =IFERROR(K52/J52-1,0) -> -1
A53: 1 | B53: 174 | C53: CARNES SELECTAS EL JALISCIENSE SA DE CV | D53: PROAPR | E53: APRORED BOLSA 1KG | F53: 1.05 | G53: 0 | H53: =G53-F53 -> -1.05 | I53: =IFERROR(G53/F53-1,0) -> -1 | J53: 316.4175 | K53: 0 | L53: =K53-J53 -> -316.4175 | M53: =IFERROR(K53/J53-1,0) -> -1
A54: 1 | H54: =G54-F54 -> 0 | I54: =IFERROR(G54/F54-1,0) -> 0 | L54: =K54-J54 -> 0 | M54: =IFERROR(K54/J54-1,0) -> 0
A55: 1 | H55: =G55-F55 -> 0 | I55: =IFERROR(G55/F55-1,0) -> 0 | L55: =K55-J55 -> 0 | M55: =IFERROR(K55/J55-1,0) -> 0
F56: =SUM(F44:F55) -> 385.35 | G56: =SUM(G44:G55) -> 180 | H56: =SUM(H44:H55) -> -205.35 | I56: =H56/F56 -> -0.53289218 | J56: =SUM(J44:J55) -> 104141.54 | K56: =SUM(K44:K55) -> 52044.79 | L56: =SUM(L44:L55) -> -52096.754 | M56: =L56/J56 -> -0.50024949
F60: MAYO
C61: PACIFICO | F61: KILOS | J61: PESOS
A62: Vend | B62: Cte | C62: Nombre | D62: Código | E62: Descripcion | F62: Pres | G62: 2020 | H62: DIF | I62: % | J62: Pres | K62: 2020 | L62: DIF | M62: %
A63: 2 | B63: 012 | C63: KAREY ALIMENTOS, SA DE CV | D63: PROAPR | E63: APRORED BOLSA 1KG | F63: 20 | G63: 30 | H63: =G63-F63 -> 10 | I63: =IFERROR(G63/F63-1,0) -> 0.5 | J63: 5846.19 | K63: 10137 | L63: =K63-J63 -> 4290.81 | M63: =IFERROR(K63/J63-1,0) -> 0.7339498
A64: 2 | H64: =G64-F64 -> 0 | I64: =IFERROR(G64/F64-1,0) -> 0 | L64: =K64-J64 -> 0 | M64: =IFERROR(K64/J64-1,0) -> 0
A65: 2 | H65: =G65-F65 -> 0 | I65: =IFERROR(G65/F65-1,0) -> 0 | L65: =K65-J65 -> 0 | M65: =IFERROR(K65/J65-1,0) -> 0
F66: =SUM(F63:F65) -> 20 | G66: =SUM(G63:G65) -> 30 | H66: =SUM(H63:H65) -> 10 | I66: =H66/F66 -> 0.5 | J66: =SUM(J63:J65) -> 5846.19 | K66: =SUM(K63:K65) -> 10137 | L66: =SUM(L63:L65) -> 4290.81 | M66: =L66/J66 -> 0.7339498
F70: MAYO
C71: COORDINADORA DE VENTAS | F71: KILOS | J71: PESOS
A72: Vend | B72: Cte | C72: Nombre | D72: Código | E72: Descripcion | F72: Pres | G72: 2020 | H72: DIF | I72: % | J72: Pres | K72: 2020 | L72: DIF | M72: %
A73: 3 | B73: 518 | C73: INTEGRADORA PECUARIA GURMA S.P.R. DE R.L. DE C.V. | D73: PROAPR | E73: APRORED BOLSA 1KG | F73: 5 | G73: 2 | H73: =G73-F73 -> -3 | I73: =IFERROR(G73/F73-1,0) -> -0.6 | J73: 1461.5475 | K73: 685.05 | L73: =K73-J73 -> -776.4975 | M73: =IFERROR(K73/J73-1,0) -> -0.53128448
A74: 3 | B74: 601 | C74: VILLESPA, SPR DE RL | D74: PROAPR | E74: APRORED BOLSA 1KG | F74: 60 | G74: 20 | H74: =G74-F74 -> -40 | I74: =IFERROR(G74/F74-1,0) -> -0.66666667 | J74: 17538.57 | K74: 6650.06 | L74: =K74-J74 -> -10888.51 | M74: =IFERROR(K74/J74-1,0) -> -0.62083226
A75: 3 | B75: 106 | C75: VENTAS DE MOSTRADOR | D75: PROAPR10 | E75: COM0213 APRORED BOLSA 10KG | F75: 0 | G75: 10 | H75: =G75-F75 -> 10 | I75: =IFERROR(G75/F75-1,0) -> 0 | J75: 0 | K75: 3199.07 | L75: =K75-J75 -> 3199.07 | M75: =IFERROR(K75/J75-1,0) -> 0
A76: 3 | B76: 601 | C76: VILLESPA, SPR DE RL | D76: PROAPR10 | E76: COM0213 APRORED BOLSA 10KG | F76: 0 | G76: 10 | H76: =G76-F76 -> 10 | I76: =IFERROR(G76/F76-1,0) -> 0 | J76: 0 | K76: 3294.76 | L76: =K76-J76 -> 3294.76 | M76: =IFERROR(K76/J76-1,0) -> 0
F77: =SUM(F73:F76) -> 65 | G77: =SUM(G73:G76) -> 42 | H77: =SUM(H73:H76) -> -23 | I77: =H77/F77 -> -0.35384615 | J77: =SUM(J73:J76) -> 19000.118 | K77: =SUM(K73:K76) -> 13828.94 | L77: =SUM(L73:L76) -> -5171.1775 | M77: =L77/J77 -> -0.27216555
F81: MAYO
C82: ALTOS NORTE | F82: KILOS | J82: PESOS
A83: Vend | B83: Cte | C83: Nombre | D83: Código | E83: Descripcion | F83: Pres | G83: 2020 | H83: DIF | I83: % | J83: Pres | K83: 2020 | L83: DIF | M83: %
A84: 6 | B84: 013 | C84: EMBUTIDOS SUPREMOS, SA DE CV | D84: PROAPR | E84: APRORED BOLSA 1KG | F84: 5 | G84: 5 | H84: =G84-F84 -> 0 | I84: =IFERROR(G84/F84-1,0) -> 0 | J84: 1461.5475 | K84: 1699.08 | L84: =K84-J84 -> 237.5325 | M84: =IFERROR(K84/J84-1,0) -> 0.16252123
A85: 6 | B85: 030 | C85: EMPACADORA ESTRELLA, SA DE CV | D85: PROAPR | E85: APRORED BOLSA 1KG | F85: 5 | G85: 0 | H85: =G85-F85 -> -5 | I85: =IFERROR(G85/F85-1,0) -> -1 | J85: 1427.937 | K85: 0 | L85: =K85-J85 -> -1427.937 | M85: =IFERROR(K85/J85-1,0) -> -1
A86: 6 | B86: 340 | C86: PRODUCTOS JAMEX SA DE CV | D86: PROAPR | E86: APRORED BOLSA 1KG | F86: 180 | G86: 0 | H86: =G86-F86 -> -180 | I86: =IFERROR(G86/F86-1,0) -> -1 | J86: 52615.71 | K86: 0 | L86: =K86-J86 -> -52615.71 | M86: =IFERROR(K86/J86-1,0) -> -1
A87: 6 | B87: 515 | C87: CARNES SELECTAS EL CIEN, SA DE CV | D87: PROAPR | E87: APRORED BOLSA 1KG | F87: 80 | G87: 5 | H87: =G87-F87 -> -75 | I87: =IFERROR(G87/F87-1,0) -> -0.9375 | J87: 23384.76 | K87: 1712.62 | L87: =K87-J87 -> -21672.14 | M87: =IFERROR(K87/J87-1,0) -> -0.92676341
A88: 6 | B88: 708 | C88: EVANGELINA BAUTISTA SANCHEZ | D88: PROAPR | E88: APRORED BOLSA 1KG | F88: 20 | G88: 10 | H88: =G88-F88 -> -10 | I88: =IFERROR(G88/F88-1,0) -> -0.5 | J88: 5846.19 | K88: 3486.22 | L88: =K88-J88 -> -2359.97 | M88: =IFERROR(K88/J88-1,0) -> -0.40367658
A89: 6 | B89: 340 | C89: PRODUCTOS JAMEX SA DE CV | D89: PROAPR10 | E89: COM0213 APRORED BOLSA 10KG | F89: 0 | G89: 20 | H89: =G89-F89 -> 20 | I89: =IFERROR(G89/F89-1,0) -> 0 | J89: 0 | K89: 6589.52 | L89: =K89-J89 -> 6589.52 | M89: =IFERROR(K89/J89-1,0) -> 0
A90: 6 | B90: 515 | C90: CARNES SELECTAS EL CIEN, SA DE CV | D90: PROAPR10 | E90: COM0213 APRORED BOLSA 10KG | F90: 0 | G90: 20 | H90: =G90-F90 -> 20 | I90: =IFERROR(G90/F90-1,0) -> 0 | J90: 0 | K90: 6686.01 | L90: =K90-J90 -> 6686.01 | M90: =IFERROR(K90/J90-1,0) -> 0
F91: =SUM(F84:F90) -> 290 | G91: =SUM(G84:G90) -> 60 | H91: =SUM(H84:H90) -> -230 | I91: =H91/F91 -> -0.79310345 | J91: =SUM(J84:J90) -> 84736.144 | K91: =SUM(K84:K90) -> 20173.45 | L91: =SUM(L84:L90) -> -64562.694 | M91: =L91/J91 -> -0.76192627
F95: MAYO
C96: BAJIO | F96: KILOS | J96: PESOS
A97: Vend | B97: Cte | C97: Nombre | D97: Código | E97: Descripcion | F97: Pres | G97: 2020 | H97: DIF | I97: % | J97: Pres | K97: 2020 | L97: DIF | M97: %
A98: 7 | B98: 093 | C98: EMPACADORA CELAYA SA DE CV | D98: PROAPR10 | E98: COM0213 APRORED BOLSA 10KG | F98: 42 | G98: 20 | H98: =G98-F98 -> -22 | I98: =IFERROR(G98/F98-1,0) -> -0.52380952 | J98: 12105.891 | K98: 6780.11 | L98: =K98-J98 -> -5325.781 | M98: =IFERROR(K98/J98-1,0) -> -0.439933
A99: 7 | B99: 542 | C99: NESTOR LOZA QUISTIANO | D99: PROAPR | E99: APRORED BOLSA 1KG | F99: 42 | G99: 0 | H99: =G99-F99 -> -42 | I99: =IFERROR(G99/F99-1,0) -> -1 | J99: 12276.999 | K99: 0 | L99: =K99-J99 -> -12276.999 | M99: =IFERROR(K99/J99-1,0) -> -1
A100: 7 | B100: 736 | C100: MARIA DEL CARMEN MANCILLA MARTINEZ | D100: PROAPR | E100: APRORED BOLSA 1KG | F100: 94.5 | G100: 0 | H100: =G100-F100 -> -94.5 | I100: =IFERROR(G100/F100-1,0) -> -1 | J100: 27623.248 | K100: 0 | L100: =K100-J100 -> -27623.248 | M100: =IFERROR(K100/J100-1,0) -> -1
A101: 7 | B101: 678 | C101: DISTRIBUCIONES PAVA SA DE CV | D101: PROAPR | E101: APRORED BOLSA 1KG | F101: 1.05 | G101: 0 | H101: =G101-F101 -> -1.05 | I101: =IFERROR(G101/F101-1,0) -> -1 | J101: 306.92498 | K101: 0 | L101: =K101-J101 -> -306.92498 | M101: =IFERROR(K101/J101-1,0) -> -1
F102: =SUM(F98:F101) -> 179.55 | G102: =SUM(G98:G101) -> 20 | H102: =SUM(H98:H101) -> -159.55 | I102: =H102/F102 -> -0.88861041 | J102: =SUM(J98:J101) -> 52313.063 | K102: =SUM(K98:K101) -> 6780.11 | L102: =SUM(L98:L101) -> -45532.953 | M102: =L102/J102 -> -0.87039356

Sheet JUNIO
C1: CALCULO DE BONOS JUNIO
C3: REGION OCCIDENTE
C6: Presupuesto | D6: Real | E6: Variacion | F6: %
B7: KG | C7: 157176.59 | D7: 166866.79 | E7: =D7-C7 -> 9690.2026 | F7: =D7/C7-1 -> 0.061651691
B8: Importes | C8: 4727250.6 | D8: 5121030.8 | E8: =D8-C8 -> 393780.27 | F8: =D8/C8-1 -> 0.083300063
B11: COMPOSICION BONO | I11: ALCANCE DE OBJETIVOS
B12: Bono | C12: Concepto | F12: % Bono | G12: Monto | H12: Objetivo Minimo | I12: Presupuesto | J12: Real | K12: % Cobertura | L12: Bono
B13: 12000 | C13: Cumplimiento Presupuesto | F13: 0.7 | G13: =B13*F13 -> 8400 | H13: 0.9 | I13: =C8 -> 4727250.6 | J13: =D8 -> 5121030.8 | K13: =IFERROR(J13/I13,0) -> 1.0833001 | L13: =IF(K13<H13,0,K13*$G13) -> 9099.7205
C14: Cierre de 3 pedidos 1000 Kgcon clientes actuales de FMC | F14: 0.12 | G14: =B13*F14 -> 1440 | H14: 0.8 | I14: 1 | K14: =J14/I14 -> 0 | L14: =IF(K14<H14,0,K14*$G14) -> 0
C15: Contar con calendario de pruebas inicios de año 2020 | F15: 0.05 | G15: =B$13*F$15 -> 600 | H15: 1 | I15: 1 | K15: =J15/I15 -> 0 | L15: =IF(K15<H15,0,K15*$G15) -> 0
C16: Presentar estrategica por region Occidente 2020 | F16: 0.05 | G16: =B$13*F$15 -> 600 | H16: 0.75 | I16: 1 | K16: =J16/I16 -> 0 | L16: =IF(K16<H16,0,K16*$G16) -> 0
C17: Presentar presupuesto lunes 6 de Diciembre | F17: 0.08 | G17: =B13*F17 -> 960 | H17: 0.75 | I17: 1 | K17: =J17/I17 -> 0 | L17: =IF(K17<H17,0,K17*$G17) -> 0
E18: Total | F18: =SUM(F13:F17) -> 1 | G18: =SUM(G13:G17) -> 12000 | K18: Total sin Presupuesto | L18: =SUM(L14:L17) -> 0
K20: TOTAL | L20: =+L18+L13 -> 9099.7205
C24: REGION PACIFICO
C27: Presupuesto | D27: Real | E27: Variacion | F27: %
B28: KG | C28: 29892 | D28: 25613.24 | E28: =D28-C28 -> -4278.76 | F28: =D28/C28-1 -> -0.14314064
B29: Importes | C29: 2181324.4 | D29: 1813161.1 | E29: =D29-C29 -> -368163.29 | F29: =D29/C29-1 -> -0.16877971
B32: COMPOSICION BONO | I32: ALCANCE DE OBJETIVOS
B33: Bono | C33: Concepto | F33: % Bono | G33: Monto | H33: Objetivo Minimo | I33: Presupuesto | J33: Real | K33: % Cobertura | L33: Bono
B34: 6500 | C34: Cumplimiento Presupuesto | F34: 0.15384615 | G34: 1000 | H34: 0.5 | I34: =C29 -> 2181324.4 | J34: =D29 -> 1813161.1 | K34: =IFERROR(J34/I34,0) -> 0.83122029 | L34: =IF(K34<H34,0,K34*$G34) -> 831.22029
C35: Pruebas atorizadas por realizar con cliente | F35: 0.15384615 | G35: 1000 | H35: 1 | I35: 1 | K35: =IFERROR(J35/I35,0) -> 0 | L35: =IF(K35<H35,0,K35*$G35) -> 0
C36: Armado e implementación estrategia Baja California | F36: 0.23076923 | G36: 1500 | H36: 1 | I36: 1 | K36: =IFERROR(J36/I36,0) -> 0 | L36: =IF(K36<H36,0,K36*$G36) -> 0
C37: Presentar estrategica por región 2020 | F37: 0.23076923 | G37: 1500 | H37: 0.75 | I37: 1 | K37: =IFERROR(J37/I37,0) -> 0 | L37: =IF(K37<H37,0,K37*$G37) -> 0
C38: Presentar presupuesto lunes 6 de Diciembre | F38: 0.23076923 | G38: 1500 | H38: 0.75 | I38: 1 | K38: =IFERROR(J38/I38,0) -> 0 | L38: =IF(K38<H38,0,K38*$G38) -> 0
E39: Total | F39: =SUM(F34:F38) -> 1 | G39: =SUM(G33:G38) -> 6500 | K39: Total sin Presupuesto | L39: =SUM(L36:L36) -> 0
K41: TOTAL | L41: =+L39+L34 -> 831.22029
C45: ALTOS NORTE
C48: Presupuesto | D48: Real | E48: KG | F48: %
B49: KG | C49: 21125.876 | D49: 23040.45 | E49: =D49-C49 -> 1914.574 | F49: =D49/C49-1 -> 0.090626964
B50: Importes | C50: 1169969.7 | D50: 1392992.4 | E50: =D50-C50 -> 223022.73 | F50: =D50/C50-1 -> 0.19062265
B53: COMPOSICION BONO | I53: ALCANCE DE OBJETIVOS
B54: Bono | C54: Concepto | F54: % Bono | G54: Monto | H54: Objetivo Minimo | I54: Presupuesto | J54: Real | K54: % Cobertura | L54: Bono
B55: 10000 | C55: Cumplimiento Presupuesto | F55: 0.6 | G55: =+F55*B55 -> 6000 | H55: 0.8 | I55: =C50 -> 1169969.7 | J55: =D50 -> 1392992.4 | K55: =IFERROR(J55/I55,0) -> 1.1906227 | L55: =IF(K55<H55,0,K55*$G55) -> 7143.7359
C56: Cierre de 3 pedidos 300 Kgcon clientes actuales de FMC | F56: 0.1 | G56: =B55*F56 -> 1000 | H56: 0.8 | I56: 1 | K56: =J56/I56 -> 0 | L56: =IF(K56<H56,0,K56*$G56) -> 0
C57: Contar con calendario de pruebas inicios de año 2020 | F57: 0.12 | G57: =+F57*B55 -> 1200 | H57: 1 | I57: 1 | K57: =IFERROR(J57/I57,0) -> 0 | L57: =IF(K57<H57,0,K57*$G57) -> 0
C58: Presentar estrategica por region 2020 | F58: 0.07 | G58: =+F58*B55 -> 700 | H58: 1 | I58: 1 | K58: =IFERROR(J58/I58,0) -> 0 | L58: =IF(K58<H58,0,K58*$G58) -> 0
C59: Presentar presupuesto lunes 6 de Diciembre | F59: 0.11 | G59: =+F59*B55 -> 1100 | H59: 1 | I59: 1 | K59: =IFERROR(J59/I59,0) -> 0 | L59: =IF(K59<H59,0,K59*$G59) -> 0
E60: Total | F60: =SUM(F55:F59) -> 1 | G60: =SUM(G55:G59) -> 10000 | K60: Total sin Presupuesto | L60: =SUM(L56:L59) -> 0
K62: TOTAL | L62: =+L60+L55 -> 7143.7359
C66: COORDINACION DE VENTAS
C69: Presupuesto | D69: Real | E69: KG | F69: %
B70: KG | C70: 61091.8 | D70: 38980.7 | E70: =D70-C70 -> -22111.1 | F70: =D70/C70-1 -> -0.36193237
B71: Importes | C71: 1742621 | D71: 1267303.8 | E71: =D71-C71 -> -475317.16 | F71: =D71/C71-1 -> -0.27275992
B74: COMPOSICION BONO | I74: ALCANCE DE OBJETIVOS
B75: Bono | C75: Concepto | F75: % Bono | G75: Monto | H75: Objetivo Minimo | I75: Presupuesto | J75: Real | K75: % Cobertura | L75: Bono
C76: Cumplimiento Presupuesto | F76: 1 | G76: =+F76*B76 -> 0 | H76: 0.8 | I76: =C71 -> 1742621 | J76: =D71 -> 1267303.8 | K76: =IFERROR(J76/I76,0) -> 0.72724008 | L76: =IF(K76<H76,0,K76*$G76) -> 0
G77: =B76*F77 -> 0 | H77: 0.8 | I77: 1 | K77: =J77/I77 -> 0 | L77: =IF(K77<H77,0,K77*$G77) -> 0
G78: =+F78*B76 -> 0 | H78: 1 | I78: 1 | K78: =IFERROR(J78/I78,0) -> 0 | L78: =IF(K78<H78,0,K78*$G78) -> 0
G79: =+F79*B76 -> 0 | H79: 1 | I79: 1 | K79: =IFERROR(J79/I79,0) -> 0 | L79: =IF(K79<H79,0,K79*$G79) -> 0
G80: =+F80*B76 -> 0 | H80: 1 | I80: 1 | K80: =IFERROR(J80/I80,0) -> 0 | L80: =IF(K80<H80,0,K80*$G80) -> 0
E81: Total | F81: =SUM(F76:F80) -> 1 | G81: =SUM(G76:G80) -> 0 | K81: Total sin Presupuesto | L81: =SUM(L77:L80) -> 0
K83: TOTAL | L83: =+L81+L76 -> 0
C87: CUENTAS CLAVE
C90: Presupuesto | D90: Real | E90: KG | F90: %
B91: KG | C91: 61091.8 | D91: 38980.7 | E91: =D91-C91 -> -22111.1 | F91: =D91/C91-1 -> -0.36193237
B92: Importes | C92: 1742621 | D92: 1267303.8 | E92: =D92-C92 -> -475317.16 | F92: =D92/C92-1 -> -0.27275992
B95: COMPOSICION BONO | I95: ALCANCE DE OBJETIVOS
B96: Bono | C96: Concepto | F96: % Bono | G96: Monto | H96: Objetivo Minimo | I96: Presupuesto | J96: Real | K96: % Cobertura | L96: Bono
C97: Cumplimiento Presupuesto | F97: 1 | G97: =+F97*B97 -> 0 | H97: 0.8 | I97: =C92 -> 1742621 | J97: =D92 -> 1267303.8 | K97: =IFERROR(J97/I97,0) -> 0.72724008 | L97: =IF(K97<H97,0,K97*$G97) -> 0
G98: =B97*F98 -> 0 | H98: 0.8 | I98: 1 | K98: =J98/I98 -> 0 | L98: =IF(K98<H98,0,K98*$G98) -> 0
G99: =+F99*B97 -> 0 | H99: 1 | I99: 1 | K99: =IFERROR(J99/I99,0) -> 0 | L99: =IF(K99<H99,0,K99*$G99) -> 0
G100: =+F100*B97 -> 0 | H100: 1 | I100: 1 | K100: =IFERROR(J100/I100,0) -> 0 | L100: =IF(K100<H100,0,K100*$G100) -> 0
G101: =+F101*B97 -> 0 | H101: 1 | I101: 1 | K101: =IFERROR(J101/I101,0) -> 0 | L101: =IF(K101<H101,0,K101*$G101) -> 0
E102: Total | F102: =SUM(F97:F101) -> 1 | G102: =SUM(G97:G101) -> 0 | K102: Total sin Presupuesto | L102: =SUM(L98:L101) -> 0
K104: TOTAL | L104: =+L102+L97 -> 0
C108: REGION BAJIO
C110: KILOS | E110: Variacion
B111: MES | C111: Presupuesto | D111: Real | E111: KG | F111: %
B112: =$B$5 -> 0 | C112: 27947.209 | D112: 30138.18 | E112: =D112-C112 -> 2190.9707 | F112: =D112/C112-1 -> 0.078396762
C113: 1708628 | D113: 1711839.8 | E113: =D113-C113 -> 3211.7947 | F113: =D113/C113-1 -> 0.0018797507
B116: COMPOSICION BONO | I116: ALCANCE DE OBJETIVOS
B117: Bono | C117: Concepto | F117: % Bono | G117: Monto | H117: Objetivo Minimo | I117: Presupuesto | J117: Real | K117: % Cobertura | L117: Bono
B118: 7000 | C118: Cumplimiento Presupuesto | F118: 0.5 | G118: =B118*F118 -> 3500 | H118: 0.95 | I118: =C113 -> 1708628 | J118: =D113 -> 1711839.8 | K118: =IFERROR(J118/I118,0) -> 1.0018798 | L118: =IF(K118<H118,0,K118*$G118) -> 3506.5791
C119: Aplicación de pruebas unidades de chorizo | F119: 0.2 | G119: =B118*F119 -> 1400 | H119: 0.75 | I119: 1 | K119: =IFERROR(J119/I119,0) -> 0 | L119: =IF(K119<H119,0,K119*$G119) -> 0
C120: Prospectación | F120: 0.2 | G120: =B118*F120 -> 1400 | H120: 0.75 | I120: 1 | K120: =IFERROR(J120/I120,0) -> 0 | L120: =IF(K120<H120,0,K120*$G120) -> 0
C121: Cierre de venta con productos nuevos AGR | F121: 0.1 | G121: =+F121*B118 -> 700 | H121: 0.75 | I121: 1 | K121: =IFERROR(J121/I121,0) -> 0 | L121: =IF(K121<H121,0,K121*$G121) -> 0
E122: Total | F122: =SUM(F118:F121) -> 1 | G122: =SUM(G118:G121) -> 7000 | K122: Total sin Presupuesto | L122: =SUM(L119:L121) -> 0
K124: TOTAL | L124: =+L122+L118 -> 3506.5791
O199: 3 | P199: 3.1 | Q199: =+P199-O199 -> 0.1 | R199: =+Q199/P199 -> 0.032258065
Q203: =2000*3*12 -> 72000
Q206: =2000*12 -> 24000

Sheet JULIO
C1: CALCULO DE BONOS JULIO
C3: REGION OCCIDENTE
C6: Presupuesto | D6: Real | E6: Variacion | F6: %
B7: KG | C7: 170541 | D7: 169858.36 | E7: =D7-C7 -> -682.64 | F7: =D7/C7-1 -> -0.0040027911
B8: Importes | C8: 5173873.2 | D8: 6037366.4 | E8: =D8-C8 -> 863493.2 | F8: =D8/C8-1 -> 0.16689493
B11: COMPOSICION BONO | I11: ALCANCE DE OBJETIVOS
B12: Bono | C12: Concepto | F12: % Bono | G12: Monto | H12: Objetivo Minimo | I12: Presupuesto | J12: Real | K12: % Cobertura | L12: Bono
B13: 11500 | C13: Cumplimiento Presupuesto | F13: 1 | G13: =B13*F13 -> 11500 | H13: 0.9 | I13: =C8 -> 5173873.2 | J13: =D8 -> 6037366.4 | K13: =IFERROR(J13/I13,0) -> 1.1668949 | L13: =IF(K13<H13,0,K13*$G13) -> 13419.292
G14: =B13*F14 -> 0 | H14: 0.8 | I14: 1 | K14: =J14/I14 -> 0 | L14: =IF(K14<H14,0,K14*$G14) -> 0
G15: =B$13*F$15 -> 0 | H15: 1 | I15: 1 | K15: =J15/I15 -> 0 | L15: =IF(K15<H15,0,K15*$G15) -> 0
G16: =B$13*F$15 -> 0 | H16: 0.75 | I16: 1 | K16: =J16/I16 -> 0 | L16: =IF(K16<H16,0,K16*$G16) -> 0
G17: =B13*F17 -> 0 | H17: 0.75 | I17: 1 | K17: =J17/I17 -> 0 | L17: =IF(K17<H17,0,K17*$G17) -> 0
E18: Total | F18: =SUM(F13:F17) -> 1 | G18: =SUM(G13:G17) -> 11500 | K18: Total sin Presupuesto | L18: =SUM(L14:L17) -> 0
K20: TOTAL | L20: =+L18+L13 -> 13419.292
C22: REGION PACIFICO
C25: Presupuesto | D25: Real | E25: Variacion | F25: %
B26: KG | C26: 23624.4 | D26: 26515.252 | E26: =D26-C26 -> 2890.852 | F26: =D26/C26-1 -> 0.12236721
B27: Importes | C27: 1753717 | D27: 2095225.6 | E27: =D27-C27 -> 341508.54 | F27: =D27/C27-1 -> 0.19473412
B30: COMPOSICION BONO | I30: ALCANCE DE OBJETIVOS
B31: Bono | C31: Concepto | F31: % Bono | G31: Monto | H31: Objetivo Minimo | I31: Presupuesto | J31: Real | K31: % Cobertura | L31: Bono
B32: 10500 | C32: Cumplimiento Presupuesto | F32: 1 | G32: =B32*F32 -> 10500 | H32: 0.8 | I32: =C27 -> 1753717 | J32: =D27 -> 2095225.6 | K32: =IFERROR(J32/I32,0) -> 1.1947341 | L32: =IF(K32<H32,0,K32*$G32) -> 12544.708
H33: 0 | I33: 1 | K33: =IFERROR(J33/I33,0) -> 0 | L33: =IF(K33<H33,0,K33*$G33) -> 0
H34: 0 | I34: 1 | K34: =IFERROR(J34/I34,0) -> 0 | L34: =IF(K34<H34,0,K34*$G34) -> 0
H35: 0 | I35: 1 | K35: =IFERROR(J35/I35,0) -> 0 | L35: =IF(K35<H35,0,K35*$G35) -> 0
H36: 0 | I36: 1 | K36: =IFERROR(J36/I36,0) -> 0 | L36: =IF(K36<H36,0,K36*$G36) -> 0
E37: Total | F37: =SUM(F32:F36) -> 1 | G37: =SUM(G31:G36) -> 10500 | K37: Total sin Presupuesto | L37: =SUM(L34:L34) -> 0
K39: TOTAL | L39: =+L37+L32 -> 12544.708
C41: ALTOS NORTE
C44: Presupuesto | D44: Real | E44: KG | F44: %
B45: KG | C45: 22853.032 | D45: 32695.299 | E45: =D45-C45 -> 9842.267 | F45: =D45/C45-1 -> 0.43067664
B46: Importes | C46: 1374179.3 | D46: 1550018.1 | E46: =D46-C46 -> 175838.82 | F46: =D46/C46-1 -> 0.12795916
B49: COMPOSICION BONO | I49: ALCANCE DE OBJETIVOS
B50: Bono | C50: Concepto | F50: % Bono | G50: Monto | H50: Objetivo Minimo | I50: Presupuesto | J50: Real | K50: % Cobertura | L50: Bono
B51: 10000 | C51: Cumplimiento Presupuesto | F51: 0.7 | G51: =+F51*B51 -> 7000 | H51: 0.8 | I51: =C46 -> 1374179.3 | J51: =D46 -> 1550018.1 | K51: =IFERROR(J51/I51,0) -> 1.1279592 | L51: =IF(K51<H51,0,K51*$G51) -> 7895.7141
C52: Prospeccion y filtrado Morelia | F52: 0.15 | G52: =B51*F52 -> 1500 | H52: 0.8 | I52: 1 | J52: 0 | K52: 0.5 | L52: =IF(K52<H52,0,K52*$G52) -> 0
C53: Prospeccion y filtrado Aguascalientes | F53: 0.15 | G53: =+F53*B51 -> 1500 | H53: 0.8 | I53: 1 | K53: 0.5 | L53: =IF(K53<H53,0,K53*$G53) -> 0
G54: =+F54*B51 -> 0 | H54: 1 | I54: 1 | K54: =IFERROR(J54/I54,0) -> 0 | L54: =IF(K54<H54,0,K54*$G54) -> 0
G55: =+F55*B51 -> 0 | H55: 1 | I55: 1 | K55: =IFERROR(J55/I55,0) -> 0 | L55: =IF(K55<H55,0,K55*$G55) -> 0
E56: Total | F56: =SUM(F51:F55) -> 1 | G56: =SUM(G51:G55) -> 10000 | K56: Total sin Presupuesto | L56: =SUM(L52:L55) -> 0
K58: TOTAL | L58: =+L56+L51 -> 7895.7141
C60: COORDINACION DE VENTAS
C63: Presupuesto | D63: Real | E63: KG | F63: %
B64: KG | C64: 29841.2 | D64: 29792 | E64: =D64-C64 -> -49.2 | F64: =D64/C64-1 -> -0.0016487273
B65: Importes | C65: 1245927.4 | D65: 1450584 | E65: =D65-C65 -> 204656.58 | F65: =D65/C65-1 -> 0.16426044
B68: COMPOSICION BONO | I68: ALCANCE DE OBJETIVOS
B69: Bono | C69: Concepto | F69: % Bono | G69: Monto | H69: Objetivo Minimo | I69: Presupuesto | J69: Real | K69: % Cobertura | L69: Bono
B70: 4000 | C70: Cumplimiento Presupuesto | F70: 1 | G70: =+F70*B70 -> 4000 | H70: 0.8 | I70: =C65 -> 1245927.4 | J70: =D65 -> 1450584 | K70: =IFERROR(J70/I70,0) -> 1.1642604 | L70: =IF(K70<H70,0,K70*$G70) -> 4657.0418
G71: =+F71*B70 -> 0 | I71: 1 | K71: =IFERROR(J71/I71,0) -> 0 | L71: =IF(K71<H71,0,K71*$G71) -> 0
E72: Total | F72: =SUM(F70:F71) -> 1 | G72: =SUM(G70:G71) -> 4000 | K72: Total sin Presupuesto | L72: =SUM(L71:L71) -> 0
K74: TOTAL | L74: =+L72+L70 -> 4657.0418
C76: CUENTAS CLAVE
C78: Presupuesto | D78: Real | E78: KG | F78: %
B79: KG | C79: 72301.28 | D79: 72233.24 | E79: =D79-C79 -> -68.04 | F79: =D79/C79-1 -> -0.00094106218
B80: Importes | C80: 1660857.6 | D80: 1836426.5 | E80: =D80-C80 -> 175568.96 | F80: =D80/C80-1 -> 0.10570982
B83: COMPOSICION BONO | I83: ALCANCE DE OBJETIVOS
B84: Bono | C84: Concepto | F84: % Bono | G84: Monto | H84: Objetivo Minimo | I84: Presupuesto | J84: Real | K84: % Cobertura | L84: Bono
C85: Cumplimiento Presupuesto | F85: 1 | G85: =+F85*B85 -> 0 | H85: 0.8 | I85: =C80 -> 1660857.6 | J85: =D80 -> 1836426.5 | K85: =IFERROR(J85/I85,0) -> 1.1057098 | L85: =IF(K85<H85,0,K85*$G85) -> 0
G86: =B85*F86 -> 0 | H86: 0.8 | I86: 1 | K86: =J86/I86 -> 0 | L86: =IF(K86<H86,0,K86*$G86) -> 0
G87: =+F87*B85 -> 0 | H87: 1 | I87: 1 | K87: =IFERROR(J87/I87,0) -> 0 | L87: =IF(K87<H87,0,K87*$G87) -> 0
G88: =+F88*B85 -> 0 | H88: 1 | I88: 1 | K88: =IFERROR(J88/I88,0) -> 0 | L88: =IF(K88<H88,0,K88*$G88) -> 0
G89: =+F89*B85 -> 0 | H89: 1 | I89: 1 | K89: =IFERROR(J89/I89,0) -> 0 | L89: =IF(K89<H89,0,K89*$G89) -> 0
E90: Total | F90: =SUM(F85:F89) -> 1 | G90: =SUM(G85:G89) -> 0 | K90: Total sin Presupuesto | L90: =SUM(L86:L89) -> 0
K92: TOTAL | L92: =+L90+L85 -> 0
C94: REGION BAJIO
C96: KILOS | E96: Variacion
B97: KG | C97: Presupuesto | D97: Real | E97: KG | F97: %
B98: Importes | C98: 21857.81 | D98: 28212.25 | E98: =D98-C98 -> 6354.44 | F98: =D98/C98-1 -> 0.29071714
C99: 1321719.9 | D99: 1792760.9 | E99: =D99-C99 -> 471041.02 | F99: =D99/C99-1 -> 0.35638492
B102: COMPOSICION BONO | I102: ALCANCE DE OBJETIVOS
B103: Bono | C103: Concepto | F103: % Bono | G103: Monto | H103: Objetivo Minimo | I103: Presupuesto | J103: Real | K103: % Cobertura | L103: Bono
B104: 7000 | C104: Cumplimiento Presupuesto | F104: 0.5 | G104: =B104*F104 -> 3500 | H104: 0.95 | I104: =C99 -> 1321719.9 | J104: =D99 -> 1792760.9 | K104: =IFERROR(J104/I104,0) -> 1.3563849 | L104: =IF(K104<H104,0,K104*$G104) -> 4747.3472
C105: Aplicación de pruebas unidades de chorizo | F105: 0.2 | G105: =B104*F105 -> 1400 | H105: 0.75 | I105: 1 | K105: =IFERROR(J105/I105,0) -> 0 | L105: =IF(K105<H105,0,K105*$G105) -> 0
C106: Prospectación | F106: 0.2 | G106: =B104*F106 -> 1400 | H106: 0.75 | I106: 1 | K106: =IFERROR(J106/I106,0) -> 0 | L106: =IF(K106<H106,0,K106*$G106) -> 0
C107: Cierre de venta con productos nuevos AGR | F107: 0.1 | G107: =+F107*B104 -> 700 | H107: 0.75 | I107: 1 | K107: =IFERROR(J107/I107,0) -> 0 | L107: =IF(K107<H107,0,K107*$G107) -> 0
E108: Total | F108: =SUM(F104:F107) -> 1 | G108: =SUM(G104:G107) -> 7000 | K108: Total sin Presupuesto | L108: =SUM(L105:L107) -> 0
K110: TOTAL | L110: =+L108+L104 -> 4747.3472
O185: 3 | P185: 3.1 | Q185: =+P185-O185 -> 0.1 | R185: =+Q185/P185 -> 0.032258065
Q189: =2000*3*12 -> 72000
Q192: =2000*12 -> 24000

Sheet AGOSTO 
C1: CALCULO DE BONOS JULIO
C3: REGION OCCIDENTE
C6: Presupuesto | D6: Real | E6: Variacion | F6: %
B7: KG | E7: =D7-C7 -> 0 | F7: =D7/C7-1 -> #DIV/0!
B8: Importes | E8: =D8-C8 -> 0 | F8: =D8/C8-1 -> #DIV/0!
B11: COMPOSICION BONO | I11: ALCANCE DE OBJETIVOS
B12: Bono | C12: Concepto | F12: % Bono | G12: Monto | H12: Objetivo Minimo | I12: Presupuesto | J12: Real | K12: % Cobertura | L12: Bono
B13: 11500 | C13: Cumplimiento Presupuesto | F13: 0.75 | G13: =B13*F13 -> 8625 | H13: 0.9 | I13: =C8 -> 0 | J13: =D8 -> 0 | K13: =IFERROR(J13/I13,0) -> 0 | L13: =IF(K13<H13,0,K13*$G13) -> 0
C14: Promoción de prospectos de inyección de cerdo NAVSA , SIERRA | F14: 0.07 | G14: =B13*F14 -> 805 | H14: 1
C15: Desplazamiento carragenina 84400 300 KG | F15: 0.1 | G15: =B13*F15 -> 1150 | H15: 0.7 | I15: 1 | K15: =J15/I15 -> 0 | L15: =IF(K15<H15,0,K15*$G15) -> 0
C16: Evaluación y plan de impulso almidones modificados nuevos | F16: 0.08 | G16: =B13*F16 -> 920 | H16: 1 | I16: 1 | K16: =J16/I16 -> 0 | L16: =IF(K16<H16,0,K16*$G16) -> 0
G17: =B13*F17 -> 0 | I17: 1 | K17: =J17/I17 -> 0 | L17: =IF(K17<H17,0,K17*$G17) -> 0
E18: Total | F18: =SUM(F13:F17) -> 1 | G18: =SUM(G13:G17) -> 11500 | K18: Total sin Presupuesto | L18: =SUM(L15:L17) -> 0
K20: TOTAL | L20: =+L18+L13 -> 0
C24: REGION PACIFICO
C27: Presupuesto | D27: Real | E27: Variacion | F27: %
B28: KG | E28: =D28-C28 -> 0 | F28: =D28/C28-1 -> #DIV/0!
B29: Importes | E29: =D29-C29 -> 0 | F29: =D29/C29-1 -> #DIV/0!
B32: COMPOSICION BONO | I32: ALCANCE DE OBJETIVOS
B33: Bono | C33: Concepto | F33: % Bono | G33: Monto | H33: Objetivo Minimo | I33: Presupuesto | J33: Real | K33: % Cobertura | L33: Bono
B34: 10500 | C34: Cumplimiento Presupuesto | F34: 0.7 | G34: =B34*F34 -> 7350 | H34: 0.75 | I34: =C29 -> 0 | J34: =D29 -> 0 | K34: =IFERROR(J34/I34,0) -> 0 | L34: =IF(K34<H34,0,K34*$G34) -> 0
C35: Cierre super chivas, Meza, Cornejo , Sasa Sonora | F35: 0.15 | G35: =B34*F35 -> 1575 | H35: 0.5 | I35: 1 | K35: =IFERROR(J35/I35,0) -> 0 | L35: =IF(K35<H35,0,K35*$G35) -> 0
C36: Desplazamiento carragenina 84400 300 KG | F36: 0.15 | G36: =B34*F36 -> 1575 | H36: 0.5 | I36: 1 | K36: =IFERROR(J36/I36,0) -> 0 | L36: =IF(K36<H36,0,K36*$G36) -> 0
H37: 0 | I37: 1 | K37: =IFERROR(J37/I37,0) -> 0 | L37: =IF(K37<H37,0,K37*$G37) -> 0
H38: 0 | I38: 1 | K38: =IFERROR(J38/I38,0) -> 0 | L38: =IF(K38<H38,0,K38*$G38) -> 0
E39: Total | F39: =SUM(F34:F38) -> 1 | G39: =SUM(G33:G38) -> 10500 | K39: Total sin Presupuesto | L39: =SUM(L36:L36) -> 0
K41: TOTAL | L41: =+L39+L34 -> 0
C45: ALTOS NORTE
C48: Presupuesto | D48: Real | E48: KG | F48: %
B49: KG | F49: =D49/C49-1 -> #DIV/0!
B50: Importes | F50: =D50/C50-1 -> #DIV/0!
B53: COMPOSICION BONO | I53: ALCANCE DE OBJETIVOS
B54: Bono | C54: Concepto | F54: % Bono | G54: Monto | H54: Objetivo Minimo | I54: Presupuesto | J54: Real | K54: % Cobertura | L54: Bono
B55: 10000 | C55: Cumplimiento Presupuesto | F55: 0.7 | G55: =+F55*B55 -> 7000 | H55: 0.9 | I55: =C50 -> 0 | J55: =D50 -> 0 | K55: =IFERROR(J55/I55,0) -> 0 | L55: =IF(K55<H55,0,K55*$G55) -> 0
C56: Prospeccion y filtrado Morelia | F56: 0.1 | G56: =B55*F56 -> 1000 | H56: 1 | I56: 1 | J56: 0 | K56: 0.5 | L56: =IF(K56<H56,0,K56*$G56) -> 0
C57: Desplazamiento carragenina 84400 300 KG | F57: 0.1 | G57: =+F57*B55 -> 1000 | H57: 1 | I57: 1 | K57: 0.5 | L57: =IF(K57<H57,0,K57*$G57) -> 0
C58: Evaluación y plan de impulso almidones modificados nuevos | F58: 0.1 | G58: =+F58*B55 -> 1000 | H58: 1 | I58: 1 | K58: =IFERROR(J58/I58,0) -> 0 | L58: =IF(K58<H58,0,K58*$G58) -> 0
G59: =+F59*B55 -> 0 | I59: 1 | K59: =IFERROR(J59/I59,0) -> 0 | L59: =IF(K59<H59,0,K59*$G59) -> 0
E60: Total | F60: =SUM(F55:F59) -> 1 | G60: =SUM(G55:G59) -> 10000 | K60: Total sin Presupuesto | L60: =SUM(L56:L59) -> 0
K62: TOTAL | L62: =+L60+L55 -> 0
C66: COORDINACION DE VENTAS
C69: Presupuesto | D69: Real | E69: KG | F69: %
B70: KG | F70: =D70/C70-1 -> #DIV/0!
B71: Importes | F71: =D71/C71-1 -> #DIV/0!
B74: COMPOSICION BONO | I74: ALCANCE DE OBJETIVOS
B75: Bono | C75: Concepto | F75: % Bono | G75: Monto | H75: Objetivo Minimo | I75: Presupuesto | J75: Real | K75: % Cobertura | L75: Bono
B76: 4000 | C76: Cumplimiento Presupuesto | F76: 0.8 | G76: =+F76*B76 -> 3200 | H76: 0.75 | I76: =C71 -> 0 | J76: =D71 -> 0 | K76: =IFERROR(J76/I76,0) -> 0 | L76: =IF(K76<H76,0,K76*$G76) -> 0
C77: Crecer la saturación de productos por cliente | F77: 0.2 | G77: =+F77*B76 -> 800 | H77: 0.6 | I77: 1 | K77: =IFERROR(J77/I77,0) -> 0 | L77: =IF(K77<H77,0,K77*$G77) -> 0
E78: Total | F78: =SUM(F76:F77) -> 1 | G78: =SUM(G76:G77) -> 4000 | K78: Total sin Presupuesto | L78: =SUM(L77:L77) -> 0
K80: TOTAL | L80: =+L78+L76 -> 0
C84: CUENTAS CLAVE
C87: Presupuesto | D87: Real | E87: KG | F87: %
B88: KG | C88: 72301.28 | D88: 72233.24 | E88: =D88-C88 -> -68.04 | F88: =D88/C88-1 -> -0.00094106218
B89: Importes | C89: 1660857.6 | D89: 1836426.5 | E89: =D89-C89 -> 175568.96 | F89: =D89/C89-1 -> 0.10570982
B92: COMPOSICION BONO | I92: ALCANCE DE OBJETIVOS
B93: Bono | C93: Concepto | F93: % Bono | G93: Monto | H93: Objetivo Minimo | I93: Presupuesto | J93: Real | K93: % Cobertura | L93: Bono
C94: Cumplimiento Presupuesto | F94: 1 | G94: =+F94*B94 -> 0 | H94: 0.8 | I94: =C89 -> 1660857.6 | J94: =D89 -> 1836426.5 | K94: =IFERROR(J94/I94,0) -> 1.1057098 | L94: =IF(K94<H94,0,K94*$G94) -> 0
G95: =B94*F95 -> 0 | H95: 0.8 | I95: 1 | K95: =J95/I95 -> 0 | L95: =IF(K95<H95,0,K95*$G95) -> 0
G96: =+F96*B94 -> 0 | H96: 1 | I96: 1 | K96: =IFERROR(J96/I96,0) -> 0 | L96: =IF(K96<H96,0,K96*$G96) -> 0
G97: =+F97*B94 -> 0 | H97: 1 | I97: 1 | K97: =IFERROR(J97/I97,0) -> 0 | L97: =IF(K97<H97,0,K97*$G97) -> 0
G98: =+F98*B94 -> 0 | H98: 1 | I98: 1 | K98: =IFERROR(J98/I98,0) -> 0 | L98: =IF(K98<H98,0,K98*$G98) -> 0
E99: Total | F99: =SUM(F94:F98) -> 1 | G99: =SUM(G94:G98) -> 0 | K99: Total sin Presupuesto | L99: =SUM(L95:L98) -> 0
K101: TOTAL | L101: =+L99+L94 -> 0
C105: REGION BAJIO
C107: KILOS | E107: Variacion
B108: KG | C108: Presupuesto | D108: Real | E108: KG | F108: %
B109: Importes | C109: 21857.81 | D109: 28212.25 | E109: =D109-C109 -> 6354.44 | F109: =D109/C109-1 -> 0.29071714
C110: 1321719.9 | D110: 1792760.9 | E110: =D110-C110 -> 471041.02 | F110: =D110/C110-1 -> 0.35638492
B113: COMPOSICION BONO | I113: ALCANCE DE OBJETIVOS
B114: Bono | C114: Concepto | F114: % Bono | G114: Monto | H114: Objetivo Minimo | I114: Presupuesto | J114: Real | K114: % Cobertura | L114: Bono
B115: 7000 | C115: Cumplimiento Presupuesto | F115: 0.5 | G115: =B115*F115 -> 3500 | H115: 0.95 | I115: =C110 -> 1321719.9 | J115: =D110 -> 1792760.9 | K115: =IFERROR(J115/I115,0) -> 1.3563849 | L115: =IF(K115<H115,0,K115*$G115) -> 4747.3472
C116: Aplicación de pruebas unidades de chorizo | F116: 0.2 | G116: =B115*F116 -> 1400 | H116: 0.75 | I116: 1 | K116: =IFERROR(J116/I116,0) -> 0 | L116: =IF(K116<H116,0,K116*$G116) -> 0
C117: Prospectación | F117: 0.2 | G117: =B115*F117 -> 1400 | H117: 0.75 | I117: 1 | K117: =IFERROR(J117/I117,0) -> 0 | L117: =IF(K117<H117,0,K117*$G117) -> 0
C118: Cierre de venta con productos nuevos AGR | F118: 0.1 | G118: =+F118*B115 -> 700 | H118: 0.75 | I118: 1 | K118: =IFERROR(J118/I118,0) -> 0 | L118: =IF(K118<H118,0,K118*$G118) -> 0
E119: Total | F119: =SUM(F115:F118) -> 1 | G119: =SUM(G115:G118) -> 7000 | K119: Total sin Presupuesto | L119: =SUM(L116:L118) -> 0
K121: TOTAL | L121: =+L119+L115 -> 4747.3472
O196: 3 | P196: 3.1 | Q196: =+P196-O196 -> 0.1 | R196: =+Q196/P196 -> 0.032258065
Q200: =2000*3*12 -> 72000
Q203: =2000*12 -> 24000

Sheet SEPT
C1: CALCULO DE BONOS JULIO
C3: REGION OCCIDENTE
C6: Presupuesto | D6: Real | E6: Variacion | F6: %
B7: KG | F7: =D7/C7-1 -> #DIV/0!
B8: Importes | F8: =D8/C8-1 -> #DIV/0!
B11: COMPOSICION BONO | I11: ALCANCE DE OBJETIVOS
B12: Bono | C12: Concepto | F12: % Bono | G12: Monto | H12: Objetivo Minimo | I12: Presupuesto | J12: Real | K12: % Cobertura | L12: Bono
B13: 11500 | C13: Cumplimiento Presupuesto | F13: 0.8 | G13: =B13*F13 -> 9200 | H13: 0.9 | I13: =C8 -> 0 | J13: =D8 -> 0 | K13: =IFERROR(J13/I13,0) -> 0 | L13: =IF(K13<H13,0,K13*$G13) -> 0
C14: Desplazamiento carragenina 84400 500 KG | F14: 0.1 | G14: =B$13*F$14 -> 1150 | H14: 0.7 | I14: 1 | K14: =J14/I14 -> 0 | L14: =IF(K14<H14,0,K14*$G14) -> 0
C15: Venta de nuevos productos de ingredion 500 KG | F15: 0.1 | G15: =B$13*F$14 -> 1150 | H15: 0.5 | I15: 1 | K15: =J15/I15 -> 0 | L15: =IF(K15<H15,0,K15*$G15) -> 0
G16: =B13*F16 -> 0 | I16: 1 | K16: =J16/I16 -> 0 | L16: =IF(K16<H16,0,K16*$G16) -> 0
E17: Total | F17: =SUM(F13:F16) -> 1 | G17: =SUM(G13:G16) -> 11500 | K17: Total sin Presupuesto | L17: =SUM(L14:L16) -> 0
K19: TOTAL | L19: =+L17+L13 -> 0
C23: REGION PACIFICO
C26: Presupuesto | D26: Real | E26: Variacion | F26: %
B27: KG | F27: =D27/C27-1 -> #DIV/0!
B28: Importes | F28: =D28/C28-1 -> #DIV/0!
B31: COMPOSICION BONO | I31: ALCANCE DE OBJETIVOS
B32: Bono | C32: Concepto | F32: % Bono | G32: Monto | H32: Objetivo Minimo | I32: Presupuesto | J32: Real | K32: % Cobertura | L32: Bono
B33: 10500 | C33: Cumplimiento Presupuesto | F33: 0.7 | H33: 0.8 | I33: =C28 -> 0 | J33: =D28 -> 0 | K33: =IFERROR(J33/I33,0) -> 0 | L33: =IF(K33<H33,0,K33*$G33) -> 0
C34: Cierre super chivas, Meza, Cornejo , Sasa Sonora | F34: 0.1 | H34: 0.5 | I34: 1 | K34: =IFERROR(J34/I34,0) -> 0 | L34: =IF(K34<H34,0,K34*$G34) -> 0
C35: Desplazamiento carragenina 84400 300 KG | F35: 0.1 | H35: 0.5 | I35: 1 | K35: =IFERROR(J35/I35,0) -> 0 | L35: =IF(K35<H35,0,K35*$G35) -> 0
C36: Venta de nuevos productos de ingredion 500 KG | F36: 0.1 | H36: 0 | I36: 1 | K36: =IFERROR(J36/I36,0) -> 0 | L36: =IF(K36<H36,0,K36*$G36) -> 0
H37: 0 | I37: 1 | K37: =IFERROR(J37/I37,0) -> 0 | L37: =IF(K37<H37,0,K37*$G37) -> 0
E38: Total | F38: =SUM(F33:F37) -> 1 | G38: =SUM(G32:G37) -> 0 | K38: Total sin Presupuesto | L38: =SUM(L35:L35) -> 0
K40: TOTAL | L40: =+L38+L33 -> 0
C44: ALTOS NORTE
C47: Presupuesto | D47: Real | E47: KG | F47: %
B48: KG | C48: 22853.032 | D48: 32695.299 | E48: =D48-C48 -> 9842.267 | F48: =D48/C48-1 -> 0.43067664
B49: Importes | C49: 1374179.3 | D49: 1550018.1 | E49: =D49-C49 -> 175838.82 | F49: =D49/C49-1 -> 0.12795916
B52: COMPOSICION BONO | I52: ALCANCE DE OBJETIVOS
B53: Bono | C53: Concepto | F53: % Bono | G53: Monto | H53: Objetivo Minimo | I53: Presupuesto | J53: Real | K53: % Cobertura | L53: Bono
B54: 10000 | C54: Cumplimiento Presupuesto | F54: 0.7 | G54: =+F54*B54 -> 7000 | H54: 0.9 | I54: =C49 -> 1374179.3 | J54: =D49 -> 1550018.1 | K54: =IFERROR(J54/I54,0) -> 1.1279592 | L54: =IF(K54<H54,0,K54*$G54) -> 7895.7141
C55: Visita a Morelia primeros cierres de venta | F55: 0.08 | G55: =B54*F55 -> 800 | H55: 0.8 | I55: 1 | J55: 0 | K55: 0.5 | L55: =IF(K55<H55,0,K55*$G55) -> 0
C56: Desplazamiento carragenina 84400 300 KG | F56: 0.1 | G56: =+F56*B54 -> 1000 | H56: 0.8 | I56: 1 | K56: 0.5 | L56: =IF(K56<H56,0,K56*$G56) -> 0
C57: Evaluación y plan de impulso almidones modificados nuevos | F57: 0.12 | G57: =+F57*B54 -> 1200 | H57: 1 | I57: 1 | K57: =IFERROR(J57/I57,0) -> 0 | L57: =IF(K57<H57,0,K57*$G57) -> 0
G58: =+F58*B54 -> 0 | H58: 1 | I58: 1 | K58: =IFERROR(J58/I58,0) -> 0 | L58: =IF(K58<H58,0,K58*$G58) -> 0
E59: Total | F59: =SUM(F54:F58) -> 1 | G59: =SUM(G54:G58) -> 10000 | K59: Total sin Presupuesto | L59: =SUM(L55:L58) -> 0
K61: TOTAL | L61: =+L59+L54 -> 7895.7141
C65: COORDINACION DE VENTAS
C68: Presupuesto | D68: Real | E68: KG | F68: %
B69: KG | F69: =D69/C69-1 -> #DIV/0!
B70: Importes | F70: =D70/C70-1 -> #DIV/0!
B73: COMPOSICION BONO | I73: ALCANCE DE OBJETIVOS
B74: Bono | C74: Concepto | F74: % Bono | G74: Monto | H74: Objetivo Minimo | I74: Presupuesto | J74: Real | K74: % Cobertura | L74: Bono
B75: 4000 | C75: Cumplimiento Presupuesto | F75: 0.75 | G75: =+F75*B75 -> 3000 | H75: 0.8 | I75: =C70 -> 0 | J75: =D70 -> 0 | K75: =IFERROR(J75/I75,0) -> 0 | L75: =IF(K75<H75,0,K75*$G75) -> 0
C76: Promoción de nuevos productos ( marinadores, ajo , cebolla, conservador 2020) | F76: 0.1 | G76: =+F76*B75 -> 400 | H76: 0.7
C77: Generar 50 mil pesos de venta extra | F77: 0.15 | G77: =+F77*B75 -> 600 | H77: 0.7 | I77: 1 | K77: =IFERROR(J77/I77,0) -> 0 | L77: =IF(K77<H77,0,K77*$G77) -> 0
E78: Total | F78: =SUM(F75:F77) -> 1 | G78: =SUM(G75:G77) -> 4000 | K78: Total sin Presupuesto | L78: =SUM(L77:L77) -> 0
K80: TOTAL | L80: =+L78+L75 -> 0
C84: CUENTAS CLAVE
C87: Presupuesto | D87: Real | E87: KG | F87: %
B88: KG | C88: 72301.28 | D88: 72233.24 | E88: =D88-C88 -> -68.04 | F88: =D88/C88-1 -> -0.00094106218
B89: Importes | C89: 1660857.6 | D89: 1836426.5 | E89: =D89-C89 -> 175568.96 | F89: =D89/C89-1 -> 0.10570982
B92: COMPOSICION BONO | I92: ALCANCE DE OBJETIVOS
B93: Bono | C93: Concepto | F93: % Bono | G93: Monto | H93: Objetivo Minimo | I93: Presupuesto | J93: Real | K93: % Cobertura | L93: Bono
C94: Cumplimiento Presupuesto | F94: 1 | G94: =+F94*B94 -> 0 | H94: 0.8 | I94: =C89 -> 1660857.6 | J94: =D89 -> 1836426.5 | K94: =IFERROR(J94/I94,0) -> 1.1057098 | L94: =IF(K94<H94,0,K94*$G94) -> 0
G95: =B94*F95 -> 0 | H95: 0.8 | I95: 1 | K95: =J95/I95 -> 0 | L95: =IF(K95<H95,0,K95*$G95) -> 0
G96: =+F96*B94 -> 0 | H96: 1 | I96: 1 | K96: =IFERROR(J96/I96,0) -> 0 | L96: =IF(K96<H96,0,K96*$G96) -> 0
G97: =+F97*B94 -> 0 | H97: 1 | I97: 1 | K97: =IFERROR(J97/I97,0) -> 0 | L97: =IF(K97<H97,0,K97*$G97) -> 0
G98: =+F98*B94 -> 0 | H98: 1 | I98: 1 | K98: =IFERROR(J98/I98,0) -> 0 | L98: =IF(K98<H98,0,K98*$G98) -> 0
E99: Total | F99: =SUM(F94:F98) -> 1 | G99: =SUM(G94:G98) -> 0 | K99: Total sin Presupuesto | L99: =SUM(L95:L98) -> 0
K101: TOTAL | L101: =+L99+L94 -> 0
C105: REGION BAJIO
C107: KILOS | E107: Variacion
B108: KG | C108: Presupuesto | D108: Real | E108: KG | F108: %
B109: Importes | C109: 21857.81 | D109: 28212.25 | E109: =D109-C109 -> 6354.44 | F109: =D109/C109-1 -> 0.29071714
C110: 1321719.9 | D110: 1792760.9 | E110: =D110-C110 -> 471041.02 | F110: =D110/C110-1 -> 0.35638492
B113: COMPOSICION BONO | I113: ALCANCE DE OBJETIVOS
B114: Bono | C114: Concepto | F114: % Bono | G114: Monto | H114: Objetivo Minimo | I114: Presupuesto | J114: Real | K114: % Cobertura | L114: Bono
B115: 7000 | C115: Cumplimiento Presupuesto | F115: 0.5 | G115: =B115*F115 -> 3500 | H115: 0.95 | I115: =C110 -> 1321719.9 | J115: =D110 -> 1792760.9 | K115: =IFERROR(J115/I115,0) -> 1.3563849 | L115: =IF(K115<H115,0,K115*$G115) -> 4747.3472
C116: Aplicación de pruebas unidades de chorizo | F116: 0.2 | G116: =B115*F116 -> 1400 | H116: 0.75 | I116: 1 | K116: =IFERROR(J116/I116,0) -> 0 | L116: =IF(K116<H116,0,K116*$G116) -> 0
C117: Prospectación | F117: 0.2 | G117: =B115*F117 -> 1400 | H117: 0.75 | I117: 1 | K117: =IFERROR(J117/I117,0) -> 0 | L117: =IF(K117<H117,0,K117*$G117) -> 0
C118: Cierre de venta con productos nuevos AGR | F118: 0.1 | G118: =+F118*B115 -> 700 | H118: 0.75 | I118: 1 | K118: =IFERROR(J118/I118,0) -> 0 | L118: =IF(K118<H118,0,K118*$G118) -> 0
E119: Total | F119: =SUM(F115:F118) -> 1 | G119: =SUM(G115:G118) -> 7000 | K119: Total sin Presupuesto | L119: =SUM(L116:L118) -> 0
K121: TOTAL | L121: =+L119+L115 -> 4747.3472
O196: 3 | P196: 3.1 | Q196: =+P196-O196 -> 0.1 | R196: =+Q196/P196 -> 0.032258065
Q200: =2000*3*12 -> 72000
Q203: =2000*12 -> 24000

Sheet Hoja1
A1: BONO POR RESULTADO | B1: 0
A2: BONO POR PROCESO | B2: 2500
A3: AJUSTE TRIMESTRAL | B3: 6535
A4: BONO A PAGAR MARZO | B4: =SUM(B1:B3) -> 9035

Sheet 4o TRIM
E5: Sueldo base (Fijo): | F5: 15000
E6: Bono mensual (Variable): | F6: 25000 | I6: OCTUBRE | J6: NOVIEMBRE | K6: DICIEMBRE | M6: Revisión trimestral
C9: RESULTADO: | E9: Ponderación | F9: 0.3 | H9: Meta: | I9: 1500000 | J9: 1500000 | K9: 1500000 | M9: =I9+J9+K9 -> 4500000
E10: Alcance mínimo | F10: 0.8 | H10: Resultado: | M10: =I10+J10+K10 -> 0
E11: Tope superor | F11: 2 | H11: Superávit/ déficit vs. meta | I11: =+I10-I9 -> -1500000 | J11: =+J10-J9 -> -1500000 | K11: =+K10-K9 -> -1500000 | M11: =+M10-M9 -> -4500000
E12: Bono por resultado: | F12: =F6*F9 -> 7500 | H12: Avance vs. meta | I12: =I10/I9 -> 0 | J12: =J10/J9 -> 0 | K12: =K10/K9 -> 0 | M12: =M10/M9 -> 0
E13: Margen de contribucion mayor al 35 % | H13: Candidato pago de bono | I13: =IF((I$12>=$F$10),"Ok","No") -> No | J13: =IF((J$12>=$F$10),"Ok","No") -> No | K13: =IF((K$12>=$F$10),"Ok","No") -> No | M13: =IF((M$12>$F$10),"Ok","No") -> No
H14: Validación limite superior | I14: =IF(AND(I$13="No"),"No Aplica",IF(AND(I$12<=1),"Ok",IF(AND(I$12>1),"Revisar"))) -> No Aplica | J14: =IF(AND(J$13="No"),"No Aplica",IF(AND(J$12<=1),"Ok",IF(AND(J$12>1),"Revisar"))) -> No Aplica | K14: =IF(AND(K$13="No"),"No Aplica",IF(AND(K$12<=1),"Ok",IF(AND(K$12>1),"Revisar"))) -> No Aplica | M14: =IF(AND(M$13="No"),"No Aplica",IF(AND(M$12<=1),"Ok",IF(AND(M$12>1),"Revisar"))) -> No Aplica
H15: Cálculo bono | I15: =IF(AND(I$14="No aplica"),"0",IF(AND(I$14="Ok"),(I$12*$F$12),IF(AND(I$14="Revisar"),(I$12*$F$12)))) -> 0 | J15: =IF(AND(J$14="No aplica"),"0",IF(AND(J$14="Ok"),(J$12*$F$12),IF(AND(J$14="Revisar"),(J$12*$F$12)))) -> 0 | K15: =IF(AND(K$14="No aplica"),"0",IF(AND(K$14="Ok"),(K$12*$F$12),IF(AND(K$14="Revisar"),(K$12*$F$12)))) -> 0 | M15: =IF(AND(M$14="No aplica"),"0",IF(AND(M$14="Ok"),(M$12*$F$12*3),IF(AND(M$14="Revisar"),(M$12*$F$12*3)))) -> 0
H16: Validación bono por resultado | I16: =MIN(($F$11*$F$12),(IF(AND(I$14="No aplica"),"0",IF(AND(I$14="Ok"),(I$12*$F$12),IF(AND(I$14="Revisar"),(I$12*$F$12)))))) -> 0 | J16: =MIN(($F$11*$F$12),(IF(AND(J$14="No aplica"),"0",IF(AND(J$14="Ok"),(J$12*$F$12),IF(AND(J$14="Revisar"),(J$12*$F$12)))))) -> 0 | K16: =MIN(($F$11*$F$12),(IF(AND(K$14="No aplica"),"0",IF(AND(K$14="Ok"),(K$12*$F$12),IF(AND(K$14="Revisar"),(K$12*$F$12)))))) -> 0 | M16: =MIN(($F$11*(3*$F$12)),(IF(AND(M$14="No aplica"),"0",IF(AND(M$14="Ok"),(M$12*(3*$F$12)),IF(AND(M$14="Revisar"),(M$12*(3*$F$12))))))) -> 0
H17: Bono resultados: | I17: =I16 -> 0 | J17: =J16 -> 0 | K17: =K16 -> 0 | M17: =M16 -> 0
H18: Ajuste Trimestral | M18: =M17-I17-J17-K17 -> 0
C22: PROCESO: | E22: Total | F22: 0.7 | H22: Meta Registro de proyectos clientes nuevos | I22: 15 | J22: 15 | K22: 15 | M22: =I22+J22+K22 -> 45
E23: Registro de proyectos clientes nuevos en las plataformas asignadas | F23: 0.3 | H23: Resultado Registro de proyectos clientes nuevos | M23: =I23+J23+K23 -> 0
E24: Registro de proyectos clientes actuales en las plataformas asignadas | F24: 0.3 | H24: Avance vs. meta | I24: =I23/I22 -> 0 | J24: =J23/J22 -> 0 | K24: =K23/K22 -> 0 | M24: =M23/M22 -> 0
E25: Eficiencia en cierre | F25: 0.4 | H25: Subtotal bono proceso 1/3 | I25: =$F$27*$F$23*I$24 -> 0 | J25: =$F$27*$F$23*J$24 -> 0 | K25: =$F$27*$F$23*K$24 -> 0 | M25: =SUM(I25:K25) -> 0
E26: Tope superor | F26: 2 | H26: Meta Registro de proyectos clientes actuales | I26: 15 | J26: 15 | K26: 15 | M26: =I26+J26+K26 -> 45
E27: Bono por procesos: | F27: =F22*F6 -> 17500 | H27: Resultado Registro de proyectos clientes actuales | M27: =I27+J27+K27 -> 0
E28: Meter Alcance en los procesos | H28: Avance vs. meta | I28: =I27/I26 -> 0 | J28: =J27/J26 -> 0 | K28: =K27/K26 -> 0 | M28: =M27/M26 -> 0
H29: Subtotal bono proceso 2/3 | I29: =$F$27*$F$24*I$28 -> 0 | J29: =$F$27*$F$24*J$28 -> 0 | K29: =$F$27*$F$24*K$28 -> 0 | M29: =SUM(I29:K29) -> 0
H30: Meta Eficiencia en cierre | I30: 5 | J30: 5 | K30: 5 | M30: =I30+J30+K30 -> 15
H31: Resultado Eficiencia en cierre | M31: =I31+J31+K31 -> 0
H32: Avance vs. meta | I32: =I31/I30 -> 0 | J32: =J31/J30 -> 0 | K32: =K31/K30 -> 0 | M32: =M31/M30 -> 0
H33: Subtotal bono proceso 3/3 | I33: =$F$27*$F$25*I$32 -> 0 | J33: =$F$27*$F$25*J$32 -> 0 | K33: =$F$27*$F$25*K$32 -> 0 | M33: =SUM(I33:K33) -> 0
H34: Validación bono por procesos | I34: =I25+I29+I33 -> 0 | J34: =J25+J29+J33 -> 0 | K34: =K25+K29+K33 -> 0 | L34: =L25+L29+L33 -> 0 | M34: =M25+M29+M33 -> 0
H35: Bono procesos: | I35: =MIN((($F$26*$F$27)),I34) -> 0 | J35: =MIN((($F$26*$F$27)),J34) -> 0 | K35: =MIN((($F$26*$F$27)),K34) -> 0 | M35: =MIN((($F$26*$F$27*3)),M34) -> 0
H36: Ajuste Trimestral | M36: =M35-I35-J35-K35 -> 0
C40: INTEGRACIÓN RESULTADOS | H40: Total Mensual Integrado | I40: =I17+I35 -> 0 | J40: =J17+J35 -> 0 | K40: =K17+K35 -> 0 | M40: =M17+M35 -> 0
H41: Ajuste Trimestral | M41: =M36+M18 -> 0

Sheet Bono
A1: KPI´S Comercial | B1: Ponderacion | C1: Sonia | F1: Yareli | I1: Eli | L1: Carlos
C2: Objetivo | D2: Real | E2: % Cumpl. | F2: Objetivo | G2: Real | H2: % Cumpl. | I2: Objetivo | J2: Real | K2: % Cumpl. | L2: Objetivo | M2: Real | N2: % Cumpl.
A3: Meta Ponderacion 50%) | B3: 1 | C3: 1500000 | D3: 79306 | E3: =IF(C3=0,0,MIN(D3/C3,1)) -> 0.052870667 | F3: 1500000 | G3: 427977 | H3: =IF(F3=0,0,MIN(G3/F3,1)) -> 0.285318 | I3: 150000 | J3: 28545 | K3: =IF(I3=0,0,MIN(J3/I3,1)) -> 0.1903 | L3: 150000 | M3: 16329 | N3: =IF(L3=0,0,MIN(M3/L3,1)) -> 0.10886
A4: Contactar Clientes | B4: 0.05 | C4: 20 | D4: 9 | E4: =IF(C4=0,0,MIN(D4/C4,1)) -> 0.45 | F4: 20 | G4: 0 | H4: =IF(F4=0,0,MIN(G4/F4,1)) -> 0 | I4: 20 | J4: 26 | K4: =IF(I4=0,0,MIN(J4/I4,1)) -> 1 | L4: 20 | M4: 13 | N4: =IF(L4=0,0,MIN(M4/L4,1)) -> 0.65
A5: Citas | B5: 0.05 | C5: 4 | D5: 2 | E5: =IF(C5=0,0,MIN(D5/C5,1)) -> 0.5 | F5: 4 | G5: 2 | H5: =IF(F5=0,0,MIN(G5/F5,1)) -> 0.5 | I5: 10 | J5: 10 | K5: =IF(I5=0,0,MIN(J5/I5,1)) -> 1 | L5: 10 | M5: 4 | N5: =IF(L5=0,0,MIN(M5/L5,1)) -> 0.4
A6: Proyectos Prospectos/Leads | B6: 0.2 | C6: 4 | D6: 0 | E6: =IF(C6=0,0,MIN(D6/C6,1)) -> 0 | F6: 4 | G6: 0 | H6: =IF(F6=0,0,MIN(G6/F6,1)) -> 0 | I6: 3 | J6: 2 | K6: =IF(I6=0,0,MIN(J6/I6,1)) -> 0.66666667 | L6: 3 | M6: 2 | N6: =IF(L6=0,0,MIN(M6/L6,1)) -> 0.66666667
A7: Proyectos Clientes Actuales | B7: 0.1 | C7: 8 | D7: 2 | E7: =IF(C7=0,0,MIN(D7/C7,1)) -> 0.25 | F7: 8 | G7: 5 | H7: =IF(F7=0,0,MIN(G7/F7,1)) -> 0.625 | I7: 1 | J7: 0 | K7: =IF(I7=0,0,MIN(J7/I7,1)) -> 0 | L7: 0 | M7: 0 | N7: =IF(L7=0,0,MIN(M7/L7,1)) -> 0
A8: Proyectos Ganados | B8: 0.6 | C8: 5 | D8: 0 | E8: =IF(C8=0,0,MIN(D8/C8,1)) -> 0 | F8: 5 | G8: 0 | H8: =IF(F8=0,0,MIN(G8/F8,1)) -> 0 | I8: 2 | J8: 0 | K8: =IF(I8=0,0,MIN(J8/I8,1)) -> 0 | L8: 2 | M8: 0 | N8: =IF(L8=0,0,MIN(M8/L8,1)) -> 0
A10: Total Ponderacion 50% | B10: =SUM(B4:B8) -> 1
A11: % Cumplimiento Ponderado | D11: =SUMPRODUCT($B$3:$B$8,E3:E8) -> 0.12537067 | G11: =SUMPRODUCT($B$3:$B$8,H3:H8) -> 0.372818 | J11: =SUMPRODUCT($B$3:$B$8,K3:K8) -> 0.42363333 | M11: =SUMPRODUCT($B$3:$B$8,N3:N8) -> 0.29469333
A12: Objetivo Minimo para recibir bono (%) | D12: 0.7 | G12: 0.7 | J12: 0.7 | M12: 0.7
A13: Bono Objetivo ($) | D13: 10000 | G13: 10000 | J13: 10000 | M13: 10000
A14: BONO A PAGAR x PROCESOS ($) 50% | D14: =IF(D11>=D12,D11*D13,0) -> 0 | G14: =IF(G11>=G12,G11*G13,0) -> 0 | J14: =IF(J11>=J12,J11*J13,0) -> 0 | M14: =IF(M11>=M12,M11*M13,0) -> 0
A15: BONO A PAGAR x VENTA 50% | D15: =IF(E3=100%, D14*1%, D14*0.8%) -> 0 | G15: =IF(H3=100%, G14*1%, G14*0.8%) -> 0 | J15: =IF(K3=100%, J14*1%, J14*0.8%) -> 0 | M15: =IF(N3=100%, M14*1%, M14*0.8%) -> 0
A16: TOTAL BONO | D16: =D15+D14 -> 0 | G16: =G15+G14 -> 0 | J16: =J15+J14 -> 0 | M16: =M15+M14 -> 0
A18: Nota:
A19: KPI´S Proyectos | C19: Cristina | F19: Luis | I19: Alex
A20: Proyectos | B20: 0.5 | C20: 4 | D20: 3 | E20: =IF(C20=0,0,MIN(D20/C20,1)) -> 0.75 | F20: 8 | G20: 4 | H20: =IF(F20=0,0,MIN(G20/F20,1)) -> 0.5 | I20: 6 | J20: 5 | K20: =IF(I20=0,0,MIN(J20/I20,1)) -> 0.83333333
A21: Cumplimiento de Fechas | B21: 0.3 | C21: 3 | D21: 2 | E21: =IF(C21=0,0,MIN(D21/C21,1)) -> 0.66666667 | F21: 6 | G21: 4 | H21: =IF(F21=0,0,MIN(G21/F21,1)) -> 0.66666667 | I21: 5 | J21: 5 | K21: =IF(I21=0,0,MIN(J21/I21,1)) -> 1
A22: Calidad Técnica: Precisión y la falta de errores. | B22: 0.1 | C22: 4 | D22: 2 | E22: =IF(C22=0,0,MIN(D22/C22,1)) -> 0.5 | F22: 7 | G22: 4 | H22: =IF(F22=0,0,MIN(G22/F22,1)) -> 0.57142857 | I22: 6 | J22: 5 | K22: =IF(I22=0,0,MIN(J22/I22,1)) -> 0.83333333
A23: Optimización de levantamiento: Comunicación con el cliente. | B23: 0.1 | C23: 4 | D23: 2 | E23: =IF(C23=0,0,MIN(D23/C23,1)) -> 0.5 | F23: 6 | G23: 5 | H23: =IF(F23=0,0,MIN(G23/F23,1)) -> 0.83333333 | I23: 6 | J23: 4 | K23: =IF(I23=0,0,MIN(J23/I23,1)) -> 0.66666667
A25: Total Ponderacion 100% | B25: =SUM(B20:B23) -> 1
A26: % Cumplimiento Ponderado | D26: =SUMPRODUCT($B$20:$B$23,E20:E23) -> 0.675 | G26: =SUMPRODUCT($B$20:$B$23,H20:H23) -> 0.59047619 | J26: =SUMPRODUCT($B$20:$B$23,K20:K23) -> 0.86666667
A27: Objetivo Minimo para recibir bono (%) | D27: 0.7 | G27: 0.7 | J27: 0.7
A28: Bono Objetivo ($) | D28: 35000 | G28: 3000 | J28: 5000
A29: BONO A PAGAR ($) | D29: =IF(D26>=D27,D26*D28,0) -> 0 | G29: =IF(G26>=G27,G26*G28,0) -> 0 | J29: =IF(J26>=J27,J26*J28,0) -> 4333.3333

Sheet Hoja2
A1: Cada persona ahora tiene 3 columnas por KPI en vez de 2:
A3: Objetivo y Real (las capturas, amarillo) — igual que antes.
A4: % Cumpl. (nueva, automática) = Real/Objetivo, topado a 100% para que un sobre-cumplimiento en un KPI no infle el promedio.
A6: Abajo de los 6 KPIs agregué el bloque de cálculo (columna "Real" de cada persona):
A8: Total Ponderación: suma de pesos (B3:B8), debe dar 100% — ya cuadra.
A9: % Cumplimiento Ponderado: SUMPRODUCT de peso × %cumpl de cada KPI → el score final de cada vendedor.
A10: Objetivo Mínimo para recibir bono (%): dejé 70% por default (amarillo, ajústalo).
A11: Bono Objetivo ($): en amarillo, vacío — captúralo tú por persona.
A12: BONO A PAGAR ($): si el % ponderado ≥ objetivo mínimo, paga Bono Objetivo × % cumplido; si no, $0.

Sheet Check SONIA
A1: =NOW() -> 46251.717 | M1: =COUNTIF($M$5:$M$9,"R")/COUNTA($M$5:$M$9) -> 0.75 | N1: =COUNTIF($N$5:$N$9,"R")/COUNTA($N$5:$N$9) -> 0.75 | O1: =COUNTIF($O$5:$O$9,"R")/COUNTA($O$5:$O$9) -> 0.75 | P1: =COUNTIF($P$5:$P$9,"R")/COUNTA($P$5:$P$9) -> 0.75 | Q1: =COUNTIF($Q$5:$Q$9,"R")/COUNTA($Q$5:$Q$9) -> 0.5 | R1: =COUNTIF($R$5:$R$9,"R")/COUNTA($R$5:$R$9) -> 0.25 | S1: =COUNTIF($S$5:$S$9,"R")/COUNTA($S$5:$S$9) -> 0.5 | T1: =COUNTIF($T$5:$T$9,"R")/COUNTA($T$5:$T$9) -> 0.5 | U1: =COUNTIF($U$5:$U$9,"R")/COUNTA($U$5:$U$9) -> 0.5 | V1: =COUNTIF($V$5:$V$9,"R")/COUNTA($V$5:$V$9) -> 0.25 | W1: =COUNTIF($W$5:$W$9,"R")/COUNTA($W$5:$W$9) -> 0.25
A4: Líder | B4: Nomproy | C4: Codproy | D4: Cliente | E4: Contacto | F4: Telcontacto | G4: Envdate | H4: Reqdate | I4: Obradate | J4: Presupuesto | K4: Prioridad | L4: Giro | M4: Carpeta Cuisine | N4: Sistema Alpin | O4: Volumetría | P4: Cotización | Q4: Cierre | R4: Anticipo | S4: Almacén de proyecto | T4: sG | U4: Facturación | V4: Finiquito | W4: Entrega | X4: Avance | Y4: Semáforo | Z4: Observaciones
A5: Sonia Huerta | B5: GIMNASIO PASEO DEL BOSQUE | C5: 30-2-IL | D5: ALVAREZ PINTADO DIEGO | E5: ING. MIGUEL RINCÓN | F5: 33 3662 1441 | G5: 45117 | H5: 45117 | I5: 45138 | J5: 0 | K5: Alta | L5: Iluminación | M5: £ | N5: £ | O5: £ | P5: £ | Q5: £ | R5: £ | S5: £ | T5: £ | U5: £ | V5: £ | W5: £ | X5: =COUNTIF(M5:W5,"R")/COUNTA(M5:W5) -> 0 | Y5: =Tabla33[[#This Row],[Avance]] -> 0
A6: Sonia Huerta | B6: PQ INSEL - AVANT TLJ NAVE 4 | C6: 443-3-Il | D6: PQ INSEL | G6: 45135 | H6: 45135 | I6: 45169 | L6: Iluminación | M6: R | N6: R | O6: R | P6: R | Q6: R | R6: R | S6: R | T6: R | U6: R | V6: R | W6: £ | X6: =COUNTIF(M6:W6,"R")/COUNTA(M6:W6) -> 0.90909091 | Y6: =Tabla33[[#This Row],[Avance]] -> 0.90909091
A7: Sonia Huerta | B7: Valtria Cuautitlán, Edo Mex - Almacén | C7: 89-33-Il | D7: VALTRIA ENGINEERING | G7: 45124 | H7: 45126 | I7: 45139 | L7: Iluminación | M7: R | N7: R | O7: R | P7: R | Q7: £ | R7: £ | S7: £ | T7: £ | U7: £ | V7: £ | W7: £ | X7: =COUNTIF(M7:W7,"R")/COUNTA(M7:W7) -> 0.36363636 | Y7: =Tabla33[[#This Row],[Avance]] -> 0.36363636
A8: Sonia Huerta | B8: GCPI GIMNASIO GDL | C8: 261-8-IL | D8: GRUPO CONSTRUCTOR Y PROMOTOR INDUSTRIAL | G8: 45138 | H8: 45139 | I8: 45159 | L8: Iluminación | M8: R | N8: R | O8: R | P8: R | Q8: R | R8: £ | S8: R | T8: R | U8: R | V8: £ | W8: R | X8: =COUNTIF(M8:W8,"R")/COUNTA(M8:W8) -> 0.81818182 | Y8: =Tabla33[[#This Row],[Avance]] -> 0.81818182
X9: =COUNTIF(M9:W9,"R")/COUNTA(M9:W9) -> #DIV/0! | Y9: =Tabla33[[#This Row],[Avance]] -> #DIV/0!

Sheet DICIEMBRE 
C1: CALCULO DE BONOS JULIO
C3: JULIO - REGION OCCIDENTE
C5: KILOS | E5: Variacion | G5: PESOS | I5: Variacion
B6: MES | C6: Presupuesto | D6: Real | E6: KG | F6: % | G6: Presupuesto | H6: Real | I6: $ | J6: %
B7: JULIO | C7: 196014.21 | D7: 217977.08 | E7: =D7-C7 -> 21962.874 | F7: =D7/C7-1 -> 0.11204735 | G7: 6240810.6 | H7: 6562676.8 | I7: =H7-G7 -> 321866.22 | J7: =H7/G7-1 -> 0.051574424
B9: COMPOSICION BONO | G9: ALCANCE DE OBJETIVOS
B10: Bono | C10: Concepto | D10: % Bono | E10: Monto | G10: Concepto | H10: Presupuesto | I10: Real | J10: % Cobertura | K10: Bono | M10: Objetivo Minimo
B11: 11000 | C11: Cumplimiento Presupuesto | D11: 0.78 | E11: =B11*D11 -> 8580 | G11: =C11 -> Cumplimiento Presupuesto | H11: =G7 -> 6240810.6 | I11: =H7 -> 6562676.8 | J11: =IFERROR(I11/H11,0) -> 1.0515744 | K11: =IF(J11<M11,0,J11*$E11) -> 9022.5086 | M11: 0.9
C12: Desarrollo de nuevo producto para sustituación de Ligador / presentación de resultados | D12: 0.09 | E12: =B11*D12 -> 990 | G12: =C12 -> Desarrollo de nuevo producto para sustituación de Ligador / presentación de resultados | H12: 1 | I12: 0.75 | J12: =I12/H12 -> 0.75 | K12: =IF(J12<M12,0,J12*$E12) -> 742.5 | M12: 0.75
C13: Recuperación de cartera vencida | D13: 0.13 | E13: =+D13*B11 -> 1430 | G13: Recuperación de cartera vencida | H13: 1 | I13: 0.6 | J13: =I13/H13 -> 0.6 | K13: =IF(J13<M13,0,J13*$E13) -> 858 | M13: 0.6
C14: Total | D14: =SUM(D11:D13) -> 1 | E14: =SUM(E11:E13) -> 11000 | J14: Total sin Presupuesto | K14: =SUM(K12:K13) -> 1600.5 | L14: *
J16: TOTAL | K16: =+K14+K11 -> 10623.009
G18: * 0% de recuperacion con Bonnacarne, 60% Con SASA pero 100% con La Piedad
C22: JULIO - REGION PACIFICO
C24: KILOS | E24: Variacion | G24: PESOS | I24: Variacion
C25: Presupuesto | D25: Real | E25: KG | F25: % | G25: Presupuesto | H25: Real | I25: $ | J25: %
B26: JULIO | C26: 76923.356 | D26: 77385.608 | E26: =D26-C26 -> 462.25184 | F26: =D26/C26-1 -> 0.0060092521 | G26: 4471973.1 | H26: 3708727.3 | I26: =H26-G26 -> -763245.81 | J26: =H26/G26-1 -> -0.17067317
B28: COMPOSICION BONO
B29: Bono | C29: Concepto | D29: % Bono | E29: Monto | G29: Concepto | H29: Presupuesto | I29: Real | J29: % Cobertura | K29: Bono | M29: Objetivo Minimo
B30: 10600 | C30: Cumplimiento Presupuesto | D30: 0.55 | E30: =B30*D30 -> 5830 | G30: Cumplimiento Presupuesto | H30: =G26 -> 4471973.1 | I30: =H26 -> 3708727.3 | J30: 0.82 | K30: =IF(J30<M30,0,J30*$E30) -> 4780.6 | M30: 0.82
C31: Presentación de resultados sensoriales , promoción con cliente objetivo | D31: 0.25 | E31: =B30*D31 -> 2650 | G31: Presentación de resultados sensoriales , promoción con cliente objetivo | H31: 1 | I31: 0.75 | J31: =I31/H31 -> 0.75 | K31: =IF(J31<M31,0,J31*$E31) -> 1987.5 | M31: 0.75
C32: Recuperación de cartera | D32: 0.2 | E32: =B30*D32 -> 2120 | G32: Recuperación de cartera | H32: 1 | I32: 0.84 | J32: =IFERROR(I32/H32,0) -> 0.84 | K32: =IF(J32<M32,0,J32*$E32) -> 1780.8 | M32: 0.8
C33: Total | D33: =SUM(D29:D32) -> 1 | E33: =SUM(E29:E32) -> 10600 | J33: Total sin Presupuesto | K33: =SUM(K31:K32) -> 3768.3
L34: **
J35: TOTAL | K35: =+K33+K30 -> 8548.9
G36: *84% de recuperacion con SASA, el resto de sus clientes 100% o mas | J36: Abono adeudo Marinador
J37: Total a pagar | K37: =+K35-K36 -> 8548.9
C40: JULIO - REGION BAJIO
C42: KILOS | E42: Variacion | G42: PESOS | I42: Variacion
B43: MES | C43: Presupuesto | D43: Real | E43: KG | F43: % | G43: Presupuesto | H43: Real | I43: $ | J43: %
B44: JULIO | C44: 23472.868 | D44: 28712.566 | E44: =D44-C44 -> 5239.6984 | F44: =D44/C44-1 -> 0.22322362 | G44: 1453255.3 | H44: 1620088.2 | I44: =H44-G44 -> 166832.94 | J44: =H44/G44-1 -> 0.11479947
B46: COMPOSICION BONO | G46: ALCANCE DE OBJETIVOS
B47: Bono | C47: Concepto | D47: % Bono | E47: Monto | G47: Concepto | H47: Presupuesto | I47: Real | J47: % Cobertura | K47: Bono
B48: 7000 | C48: Cumplimiento Presupuesto | D48: 0.5 | E48: =B48*D48 -> 3500 | G48: =C48 -> Cumplimiento Presupuesto | H48: =G44 -> 1453255.3 | I48: =H44 -> 1620088.2 | J48: =IFERROR(I48/H48,0) -> 1.1147995 | K48: =IF(J48<M49,0,J48*$E48) -> 3901.7981 | M48: Objetivo Minimo
C49: Aplicación de pruebas unidades de chorizo | D49: 0.2 | E49: =B48*D49 -> 1400 | G49: =C49 -> Aplicación de pruebas unidades de chorizo | H49: 1 | I49: 0.75 | J49: =IFERROR(I49/H49,0) -> 0.75 | K49: =IF(J49<M50,0,J49*$E49) -> 1050 | M49: 0.95
C50: Prospectación | D50: 0.2 | E50: =B48*D50 -> 1400 | G50: =C50 -> Prospectación | H50: 1 | I50: 0 | J50: =IFERROR(I50/H50,0) -> 0 | K50: =IF(J50<M51,0,J50*$E50) -> 0 | M50: 0.75
C51: Cierre de venta con productos nuevos AGR | D51: 0.1 | E51: =+D51*B48 -> 700 | G51: =C51 -> Cierre de venta con productos nuevos AGR | H51: 1 | I51: 1 | J51: =IFERROR(I51/H51,0) -> 1 | K51: =IF(J51<M52,0,J51*$E51) -> 700 | M51: 0.75
C52: Total | D52: =SUM(D48:D51) -> 1 | E52: =SUM(E48:E51) -> 7000 | J52: Total sin Presupuesto | K52: =SUM(K49:K51) -> 1750 | M52: 0.75
J54: TOTAL | K54: =+K52+K48 -> 5651.7981
G55: *** Sin registros de prospectos nuevos en CRM
C58: JULIO - ALTOS NORTE
C60: KILOS | E60: Variacion | G60: PESOS | I60: Variacion
B61: MES | C61: Presupuesto | D61: Real | E61: KG | F61: % | G61: Presupuesto | H61: Real | I61: $ | J61: %
B62: JULIO | C62: 103898.82 | D62: 105618.62 | E62: =D62-C62 -> 1719.7967 | F62: =D62/C62-1 -> 0.016552611 | G62: 3801156.4 | H62: 3511107 | I62: =H62-G62 -> -290049.37 | J62: =H62/G62-1 -> -0.07630556
B64: COMPOSICION BONO | G64: ALCANCE DE OBJETIVOS
B65: Bono | C65: Concepto | D65: % Bono | E65: Monto | G65: Concepto | H65: Presupuesto | I65: Real | J65: % Cobertura | K65: Bono
B66: 10000 | C66: Cumplimiento Presupuesto | D66: 0.75 | E66: =B66*D66 -> 7500 | G66: =C66 -> Cumplimiento Presupuesto | H66: =G62 -> 3801156.4 | I66: =H62 -> 3511107 | J66: =IFERROR(I66/H66,0) -> 0.92369444 | K66: =IF(J66<M67,0,J66*$E66) -> 6927.7083 | M66: Objetivo Minimo
C67: Conocimiento total de los 45 clientes de la cartera | D67: 0.1 | E67: =B66*D67 -> 1000 | G67: =C67 -> Conocimiento total de los 45 clientes de la cartera | H67: 1 | I67: 0.85 | J67: =IFERROR(I67/H67,0) -> 0.85 | K67: =IF(J67<M68,0,J67*$E67) -> 850 | M67: 0.8
C68: Desarrollo e implementacion de procedimiento de nuevos productos ( validaciones , pruebas etc) | D68: 0.08 | E68: =B66*D68 -> 800 | G68: =C68 -> Desarrollo e implementacion de procedimiento de nuevos productos ( validaciones , pruebas etc) | H68: 1 | I68: 0.75 | J68: =IFERROR(I68/H68,0) -> 0.75 | K68: =IF(J68<M69,0,J68*$E68) -> 600 | M68: 0.85
C69: Actualizacion de fichas de cliente, CRM totalmente actualizado y respetando todas las etapas del proceso. | D69: 0.07 | E69: =+D69*B66 -> 700 | G69: =C69 -> Actualizacion de fichas de cliente, CRM totalmente actualizado y respetando todas las etapas del proceso. | H69: 1 | I69: 1 | J69: =IFERROR(I69/H69,0) -> 1 | K69: =IF(J69<M70,0,J69*$E69) -> 700 | M69: 0.75
C70: Total | D70: =SUM(D66:D69) -> 1 | E70: =SUM(E66:E69) -> 10000 | J70: Total sin Presupuesto | K70: =SUM(K67:K69) -> 2150 | M70: 0.75
J72: TOTAL | K72: =+K70+K66 -> 9077.7083
N167: 3 | O167: 3.1 | P167: =+O167-N167 -> 0.1 | Q167: =+P167/O167 -> 0.032258065
P171: =2000*3*12 -> 72000
P174: =2000*12 -> 24000
